Workbook

Sheet Cuadro de mando
B2: Precios de la energía en España
B3: Informe semanal · fecha de referencia 27/10/2026 · última actualización 2026-10-27 12:07 UTC · precios con impuestos salvo los mercados mayoristas
C5: 1. OMIE · mayorista, sin impuestos | D5: 2. MIBGAS · mayorista, sin impuestos | G5: 3. Gasóleo A · con impuestos | J5: 4. PVPC 2.0TD · con impuestos
C6: 0.15221557 | D6: 0.090581429 | G6: 0.183776 | J6: 0.25507757
C7: Semana: ▼ -8,6 % | D7: Semana: ▲ +5,1 % | G7: Semana: ■ -0,0 % | J7: Semana: ▲ +1,0 %
C8: Un año: ▲ +128,5 % | D8: Un año: ▲ +189,5 % | G8: Un año: ▲ +35,2 % | J8: Un año: ▲ +39,6 %
C10: OMIE · dato del 27/10/2026 | D10: MIBGAS · dato del 26/10/2026 | G10: Comisión Europea (WOB) · dato del 19/10/2026 | J10: REE/ESIOS · dato del 27/10/2026
C12: 5. TUR 2 · con impuestos | D12: 6. Gasóleo C · con impuestos | G12: 7. Butano · con impuestos | J12: 8. Pellet saco 15 kg · con impuestos
C13: 0.070629 | D13: 0.147989 | G13: 0.118405 | J13: 0.082222
C14: Semana: ■ 0,0 % | D14: Semana: ▲ +5,3 % | G14: Semana: ■ 0,0 % | J14: Semana: ■ 0,0 %
C15: Un año: ▲ +16,5 % | D15: Un año: ▲ +74,9 % | G15: Un año: ▲ +15,8 % | J15: Un año: ▲ +11,5 %
J16: Pellet granel: 0,077 €/kWh (■ 0,0 % semana, ▲ +13,1 % año)
C17: BOE (DGPEM) · dato del 01/10/2026 | D17: Comisión Europea (WOB) · dato del 19/10/2026 | G17: BOE (DGPEM) · dato del 15/09/2026 | J17: AVEBIOM · dato del 01/07/2026
B19: Tabla de indicadores
B20: N.º | C20: Indicador | D20: Precio actual (€/kWh) | E20: Var. semanal (%) | F20: Var. interanual (%) | G20: Fecha del dato | H20: Valor original | I20: Unidad original | J20: Fuente | K20: Impuestos | L20: Estado
B21: 1 | C21: Electricidad: precio del mercado diario OMIE, España | D21: 0.15221557 | E21: -0.085609564 | F21: 1.2847546 | G21: 2026-10-27 | H21: 206.8894 | I21: €/MWh | J21: OMIE | K21: sin (mayorista) | L21: actualizado
B22: 2 | C22: Gas natural: MIBGAS-ES Index | D22: 0.090581429 | E22: 0.051316488 | F22: 1.8947681 | G22: 2026-10-26 | H22: 94.69 | I22: €/MWh | J22: MIBGAS | K22: sin (mayorista) | L22: actualizado
B23: 3 | C23: Gasóleo de automoción: precio medio en España | D23: 0.183776 | E23: -8.1614442e-05 | F23: 0.35248749 | G23: 2026-10-19 | H23: 1.88922 | I23: €/l | J23: Comisión Europea (WOB) | K23: con | L23: sin actualización en el periodo
B24: 4 | C24: Electricidad PVPC: término de energía, tarifa 2.0TD (Península) | D24: 0.25507757 | E24: 0.01020306 | F24: 0.39568821 | G24: 2026-10-27 | H24: 231.6446 | I24: €/MWh | J24: REE/ESIOS | K24: con | L24: actualizado
B25: 5 | C25: Gas natural TUR 2: término variable | D25: 0.070629 | E25: 0 | F25: 0.16537967 | G25: 2026-10-01 | H25: 5.042762 | I25: c€/kWh (PCS) | J25: BOE (DGPEM) | K25: con | L25: sin actualización en el periodo
B26: 6 | C26: Gasóleo de calefacción: precio medio en España | D26: 0.147989 | E26: 0.052605749 | F26: 0.74940303 | G26: 2026-10-19 | H26: 1.52133 | I26: €/l | J26: Comisión Europea (WOB) | K26: con | L26: sin actualización en el periodo
B27: 7 | C27: Butano: bombona regulada de 12,5 kg | D27: 0.118405 | E27: 0 | F27: 0.15797246 | G27: 2026-09-15 | H27: 123.4447 | I27: c€/kg (antes de impuestos) | J27: BOE (DGPEM) | K27: con | L27: sin actualización en el periodo
B28: 8 | C28: Pellet: precio medio en España del saco de 15 kg | D28: 0.082222 | E28: 0 | F28: 0.11487458 | G28: 2026-07-01 | H28: 5.92 | I28: €/saco | J28: AVEBIOM | K28: con | L28: sin actualización en el periodo
B29: 8 | C29: Pellet: precio medio en España a granel en volquete | D29: 0.077133 | E29: 0 | F29: 0.13091608 | G29: 2026-07-01 | H29: 370.24 | I29: €/t | J29: AVEBIOM | K29: con | L29: sin actualización en el periodo
B31: Claves de la semana (generadas a partir de los datos)
B32: • Variaciones semanales de al menos un 1 %: OMIE -8,6 %; Gasóleo C +5,3 %; MIBGAS +5,1 %; PVPC 2.0TD +1,0 %.
B33: • Sin cambios apreciables en la semana (menos de un 1 %): Gasóleo A, TUR 2, Butano, Pellet saco 15 kg, Pellet granel.
B34: • Respecto a hace un año, suben OMIE (+128,5 %), MIBGAS (+189,5 %), Gasóleo A (+35,2 %), PVPC 2.0TD (+39,6 %), TUR 2 (+16,5 %), Gasóleo C (+74,9 %), Butano (+15,8 %), Pellet saco 15 kg (+11,5 %), Pellet granel (+13,1 %).
B35: • Precio por kWh de energía final, con impuestos, de menor a mayor: TUR 2 0,071 €/kWh; Pellet granel 0,077 €/kWh; Pellet saco 15 kg 0,082 €/kWh; Butano 0,118 €/kWh; Gasóleo C 0,148 €/kWh; Gasóleo A 0,184 €/kWh; PVPC 2.0TD 0,255 €/kWh. El más caro (PVPC 2.0TD) cuesta 3,6 veces el más barato (TUR 2).
B36: • Precios mayoristas, sin impuestos: OMIE 0,1522 €/kWh; MIBGAS 0,0906 €/kWh.
B38: Criterios: precio actual = media de 7 días (OMIE, MIBGAS, PVPC), última semana (gasóleos) o valor vigente (TUR 2, butano, pellet); variaciones frente al periodo anterior y frente a hace un año; nada se estima (n. d. = no disponible).
B40: Ranking: coste por kWh de la energía final, con impuestos (de menor a mayor)
C41: Indicador | D41: €/kWh
C42: TUR 2 | D42: 0.070629
C43: Pellet granel | D43: 0.077133
C44: Pellet saco 15 kg | D44: 0.082222
C45: Butano | D45: 0.118405
C46: Gasóleo C | D46: 0.147989
C47: Gasóleo A | D47: 0.183776
C48: PVPC 2.0TD | D48: 0.25507757

Sheet Anual
A1: Año | B1: OMIE (sin imp.) | C1: MIBGAS (sin imp.) | D1: Gasóleo A | E1: PVPC 2.0TD | F1: TUR 2 | G1: Gasóleo C | H1: Butano | I1: Pellet saco 15 kg | J1: Pellet granel
A2: 2020 | B2: 0.033958917 | C2: 0.010212917 | D2: 0.1043725 | F2: 0.0575145 | G2: 0.055254917 | H2: 0.081292333 | I2: 0.060972 | J2: 0.050056
A3: 2021 | B3: 0.11139133 | C3: 0.047298667 | D3: 0.12080808 | F3: 0.05812675 | G3: 0.070687083 | H3: 0.093365583 | I3: 0.060278 | J3: 0.05134
A4: 2022 | B4: 0.1676545 | C4: 0.098655667 | D4: 0.17500292 | E4: 0.31041608 | F4: 0.07076575 | G4: 0.12557575 | H4: 0.118568 | I4: 0.090694 | J4: 0.084975
A5: 2023 | B5: 0.0874045 | C5: 0.0390675 | D5: 0.15186558 | E5: 0.15560342 | F5: 0.0588715 | G5: 0.1025375 | H5: 0.10067475 | I5: 0.08625 | J5: 0.075281
A6: 2024 | B6: 0.062893917 | C6: 0.034666 | D6: 0.14308992 | E6: 0.15014225 | F6: 0.06187425 | G6: 0.095686667 | H6: 0.100759 | I6: 0.07263925 | J6: 0.067249
A7: 2025 | B7: 0.065400167 | C7: 0.03599025 | D7: 0.13872692 | E7: 0.173742 | F7: 0.064138 | G7: 0.089194583 | H7: 0.106231 | I7: 0.0715625 | J7: 0.06549875
A8: 2026 | B8: 0.0820979 | C8: 0.0530572 | D8: 0.1636491 | E8: 0.1828093 | F8: 0.0549546 | G8: 0.1163286 | H8: 0.1043719 | I8: 0.078148 | J8: 0.074261667
A10: Media anual en €/kWh de cada serie (media de sus medias mensuales). Solo años completos; el año en curso usa los meses disponibles. Vacío = falta algún mes.

Sheet Mensual
A1: Mes | B1: OMIE (€/kWh, sin imp.) | C1: OMIE (€/MWh) | D1: MIBGAS (€/kWh, sin imp.) | E1: MIBGAS (€/MWh) | F1: Gasóleo A (€/kWh, con imp.) | G1: Gasóleo A (€/l) | H1: PVPC 2.0TD (€/kWh, con imp.) | I1: PVPC 2.0TD (€/MWh) | J1: TUR 2 (€/kWh, con imp.) | K1: TUR 2 (c€/kWh (PCS)) | L1: Gasóleo C (€/kWh, con imp.) | M1: Gasóleo C (€/l) | N1: Butano (€/kWh, con imp.) | O1: Butano (c€/kg (antes de impuestos)) | P1: Pellet saco 15 kg (€/kWh, con imp.) | Q1: Pellet saco 15 kg (€/saco) | R1: Pellet granel (€/kWh, con imp.) | S1: Pellet granel (€/t)
A2: 2020-01 | B2: 0.041101 | C2: 41.101397 | D2: 0.011879 | E2: 11.879355 | F2: 0.121196 | G2: 1.245892 | J2: 0.060353 | K2: 4.275044 | L2: 0.076468 | M2: 0.786088 | N2: 0.081509 | O2: 84.252748 | P2: 0.060972 | Q2: 4.39 | R2: 0.050056 | S2: 240.27
A3: 2020-02 | B3: 0.035869 | C3: 35.868697 | D3: 0.009817 | E3: 9.817241 | F3: 0.11745 | G3: 1.207385 | J3: 0.060353 | K3: 4.275044 | L3: 0.069908 | M3: 0.718655 | N3: 0.084047 | O3: 86.9232 | P3: 0.060972 | Q3: 4.39 | R3: 0.050056 | S3: 240.27
A4: 2020-03 | B4: 0.027729 | C4: 27.72879 | D4: 0.008563 | E4: 8.562903 | F4: 0.109557 | G4: 1.126248 | J4: 0.060353 | K4: 4.275044 | L4: 0.059326 | M4: 0.609866 | N4: 0.084047 | O4: 86.9232 | P4: 0.060972 | Q4: 4.39 | R4: 0.050056 | S4: 240.27
A5: 2020-04 | B5: 0.017653 | C5: 17.652967 | D5: 0.007482 | E5: 7.481667 | F5: 0.099217 | G5: 1.019947 | J5: 0.060353 | K5: 4.275044 | L5: 0.048452 | M5: 0.498087 | N5: 0.084047 | O5: 86.9232 | P5: 0.060972 | Q5: 4.39 | R5: 0.050056 | S5: 240.27
A6: 2020-05 | B6: 0.021255 | C6: 21.2549 | D6: 0.005331 | E6: 5.330645 | F6: 0.095941 | G6: 0.98627 | J6: 0.060353 | K6: 4.275044 | L6: 0.045096 | M6: 0.463583 | N6: 0.084047 | O6: 86.9232 | P6: 0.060972 | Q6: 4.39 | R6: 0.050056 | S6: 240.27
A7: 2020-06 | B7: 0.030618 | C7: 30.617753 | D7: 0.006426 | E7: 6.425667 | F7: 0.09917 | G7: 1.019468 | J7: 0.060353 | K7: 4.275044 | L7: 0.050138 | M7: 0.515414 | N7: 0.084047 | O7: 86.9232 | P7: 0.060972 | Q7: 4.39 | R7: 0.050056 | S7: 240.27
A8: 2020-07 | B8: 0.034636 | C8: 34.63601 | D8: 0.006435 | E8: 6.434516 | F8: 0.102768 | G8: 1.056453 | J8: 0.056262 | K8: 3.9694 | L8: 0.053658 | M8: 0.551602 | N8: 0.082581 | O8: 85.381 | P8: 0.060972 | Q8: 4.39 | R8: 0.050056 | S8: 240.27
A9: 2020-08 | B9: 0.036198 | C9: 36.198019 | D9: 0.009187 | E9: 9.186774 | F9: 0.103165 | G9: 1.060542 | J9: 0.056262 | K9: 3.9694 | L9: 0.053266 | M9: 0.54758 | N9: 0.079916 | O9: 82.577 | P9: 0.060972 | Q9: 4.39 | R9: 0.050056 | S9: 240.27
A10: 2020-09 | B10: 0.041957 | C10: 41.957077 | D10: 0.01131 | E10: 11.31 | F10: 0.101148 | G10: 1.039802 | J10: 0.056262 | K10: 3.9694 | L10: 0.05043 | M10: 0.518423 | N10: 0.077823 | O10: 80.374973 | P10: 0.060972 | Q10: 4.39 | R10: 0.050056 | S10: 240.27
A11: 2020-10 | B11: 0.03659 | C11: 36.589939 | D11: 0.013441 | E11: 13.440645 | F11: 0.100056 | G11: 1.028575 | J11: 0.05309 | K11: 3.73238 | L11: 0.050225 | M11: 0.51631 | N11: 0.075992 | O11: 78.4482 | P11: 0.060972 | Q11: 4.39 | R11: 0.050056 | S11: 240.27
A12: 2020-11 | B12: 0.041936 | C12: 41.936147 | D12: 0.0145 | E12: 14.5 | F12: 0.099839 | G12: 1.026346 | J12: 0.05309 | K12: 3.73238 | L12: 0.050907 | M12: 0.523322 | N12: 0.077732 | O12: 80.278653 | P12: 0.060972 | Q12: 4.39 | R12: 0.050056 | S12: 240.27
A13: 2020-12 | B13: 0.041965 | C13: 41.965274 | D13: 0.018184 | E13: 18.183548 | F13: 0.102963 | G13: 1.058463 | J13: 0.05309 | K13: 3.73238 | L13: 0.055185 | M13: 0.5673 | N13: 0.07972 | O13: 82.3706 | P13: 0.060972 | Q13: 4.39 | R13: 0.050056 | S13: 240.27
... A18: 2021-05 | B18: 0.067125 | C18: 67.124906 | D18: 0.024697 | E18: 24.697419 | F18: 0.117104 | G18: 1.203832 | J18: 0.057157 | K18: 4.036244 | L18: 0.066799 | M18: 0.68669 | N18: 0.089694 | O18: 92.864239 | P18: 0.060278 | Q18: 4.34 | R18: 0.05134 | S18: 246.43
A19: 2021-06 | B19: 0.0833 | C19: 83.299837 | D19: 0.028666 | E19: 28.665667 | F19: 0.12008 | G19: 1.234422 | H19: 0.186862 | I19: 149.09967 | J19: 0.057157 | K19: 4.036244 | L19: 0.069519 | M19: 0.714655 | N19: 0.092061 | O19: 95.3543 | P19: 0.060278 | Q19: 4.34 | R19: 0.05134 | S19: 246.43
A20: 2021-07 | B20: 0.092415 | C20: 92.415384 | D20: 0.036474 | E20: 36.473548 | F20: 0.122754 | G20: 1.261907 | H20: 0.182395 | I20: 157.74819 | J20: 0.059814 | K20: 4.234768 | L20: 0.071553 | M20: 0.735565 | N20: 0.093815 | O20: 97.199861 | P20: 0.060278 | Q20: 4.34 | R20: 0.05134 | S20: 246.43
A21: 2021-08 | B21: 0.105941 | C21: 105.9407 | D21: 0.044605 | E21: 44.604516 | F21: 0.123069 | G21: 1.265144 | H21: 0.20305 | I21: 175.61211 | J21: 0.059814 | K21: 4.234768 | L21: 0.071757 | M21: 0.73766 | N21: 0.096593 | O21: 100.122 | P21: 0.060278 | Q21: 4.34 | R21: 0.05134 | S21: 246.43
A22: 2021-09 | B22: 0.156144 | C22: 156.14447 | D22: 0.064683 | E22: 64.682667 | F22: 0.124203 | G22: 1.276805 | H22: 0.246414 | I22: 217.90283 | J22: 0.059814 | K22: 4.234768 | L22: 0.073308 | M22: 0.75361 | N22: 0.098179 | O22: 101.7907 | P22: 0.060278 | Q22: 4.34 | R22: 0.05134 | S22: 246.43
A23: 2021-10 | B23: 0.200057 | C23: 200.05757 | D23: 0.089705 | E23: 89.704839 | F23: 0.130744 | G23: 1.344045 | H23: 0.285797 | I23: 258.49419 | J23: 0.058379 | K23: 4.127554 | L23: 0.080606 | M23: 0.82863 | N23: 0.101351 | O23: 105.1281 | P23: 0.060278 | Q23: 4.34 | R23: 0.05134 | S23: 246.43
A24: 2021-11 | B24: 0.193431 | C24: 193.43079 | D24: 0.083105 | E24: 83.105333 | F24: 0.134418 | G24: 1.381812 | H24: 0.278164 | I24: 251.60229 | J24: 0.058379 | K24: 4.127554 | L24: 0.08317 | M24: 0.854986 | N24: 0.103849 | O24: 107.7563 | P24: 0.060278 | Q24: 4.34 | R24: 0.05134 | S24: 246.43
A25: 2021-12 | B25: 0.239165 | C25: 239.16496 | D25: 0.111953 | E25: 111.9529 | F25: 0.131186 | G25: 1.348593 | H25: 0.345275 | I25: 312.29182 | J25: 0.058379 | K25: 4.127554 | L25: 0.079591 | M25: 0.818193 | N25: 0.106347 | O25: 110.3845 | P25: 0.060278 | Q25: 4.34 | R25: 0.05134 | S25: 246.43
A26: 2022-01 | B26: 0.201718 | C26: 201.71762 | D26: 0.082843 | E26: 82.842903 | F26: 0.134506 | G26: 1.382728 | H26: 0.31603 | I26: 285.86005 | J26: 0.063634 | K26: 4.520114 | L26: 0.085248 | M26: 0.876348 | N26: 0.108716 | O26: 112.87704 | P26: 0.090694 | Q26: 6.53 | R26: 0.084975 | S26: 407.88
A27: 2022-02 | B27: 0.200219 | C27: 200.21925 | D27: 0.081255 | E27: 81.255 | F27: 0.143077 | G27: 1.470835 | H27: 0.316517 | I27: 286.30842 | J27: 0.063634 | K27: 4.520114 | L27: 0.094202 | M27: 0.968397 | N27: 0.111593 | O27: 115.9037 | P27: 0.090694 | Q27: 6.53 | R27: 0.084975 | S27: 407.88
A28: 2022-03 | B28: 0.283304 | C28: 283.30356 | D28: 0.125681 | E28: 125.68097 | F28: 0.171041 | G28: 1.758297 | H28: 0.428496 | I28: 387.60415 | J28: 0.063634 | K28: 4.520114 | L28: 0.128854 | M28: 1.324612 | N28: 0.114614 | O28: 119.08171 | P28: 0.090694 | Q28: 6.53 | R28: 0.084975 | S28: 407.88
A29: 2022-04 | B29: 0.191517 | C29: 191.51655 | D29: 0.090125 | E29: 90.125 | F29: 0.178609 | G29: 1.836103 | H29: 0.297007 | I29: 268.63353 | J29: 0.069648 | K29: 4.969479 | L29: 0.129845 | M29: 1.334803 | N29: 0.117102 | O29: 121.6989 | P29: 0.090694 | Q29: 6.53 | R29: 0.084975 | S29: 407.88
A30: 2022-05 | B30: 0.187126 | C30: 187.12602 | D30: 0.076205 | E30: 76.205161 | F30: 0.182696 | G30: 1.878118 | H30: 0.287361 | I30: 259.93356 | J30: 0.069648 | K30: 4.969479 | L30: 0.132373 | M30: 1.360798 | N30: 0.119901 | O30: 124.64321 | P30: 0.090694 | Q30: 6.53 | R30: 0.084975 | S30: 407.88
... A82: 2026-09 | B82: 0.143254 | C82: 143.25404 | D82: 0.07713 | E82: 77.129667 | F82: 0.181955 | G82: 1.870492 | H82: 0.233991 | I82: 183.97466 | J82: 0.057024 | K82: 4.119908 | L82: 0.141957 | M82: 1.45932 | N82: 0.115465 | O82: 120.70149 | P82: 0.082222 | Q82: 5.92 | R82: 0.077133 | S82: 370.24
A83: 2026-10 | B83: 0.158678 | C83: 158.67789 | D83: 0.082779 | E83: 82.779231 | F83: 0.184703 | G83: 1.898743 | H83: 0.248657 | I83: 195.50572 | J83: 0.070629 | K83: 5.042762 | L83: 0.144681 | M83: 1.487323 | N83: 0.118405 | O83: 123.4447

Sheet Gráficos
A1: Gráficos vinculados a las hojas «Mensual» y «Anual»: se actualizan si cambian los datos

Sheet Comparador
B2: Comparador de series
B3: Elija hasta cuatro series en los desplegables, la frecuencia (mensual o anual) y si quiere verlas en Base 100 (cada serie dividida por su primer valor disponible). La tabla y el gráfico se recalculan con fórmulas sobre las hojas «Mensual» y «Anual».
P4: Serie | Q4: Columna en Mensual | R4: Columna en Anual
B5: Serie 1 | C5: Gasóleo C | D5: ← desplegables (deje en blanco las series que no quiera) | P5: OMIE | Q5: OMIE (€/kWh, sin imp.) | R5: OMIE (sin imp.)
B6: Serie 2 | C6: Pellet saco 15 kg | P6: MIBGAS | Q6: MIBGAS (€/kWh, sin imp.) | R6: MIBGAS (sin imp.)
B7: Serie 3 | P7: Gasóleo A | Q7: Gasóleo A (€/kWh, con imp.) | R7: Gasóleo A
B8: Serie 4 | P8: PVPC 2.0TD | Q8: PVPC 2.0TD (€/kWh, con imp.) | R8: PVPC 2.0TD
B9: Frecuencia | C9: Mensual | P9: TUR 2 | Q9: TUR 2 (€/kWh, con imp.) | R9: TUR 2
B10: Base 100 | C10: No | P10: Gasóleo C | Q10: Gasóleo C (€/kWh, con imp.) | R10: Gasóleo C
B11: Unidad: €/kWh (OMIE y MIBGAS sin impuestos; el resto con impuestos). Los huecos (#N/A) son periodos sin dato y no se dibujan. | P11: Butano | Q11: Butano (€/kWh, con imp.) | R11: Butano
G12: Columna en la hoja origen (auxiliar) | H12: =IF($C$5="",0,IF($C$9="Anual",IFERROR(MATCH(INDEX($R$5:$R$13,MATCH($C$5,$P$5:$P$13,0)),Anual!$B$1:$J$1,0),0),IFERROR(MATCH(INDEX($Q$5:$Q$13,MATCH($C$5,$P$5:$P$13,0)),Mensual!$B$1:$S$1,0),0))) | I12: =IF($C$6="",0,IF($C$9="Anual",IFERROR(MATCH(INDEX($R$5:$R$13,MATCH($C$6,$P$5:$P$13,0)),Anual!$B$1:$J$1,0),0),IFERROR(MATCH(INDEX($Q$5:$Q$13,MATCH($C$6,$P$5:$P$13,0)),Mensual!$B$1:$S$1,0),0))) | J12: =IF($C$7="",0,IF($C$9="Anual",IFERROR(MATCH(INDEX($R$5:$R$13,MATCH($C$7,$P$5:$P$13,0)),Anual!$B$1:$J$1,0),0),IFERROR(MATCH(INDEX($Q$5:$Q$13,MATCH($C$7,$P$5:$P$13,0)),Mensual!$B$1:$S$1,0),0))) | K12: =IF($C$8="",0,IF($C$9="Anual",IFERROR(MATCH(INDEX($R$5:$R$13,MATCH($C$8,$P$5:$P$13,0)),Anual!$B$1:$J$1,0),0),IFERROR(MATCH(INDEX($Q$5:$Q$13,MATCH($C$8,$P$5:$P$13,0)),Mensual!$B$1:$S$1,0),0))) | P12: Pellet saco 15 kg | Q12: Pellet saco 15 kg (€/kWh, con imp.) | R12: Pellet saco 15 kg
G13: Primer valor disponible (auxiliar, Base 100) | H13: =IFERROR(INDEX(H15:H96,MATCH(TRUE,INDEX(ISNUMBER(H15:H96),0),0)),NA()) | I13: =IFERROR(INDEX(I15:I96,MATCH(TRUE,INDEX(ISNUMBER(I15:I96),0),0)),NA()) | J13: =IFERROR(INDEX(J15:J96,MATCH(TRUE,INDEX(ISNUMBER(J15:J96),0),0)),NA()) | K13: =IFERROR(INDEX(K15:K96,MATCH(TRUE,INDEX(ISNUMBER(K15:K96),0),0)),NA()) | P13: Pellet granel | Q13: Pellet granel (€/kWh, con imp.) | R13: Pellet granel
A14: Periodo | B14: =IF($C$5="","(vacía)",$C$5) | C14: =IF($C$6="","(vacía)",$C$6) | D14: =IF($C$7="","(vacía)",$C$7) | E14: =IF($C$8="","(vacía)",$C$8) | H14: =IF($C$5="","(vacía)",$C$5&" (€/kWh)") | I14: =IF($C$6="","(vacía)",$C$6&" (€/kWh)") | J14: =IF($C$7="","(vacía)",$C$7&" (€/kWh)") | K14: =IF($C$8="","(vacía)",$C$8&" (€/kWh)")
A15: =IF($C$9="Anual",IF(1<=7,INDEX(Anual!$A$2:$A$8,1),""),IF(1<=82,INDEX(Mensual!$A$2:$A$83,1),"")) | B15: =IF($C$10="Sí",H15/H$13*100,H15) | C15: =IF($C$10="Sí",I15/I$13*100,I15) | D15: =IF($C$10="Sí",J15/J$13*100,J15) | E15: =IF($C$10="Sí",K15/K$13*100,K15) | H15: =IF(OR($A15="",H$12=0),NA(),IF($C$9="Anual",IF(INDEX(Anual!$B$2:$J$8,1,H$12)="",NA(),INDEX(Anual!$B$2:$J$8,1,H$12)),IF(INDEX(Mensual!$B$2:$S$83,1,H$12)="",NA(),INDEX(Mensual!$B$2:$S$83,1,H$12)))) | I15: =IF(OR($A15="",I$12=0),NA(),IF($C$9="Anual",IF(INDEX(Anual!$B$2:$J$8,1,I$12)="",NA(),INDEX(Anual!$B$2:$J$8,1,I$12)),IF(INDEX(Mensual!$B$2:$S$83,1,I$12)="",NA(),INDEX(Mensual!$B$2:$S$83,1,I$12)))) | J15: =IF(OR($A15="",J$12=0),NA(),IF($C$9="Anual",IF(INDEX(Anual!$B$2:$J$8,1,J$12)="",NA(),INDEX(Anual!$B$2:$J$8,1,J$12)),IF(INDEX(Mensual!$B$2:$S$83,1,J$12)="",NA(),INDEX(Mensual!$B$2:$S$83,1,J$12)))) | K15: =IF(OR($A15="",K$12=0),NA(),IF($C$9="Anual",IF(INDEX(Anual!$B$2:$J$8,1,K$12)="",NA(),INDEX(Anual!$B$2:$J$8,1,K$12)),IF(INDEX(Mensual!$B$2:$S$83,1,K$12)="",NA(),INDEX(Mensual!$B$2:$S$83,1,K$12))))
A16: =IF($C$9="Anual",IF(2<=7,INDEX(Anual!$A$2:$A$8,2),""),IF(2<=82,INDEX(Mensual!$A$2:$A$83,2),"")) | B16: =IF($C$10="Sí",H16/H$13*100,H16) | C16: =IF($C$10="Sí",I16/I$13*100,I16) | D16: =IF($C$10="Sí",J16/J$13*100,J16) | E16: =IF($C$10="Sí",K16/K$13*100,K16) | H16: =IF(OR($A16="",H$12=0),NA(),IF($C$9="Anual",IF(INDEX(Anual!$B$2:$J$8,2,H$12)="",NA(),INDEX(Anual!$B$2:$J$8,2,H$12)),IF(INDEX(Mensual!$B$2:$S$83,2,H$12)="",NA(),INDEX(Mensual!$B$2:$S$83,2,H$12)))) | I16: =IF(OR($A16="",I$12=0),NA(),IF($C$9="Anual",IF(INDEX(Anual!$B$2:$J$8,2,I$12)="",NA(),INDEX(Anual!$B$2:$J$8,2,I$12)),IF(INDEX(Mensual!$B$2:$S$83,2,I$12)="",NA(),INDEX(Mensual!$B$2:$S$83,2,I$12)))) | J16: =IF(OR($A16="",J$12=0),NA(),IF($C$9="Anual",IF(INDEX(Anual!$B$2:$J$8,2,J$12)="",NA(),INDEX(Anual!$B$2:$J$8,2,J$12)),IF(INDEX(Mensual!$B$2:$S$83,2,J$12)="",NA(),INDEX(Mensual!$B$2:$S$83,2,J$12)))) | K16: =IF(OR($A16="",K$12=0),NA(),IF($C$9="Anual",IF(INDEX(Anual!$B$2:$J$8,2,K$12)="",NA(),INDEX(Anual!$B$2:$J$8,2,K$12)),IF(INDEX(Mensual!$B$2:$S$83,2,K$12)="",NA(),INDEX(Mensual!$B$2:$S$83,2,K$12))))
A17: =IF($C$9="Anual",IF(3<=7,INDEX(Anual!$A$2:$A$8,3),""),IF(3<=82,INDEX(Mensual!$A$2:$A$83,3),"")) | B17: =IF($C$10="Sí",H17/H$13*100,H17) | C17: =IF($C$10="Sí",I17/I$13*100,I17) | D17: =IF($C$10="Sí",J17/J$13*100,J17) | E17: =IF($C$10="Sí",K17/K$13*100,K17) | H17: =IF(OR($A17="",H$12=0),NA(),IF($C$9="Anual",IF(INDEX(Anual!$B$2:$J$8,3,H$12)="",NA(),INDEX(Anual!$B$2:$J$8,3,H$12)),IF(INDEX(Mensual!$B$2:$S$83,3,H$12)="",NA(),INDEX(Mensual!$B$2:$S$83,3,H$12)))) | I17: =IF(OR($A17="",I$12=0),NA(),IF($C$9="Anual",IF(INDEX(Anual!$B$2:$J$8,3,I$12)="",NA(),INDEX(Anual!$B$2:$J$8,3,I$12)),IF(INDEX(Mensual!$B$2:$S$83,3,I$12)="",NA(),INDEX(Mensual!$B$2:$S$83,3,I$12)))) | J17: =IF(OR($A17="",J$12=0),NA(),IF($C$9="Anual",IF(INDEX(Anual!$B$2:$J$8,3,J$12)="",NA(),INDEX(Anual!$B$2:$J$8,3,J$12)),IF(INDEX(Mensual!$B$2:$S$83,3,J$12)="",NA(),INDEX(Mensual!$B$2:$S$83,3,J$12)))) | K17: =IF(OR($A17="",K$12=0),NA(),IF($C$9="Anual",IF(INDEX(Anual!$B$2:$J$8,3,K$12)="",NA(),INDEX(Anual!$B$2:$J$8,3,K$12)),IF(INDEX(Mensual!$B$2:$S$83,3,K$12)="",NA(),INDEX(Mensual!$B$2:$S$83,3,K$12))))
A18: =IF($C$9="Anual",IF(4<=7,INDEX(Anual!$A$2:$A$8,4),""),IF(4<=82,INDEX(Mensual!$A$2:$A$83,4),"")) | B18: =IF($C$10="Sí",H18/H$13*100,H18) | C18: =IF($C$10="Sí",I18/I$13*100,I18) | D18: =IF($C$10="Sí",J18/J$13*100,J18) | E18: =IF($C$10="Sí",K18/K$13*100,K18) | H18: =IF(OR($A18="",H$12=0),NA(),IF($C$9="Anual",IF(INDEX(Anual!$B$2:$J$8,4,H$12)="",NA(),INDEX(Anual!$B$2:$J$8,4,H$12)),IF(INDEX(Mensual!$B$2:$S$83,4,H$12)="",NA(),INDEX(Mensual!$B$2:$S$83,4,H$12)))) | I18: =IF(OR($A18="",I$12=0),NA(),IF($C$9="Anual",IF(INDEX(Anual!$B$2:$J$8,4,I$12)="",NA(),INDEX(Anual!$B$2:$J$8,4,I$12)),IF(INDEX(Mensual!$B$2:$S$83,4,I$12)="",NA(),INDEX(Mensual!$B$2:$S$83,4,I$12)))) | J18: =IF(OR($A18="",J$12=0),NA(),IF($C$9="Anual",IF(INDEX(Anual!$B$2:$J$8,4,J$12)="",NA(),INDEX(Anual!$B$2:$J$8,4,J$12)),IF(INDEX(Mensual!$B$2:$S$83,4,J$12)="",NA(),INDEX(Mensual!$B$2:$S$83,4,J$12)))) | K18: =IF(OR($A18="",K$12=0),NA(),IF($C$9="Anual",IF(INDEX(Anual!$B$2:$J$8,4,K$12)="",NA(),INDEX(Anual!$B$2:$J$8,4,K$12)),IF(INDEX(Mensual!$B$2:$S$83,4,K$12)="",NA(),INDEX(Mensual!$B$2:$S$83,4,K$12))))
A19: =IF($C$9="Anual",IF(5<=7,INDEX(Anual!$A$2:$A$8,5),""),IF(5<=82,INDEX(Mensual!$A$2:$A$83,5),"")) | B19: =IF($C$10="Sí",H19/H$13*100,H19) | C19: =IF($C$10="Sí",I19/I$13*100,I19) | D19: =IF($C$10="Sí",J19/J$13*100,J19) | E19: =IF($C$10="Sí",K19/K$13*100,K19) | H19: =IF(OR($A19="",H$12=0),NA(),IF($C$9="Anual",IF(INDEX(Anual!$B$2:$J$8,5,H$12)="",NA(),INDEX(Anual!$B$2:$J$8,5,H$12)),IF(INDEX(Mensual!$B$2:$S$83,5,H$12)="",NA(),INDEX(Mensual!$B$2:$S$83,5,H$12)))) | I19: =IF(OR($A19="",I$12=0),NA(),IF($C$9="Anual",IF(INDEX(Anual!$B$2:$J$8,5,I$12)="",NA(),INDEX(Anual!$B$2:$J$8,5,I$12)),IF(INDEX(Mensual!$B$2:$S$83,5,I$12)="",NA(),INDEX(Mensual!$B$2:$S$83,5,I$12)))) | J19: =IF(OR($A19="",J$12=0),NA(),IF($C$9="Anual",IF(INDEX(Anual!$B$2:$J$8,5,J$12)="",NA(),INDEX(Anual!$B$2:$J$8,5,J$12)),IF(INDEX(Mensual!$B$2:$S$83,5,J$12)="",NA(),INDEX(Mensual!$B$2:$S$83,5,J$12)))) | K19: =IF(OR($A19="",K$12=0),NA(),IF($C$9="Anual",IF(INDEX(Anual!$B$2:$J$8,5,K$12)="",NA(),INDEX(Anual!$B$2:$J$8,5,K$12)),IF(INDEX(Mensual!$B$2:$S$83,5,K$12)="",NA(),INDEX(Mensual!$B$2:$S$83,5,K$12))))
A20: =IF($C$9="Anual",IF(6<=7,INDEX(Anual!$A$2:$A$8,6),""),IF(6<=82,INDEX(Mensual!$A$2:$A$83,6),"")) | B20: =IF($C$10="Sí",H20/H$13*100,H20) | C20: =IF($C$10="Sí",I20/I$13*100,I20) | D20: =IF($C$10="Sí",J20/J$13*100,J20) | E20: =IF($C$10="Sí",K20/K$13*100,K20) | H20: =IF(OR($A20="",H$12=0),NA(),IF($C$9="Anual",IF(INDEX(Anual!$B$2:$J$8,6,H$12)="",NA(),INDEX(Anual!$B$2:$J$8,6,H$12)),IF(INDEX(Mensual!$B$2:$S$83,6,H$12)="",NA(),INDEX(Mensual!$B$2:$S$83,6,H$12)))) | I20: =IF(OR($A20="",I$12=0),NA(),IF($C$9="Anual",IF(INDEX(Anual!$B$2:$J$8,6,I$12)="",NA(),INDEX(Anual!$B$2:$J$8,6,I$12)),IF(INDEX(Mensual!$B$2:$S$83,6,I$12)="",NA(),INDEX(Mensual!$B$2:$S$83,6,I$12)))) | J20: =IF(OR($A20="",J$12=0),NA(),IF($C$9="Anual",IF(INDEX(Anual!$B$2:$J$8,6,J$12)="",NA(),INDEX(Anual!$B$2:$J$8,6,J$12)),IF(INDEX(Mensual!$B$2:$S$83,6,J$12)="",NA(),INDEX(Mensual!$B$2:$S$83,6,J$12)))) | K20: =IF(OR($A20="",K$12=0),NA(),IF($C$9="Anual",IF(INDEX(Anual!$B$2:$J$8,6,K$12)="",NA(),INDEX(Anual!$B$2:$J$8,6,K$12)),IF(INDEX(Mensual!$B$2:$S$83,6,K$12)="",NA(),INDEX(Mensual!$B$2:$S$83,6,K$12))))
A21: =IF($C$9="Anual",IF(7<=7,INDEX(Anual!$A$2:$A$8,7),""),IF(7<=82,INDEX(Mensual!$A$2:$A$83,7),"")) | B21: =IF($C$10="Sí",H21/H$13*100,H21) | C21: =IF($C$10="Sí",I21/I$13*100,I21) | D21: =IF($C$10="Sí",J21/J$13*100,J21) | E21: =IF($C$10="Sí",K21/K$13*100,K21) | H21: =IF(OR($A21="",H$12=0),NA(),IF($C$9="Anual",IF(INDEX(Anual!$B$2:$J$8,7,H$12)="",NA(),INDEX(Anual!$B$2:$J$8,7,H$12)),IF(INDEX(Mensual!$B$2:$S$83,7,H$12)="",NA(),INDEX(Mensual!$B$2:$S$83,7,H$12)))) | I21: =IF(OR($A21="",I$12=0),NA(),IF($C$9="Anual",IF(INDEX(Anual!$B$2:$J$8,7,I$12)="",NA(),INDEX(Anual!$B$2:$J$8,7,I$12)),IF(INDEX(Mensual!$B$2:$S$83,7,I$12)="",NA(),INDEX(Mensual!$B$2:$S$83,7,I$12)))) | J21: =IF(OR($A21="",J$12=0),NA(),IF($C$9="Anual",IF(INDEX(Anual!$B$2:$J$8,7,J$12)="",NA(),INDEX(Anual!$B$2:$J$8,7,J$12)),IF(INDEX(Mensual!$B$2:$S$83,7,J$12)="",NA(),INDEX(Mensual!$B$2:$S$83,7,J$12)))) | K21: =IF(OR($A21="",K$12=0),NA(),IF($C$9="Anual",IF(INDEX(Anual!$B$2:$J$8,7,K$12)="",NA(),INDEX(Anual!$B$2:$J$8,7,K$12)),IF(INDEX(Mensual!$B$2:$S$83,7,K$12)="",NA(),INDEX(Mensual!$B$2:$S$83,7,K$12))))
A22: =IF($C$9="Anual",IF(8<=7,INDEX(Anual!$A$2:$A$8,8),""),IF(8<=82,INDEX(Mensual!$A$2:$A$83,8),"")) | B22: =IF($C$10="Sí",H22/H$13*100,H22) | C22: =IF($C$10="Sí",I22/I$13*100,I22) | D22: =IF($C$10="Sí",J22/J$13*100,J22) | E22: =IF($C$10="Sí",K22/K$13*100,K22) | H22: =IF(OR($A22="",H$12=0),NA(),IF($C$9="Anual",IF(INDEX(Anual!$B$2:$J$8,8,H$12)="",NA(),INDEX(Anual!$B$2:$J$8,8,H$12)),IF(INDEX(Mensual!$B$2:$S$83,8,H$12)="",NA(),INDEX(Mensual!$B$2:$S$83,8,H$12)))) | I22: =IF(OR($A22="",I$12=0),NA(),IF($C$9="Anual",IF(INDEX(Anual!$B$2:$J$8,8,I$12)="",NA(),INDEX(Anual!$B$2:$J$8,8,I$12)),IF(INDEX(Mensual!$B$2:$S$83,8,I$12)="",NA(),INDEX(Mensual!$B$2:$S$83,8,I$12)))) | J22: =IF(OR($A22="",J$12=0),NA(),IF($C$9="Anual",IF(INDEX(Anual!$B$2:$J$8,8,J$12)="",NA(),INDEX(Anual!$B$2:$J$8,8,J$12)),IF(INDEX(Mensual!$B$2:$S$83,8,J$12)="",NA(),INDEX(Mensual!$B$2:$S$83,8,J$12)))) | K22: =IF(OR($A22="",K$12=0),NA(),IF($C$9="Anual",IF(INDEX(Anual!$B$2:$J$8,8,K$12)="",NA(),INDEX(Anual!$B$2:$J$8,8,K$12)),IF(INDEX(Mensual!$B$2:$S$83,8,K$12)="",NA(),INDEX(Mensual!$B$2:$S$83,8,K$12))))
A23: =IF($C$9="Anual",IF(9<=7,INDEX(Anual!$A$2:$A$8,9),""),IF(9<=82,INDEX(Mensual!$A$2:$A$83,9),"")) | B23: =IF($C$10="Sí",H23/H$13*100,H23) | C23: =IF($C$10="Sí",I23/I$13*100,I23) | D23: =IF($C$10="Sí",J23/J$13*100,J23) | E23: =IF($C$10="Sí",K23/K$13*100,K23) | H23: =IF(OR($A23="",H$12=0),NA(),IF($C$9="Anual",IF(INDEX(Anual!$B$2:$J$8,9,H$12)="",NA(),INDEX(Anual!$B$2:$J$8,9,H$12)),IF(INDEX(Mensual!$B$2:$S$83,9,H$12)="",NA(),INDEX(Mensual!$B$2:$S$83,9,H$12)))) | I23: =IF(OR($A23="",I$12=0),NA(),IF($C$9="Anual",IF(INDEX(Anual!$B$2:$J$8,9,I$12)="",NA(),INDEX(Anual!$B$2:$J$8,9,I$12)),IF(INDEX(Mensual!$B$2:$S$83,9,I$12)="",NA(),INDEX(Mensual!$B$2:$S$83,9,I$12)))) | J23: =IF(OR($A23="",J$12=0),NA(),IF($C$9="Anual",IF(INDEX(Anual!$B$2:$J$8,9,J$12)="",NA(),INDEX(Anual!$B$2:$J$8,9,J$12)),IF(INDEX(Mensual!$B$2:$S$83,9,J$12)="",NA(),INDEX(Mensual!$B$2:$S$83,9,J$12)))) | K23: =IF(OR($A23="",K$12=0),NA(),IF($C$9="Anual",IF(INDEX(Anual!$B$2:$J$8,9,K$12)="",NA(),INDEX(Anual!$B$2:$J$8,9,K$12)),IF(INDEX(Mensual!$B$2:$S$83,9,K$12)="",NA(),INDEX(Mensual!$B$2:$S$83,9,K$12))))
A24: =IF($C$9="Anual",IF(10<=7,INDEX(Anual!$A$2:$A$8,10),""),IF(10<=82,INDEX(Mensual!$A$2:$A$83,10),"")) | B24: =IF($C$10="Sí",H24/H$13*100,H24) | C24: =IF($C$10="Sí",I24/I$13*100,I24) | D24: =IF($C$10="Sí",J24/J$13*100,J24) | E24: =IF($C$10="Sí",K24/K$13*100,K24) | H24: =IF(OR($A24="",H$12=0),NA(),IF($C$9="Anual",IF(INDEX(Anual!$B$2:$J$8,10,H$12)="",NA(),INDEX(Anual!$B$2:$J$8,10,H$12)),IF(INDEX(Mensual!$B$2:$S$83,10,H$12)="",NA(),INDEX(Mensual!$B$2:$S$83,10,H$12)))) | I24: =IF(OR($A24="",I$12=0),NA(),IF($C$9="Anual",IF(INDEX(Anual!$B$2:$J$8,10,I$12)="",NA(),INDEX(Anual!$B$2:$J$8,10,I$12)),IF(INDEX(Mensual!$B$2:$S$83,10,I$12)="",NA(),INDEX(Mensual!$B$2:$S$83,10,I$12)))) | J24: =IF(OR($A24="",J$12=0),NA(),IF($C$9="Anual",IF(INDEX(Anual!$B$2:$J$8,10,J$12)="",NA(),INDEX(Anual!$B$2:$J$8,10,J$12)),IF(INDEX(Mensual!$B$2:$S$83,10,J$12)="",NA(),INDEX(Mensual!$B$2:$S$83,10,J$12)))) | K24: =IF(OR($A24="",K$12=0),NA(),IF($C$9="Anual",IF(INDEX(Anual!$B$2:$J$8,10,K$12)="",NA(),INDEX(Anual!$B$2:$J$8,10,K$12)),IF(INDEX(Mensual!$B$2:$S$83,10,K$12)="",NA(),INDEX(Mensual!$B$2:$S$83,10,K$12))))
A25: =IF($C$9="Anual",IF(11<=7,INDEX(Anual!$A$2:$A$8,11),""),IF(11<=82,INDEX(Mensual!$A$2:$A$83,11),"")) | B25: =IF($C$10="Sí",H25/H$13*100,H25) | C25: =IF($C$10="Sí",I25/I$13*100,I25) | D25: =IF($C$10="Sí",J25/J$13*100,J25) | E25: =IF($C$10="Sí",K25/K$13*100,K25) | H25: =IF(OR($A25="",H$12=0),NA(),IF($C$9="Anual",IF(INDEX(Anual!$B$2:$J$8,11,H$12)="",NA(),INDEX(Anual!$B$2:$J$8,11,H$12)),IF(INDEX(Mensual!$B$2:$S$83,11,H$12)="",NA(),INDEX(Mensual!$B$2:$S$83,11,H$12)))) | I25: =IF(OR($A25="",I$12=0),NA(),IF($C$9="Anual",IF(INDEX(Anual!$B$2:$J$8,11,I$12)="",NA(),INDEX(Anual!$B$2:$J$8,11,I$12)),IF(INDEX(Mensual!$B$2:$S$83,11,I$12)="",NA(),INDEX(Mensual!$B$2:$S$83,11,I$12)))) | J25: =IF(OR($A25="",J$12=0),NA(),IF($C$9="Anual",IF(INDEX(Anual!$B$2:$J$8,11,J$12)="",NA(),INDEX(Anual!$B$2:$J$8,11,J$12)),IF(INDEX(Mensual!$B$2:$S$83,11,J$12)="",NA(),INDEX(Mensual!$B$2:$S$83,11,J$12)))) | K25: =IF(OR($A25="",K$12=0),NA(),IF($C$9="Anual",IF(INDEX(Anual!$B$2:$J$8,11,K$12)="",NA(),INDEX(Anual!$B$2:$J$8,11,K$12)),IF(INDEX(Mensual!$B$2:$S$83,11,K$12)="",NA(),INDEX(Mensual!$B$2:$S$83,11,K$12))))
A26: =IF($C$9="Anual",IF(12<=7,INDEX(Anual!$A$2:$A$8,12),""),IF(12<=82,INDEX(Mensual!$A$2:$A$83,12),"")) | B26: =IF($C$10="Sí",H26/H$13*100,H26) | C26: =IF($C$10="Sí",I26/I$13*100,I26) | D26: =IF($C$10="Sí",J26/J$13*100,J26) | E26: =IF($C$10="Sí",K26/K$13*100,K26) | H26: =IF(OR($A26="",H$12=0),NA(),IF($C$9="Anual",IF(INDEX(Anual!$B$2:$J$8,12,H$12)="",NA(),INDEX(Anual!$B$2:$J$8,12,H$12)),IF(INDEX(Mensual!$B$2:$S$83,12,H$12)="",NA(),INDEX(Mensual!$B$2:$S$83,12,H$12)))) | I26: =IF(OR($A26="",I$12=0),NA(),IF($C$9="Anual",IF(INDEX(Anual!$B$2:$J$8,12,I$12)="",NA(),INDEX(Anual!$B$2:$J$8,12,I$12)),IF(INDEX(Mensual!$B$2:$S$83,12,I$12)="",NA(),INDEX(Mensual!$B$2:$S$83,12,I$12)))) | J26: =IF(OR($A26="",J$12=0),NA(),IF($C$9="Anual",IF(INDEX(Anual!$B$2:$J$8,12,J$12)="",NA(),INDEX(Anual!$B$2:$J$8,12,J$12)),IF(INDEX(Mensual!$B$2:$S$83,12,J$12)="",NA(),INDEX(Mensual!$B$2:$S$83,12,J$12)))) | K26: =IF(OR($A26="",K$12=0),NA(),IF($C$9="Anual",IF(INDEX(Anual!$B$2:$J$8,12,K$12)="",NA(),INDEX(Anual!$B$2:$J$8,12,K$12)),IF(INDEX(Mensual!$B$2:$S$83,12,K$12)="",NA(),INDEX(Mensual!$B$2:$S$83,12,K$12))))
A27: =IF($C$9="Anual",IF(13<=7,INDEX(Anual!$A$2:$A$8,13),""),IF(13<=82,INDEX(Mensual!$A$2:$A$83,13),"")) | B27: =IF($C$10="Sí",H27/H$13*100,H27) | C27: =IF($C$10="Sí",I27/I$13*100,I27) | D27: =IF($C$10="Sí",J27/J$13*100,J27) | E27: =IF($C$10="Sí",K27/K$13*100,K27) | H27: =IF(OR($A27="",H$12=0),NA(),IF($C$9="Anual",IF(INDEX(Anual!$B$2:$J$8,13,H$12)="",NA(),INDEX(Anual!$B$2:$J$8,13,H$12)),IF(INDEX(Mensual!$B$2:$S$83,13,H$12)="",NA(),INDEX(Mensual!$B$2:$S$83,13,H$12)))) | I27: =IF(OR($A27="",I$12=0),NA(),IF($C$9="Anual",IF(INDEX(Anual!$B$2:$J$8,13,I$12)="",NA(),INDEX(Anual!$B$2:$J$8,13,I$12)),IF(INDEX(Mensual!$B$2:$S$83,13,I$12)="",NA(),INDEX(Mensual!$B$2:$S$83,13,I$12)))) | J27: =IF(OR($A27="",J$12=0),NA(),IF($C$9="Anual",IF(INDEX(Anual!$B$2:$J$8,13,J$12)="",NA(),INDEX(Anual!$B$2:$J$8,13,J$12)),IF(INDEX(Mensual!$B$2:$S$83,13,J$12)="",NA(),INDEX(Mensual!$B$2:$S$83,13,J$12)))) | K27: =IF(OR($A27="",K$12=0),NA(),IF($C$9="Anual",IF(INDEX(Anual!$B$2:$J$8,13,K$12)="",NA(),INDEX(Anual!$B$2:$J$8,13,K$12)),IF(INDEX(Mensual!$B$2:$S$83,13,K$12)="",NA(),INDEX(Mensual!$B$2:$S$83,13,K$12))))
A28: =IF($C$9="Anual",IF(14<=7,INDEX(Anual!$A$2:$A$8,14),""),IF(14<=82,INDEX(Mensual!$A$2:$A$83,14),"")) | B28: =IF($C$10="Sí",H28/H$13*100,H28) | C28: =IF($C$10="Sí",I28/I$13*100,I28) | D28: =IF($C$10="Sí",J28/J$13*100,J28) | E28: =IF($C$10="Sí",K28/K$13*100,K28) | H28: =IF(OR($A28="",H$12=0),NA(),IF($C$9="Anual",IF(INDEX(Anual!$B$2:$J$8,14,H$12)="",NA(),INDEX(Anual!$B$2:$J$8,14,H$12)),IF(INDEX(Mensual!$B$2:$S$83,14,H$12)="",NA(),INDEX(Mensual!$B$2:$S$83,14,H$12)))) | I28: =IF(OR($A28="",I$12=0),NA(),IF($C$9="Anual",IF(INDEX(Anual!$B$2:$J$8,14,I$12)="",NA(),INDEX(Anual!$B$2:$J$8,14,I$12)),IF(INDEX(Mensual!$B$2:$S$83,14,I$12)="",NA(),INDEX(Mensual!$B$2:$S$83,14,I$12)))) | J28: =IF(OR($A28="",J$12=0),NA(),IF($C$9="Anual",IF(INDEX(Anual!$B$2:$J$8,14,J$12)="",NA(),INDEX(Anual!$B$2:$J$8,14,J$12)),IF(INDEX(Mensual!$B$2:$S$83,14,J$12)="",NA(),INDEX(Mensual!$B$2:$S$83,14,J$12)))) | K28: =IF(OR($A28="",K$12=0),NA(),IF($C$9="Anual",IF(INDEX(Anual!$B$2:$J$8,14,K$12)="",NA(),INDEX(Anual!$B$2:$J$8,14,K$12)),IF(INDEX(Mensual!$B$2:$S$83,14,K$12)="",NA(),INDEX(Mensual!$B$2:$S$83,14,K$12))))
A29: =IF($C$9="Anual",IF(15<=7,INDEX(Anual!$A$2:$A$8,15),""),IF(15<=82,INDEX(Mensual!$A$2:$A$83,15),"")) | B29: =IF($C$10="Sí",H29/H$13*100,H29) | C29: =IF($C$10="Sí",I29/I$13*100,I29) | D29: =IF($C$10="Sí",J29/J$13*100,J29) | E29: =IF($C$10="Sí",K29/K$13*100,K29) | H29: =IF(OR($A29="",H$12=0),NA(),IF($C$9="Anual",IF(INDEX(Anual!$B$2:$J$8,15,H$12)="",NA(),INDEX(Anual!$B$2:$J$8,15,H$12)),IF(INDEX(Mensual!$B$2:$S$83,15,H$12)="",NA(),INDEX(Mensual!$B$2:$S$83,15,H$12)))) | I29: =IF(OR($A29="",I$12=0),NA(),IF($C$9="Anual",IF(INDEX(Anual!$B$2:$J$8,15,I$12)="",NA(),INDEX(Anual!$B$2:$J$8,15,I$12)),IF(INDEX(Mensual!$B$2:$S$83,15,I$12)="",NA(),INDEX(Mensual!$B$2:$S$83,15,I$12)))) | J29: =IF(OR($A29="",J$12=0),NA(),IF($C$9="Anual",IF(INDEX(Anual!$B$2:$J$8,15,J$12)="",NA(),INDEX(Anual!$B$2:$J$8,15,J$12)),IF(INDEX(Mensual!$B$2:$S$83,15,J$12)="",NA(),INDEX(Mensual!$B$2:$S$83,15,J$12)))) | K29: =IF(OR($A29="",K$12=0),NA(),IF($C$9="Anual",IF(INDEX(Anual!$B$2:$J$8,15,K$12)="",NA(),INDEX(Anual!$B$2:$J$8,15,K$12)),IF(INDEX(Mensual!$B$2:$S$83,15,K$12)="",NA(),INDEX(Mensual!$B$2:$S$83,15,K$12))))
A30: =IF($C$9="Anual",IF(16<=7,INDEX(Anual!$A$2:$A$8,16),""),IF(16<=82,INDEX(Mensual!$A$2:$A$83,16),"")) | B30: =IF($C$10="Sí",H30/H$13*100,H30) | C30: =IF($C$10="Sí",I30/I$13*100,I30) | D30: =IF($C$10="Sí",J30/J$13*100,J30) | E30: =IF($C$10="Sí",K30/K$13*100,K30) | H30: =IF(OR($A30="",H$12=0),NA(),IF($C$9="Anual",IF(INDEX(Anual!$B$2:$J$8,16,H$12)="",NA(),INDEX(Anual!$B$2:$J$8,16,H$12)),IF(INDEX(Mensual!$B$2:$S$83,16,H$12)="",NA(),INDEX(Mensual!$B$2:$S$83,16,H$12)))) | I30: =IF(OR($A30="",I$12=0),NA(),IF($C$9="Anual",IF(INDEX(Anual!$B$2:$J$8,16,I$12)="",NA(),INDEX(Anual!$B$2:$J$8,16,I$12)),IF(INDEX(Mensual!$B$2:$S$83,16,I$12)="",NA(),INDEX(Mensual!$B$2:$S$83,16,I$12)))) | J30: =IF(OR($A30="",J$12=0),NA(),IF($C$9="Anual",IF(INDEX(Anual!$B$2:$J$8,16,J$12)="",NA(),INDEX(Anual!$B$2:$J$8,16,J$12)),IF(INDEX(Mensual!$B$2:$S$83,16,J$12)="",NA(),INDEX(Mensual!$B$2:$S$83,16,J$12)))) | K30: =IF(OR($A30="",K$12=0),NA(),IF($C$9="Anual",IF(INDEX(Anual!$B$2:$J$8,16,K$12)="",NA(),INDEX(Anual!$B$2:$J$8,16,K$12)),IF(INDEX(Mensual!$B$2:$S$83,16,K$12)="",NA(),INDEX(Mensual!$B$2:$S$83,16,K$12))))
A31: =IF($C$9="Anual",IF(17<=7,INDEX(Anual!$A$2:$A$8,17),""),IF(17<=82,INDEX(Mensual!$A$2:$A$83,17),"")) | B31: =IF($C$10="Sí",H31/H$13*100,H31) | C31: =IF($C$10="Sí",I31/I$13*100,I31) | D31: =IF($C$10="Sí",J31/J$13*100,J31) | E31: =IF($C$10="Sí",K31/K$13*100,K31) | H31: =IF(OR($A31="",H$12=0),NA(),IF($C$9="Anual",IF(INDEX(Anual!$B$2:$J$8,17,H$12)="",NA(),INDEX(Anual!$B$2:$J$8,17,H$12)),IF(INDEX(Mensual!$B$2:$S$83,17,H$12)="",NA(),INDEX(Mensual!$B$2:$S$83,17,H$12)))) | I31: =IF(OR($A31="",I$12=0),NA(),IF($C$9="Anual",IF(INDEX(Anual!$B$2:$J$8,17,I$12)="",NA(),INDEX(Anual!$B$2:$J$8,17,I$12)),IF(INDEX(Mensual!$B$2:$S$83,17,I$12)="",NA(),INDEX(Mensual!$B$2:$S$83,17,I$12)))) | J31: =IF(OR($A31="",J$12=0),NA(),IF($C$9="Anual",IF(INDEX(Anual!$B$2:$J$8,17,J$12)="",NA(),INDEX(Anual!$B$2:$J$8,17,J$12)),IF(INDEX(Mensual!$B$2:$S$83,17,J$12)="",NA(),INDEX(Mensual!$B$2:$S$83,17,J$12)))) | K31: =IF(OR($A31="",K$12=0),NA(),IF($C$9="Anual",IF(INDEX(Anual!$B$2:$J$8,17,K$12)="",NA(),INDEX(Anual!$B$2:$J$8,17,K$12)),IF(INDEX(Mensual!$B$2:$S$83,17,K$12)="",NA(),INDEX(Mensual!$B$2:$S$83,17,K$12))))
A32: =IF($C$9="Anual",IF(18<=7,INDEX(Anual!$A$2:$A$8,18),""),IF(18<=82,INDEX(Mensual!$A$2:$A$83,18),"")) | B32: =IF($C$10="Sí",H32/H$13*100,H32) | C32: =IF($C$10="Sí",I32/I$13*100,I32) | D32: =IF($C$10="Sí",J32/J$13*100,J32) | E32: =IF($C$10="Sí",K32/K$13*100,K32) | H32: =IF(OR($A32="",H$12=0),NA(),IF($C$9="Anual",IF(INDEX(Anual!$B$2:$J$8,18,H$12)="",NA(),INDEX(Anual!$B$2:$J$8,18,H$12)),IF(INDEX(Mensual!$B$2:$S$83,18,H$12)="",NA(),INDEX(Mensual!$B$2:$S$83,18,H$12)))) | I32: =IF(OR($A32="",I$12=0),NA(),IF($C$9="Anual",IF(INDEX(Anual!$B$2:$J$8,18,I$12)="",NA(),INDEX(Anual!$B$2:$J$8,18,I$12)),IF(INDEX(Mensual!$B$2:$S$83,18,I$12)="",NA(),INDEX(Mensual!$B$2:$S$83,18,I$12)))) | J32: =IF(OR($A32="",J$12=0),NA(),IF($C$9="Anual",IF(INDEX(Anual!$B$2:$J$8,18,J$12)="",NA(),INDEX(Anual!$B$2:$J$8,18,J$12)),IF(INDEX(Mensual!$B$2:$S$83,18,J$12)="",NA(),INDEX(Mensual!$B$2:$S$83,18,J$12)))) | K32: =IF(OR($A32="",K$12=0),NA(),IF($C$9="Anual",IF(INDEX(Anual!$B$2:$J$8,18,K$12)="",NA(),INDEX(Anual!$B$2:$J$8,18,K$12)),IF(INDEX(Mensual!$B$2:$S$83,18,K$12)="",NA(),INDEX(Mensual!$B$2:$S$83,18,K$12))))
A33: =IF($C$9="Anual",IF(19<=7,INDEX(Anual!$A$2:$A$8,19),""),IF(19<=82,INDEX(Mensual!$A$2:$A$83,19),"")) | B33: =IF($C$10="Sí",H33/H$13*100,H33) | C33: =IF($C$10="Sí",I33/I$13*100,I33) | D33: =IF($C$10="Sí",J33/J$13*100,J33) | E33: =IF($C$10="Sí",K33/K$13*100,K33) | H33: =IF(OR($A33="",H$12=0),NA(),IF($C$9="Anual",IF(INDEX(Anual!$B$2:$J$8,19,H$12)="",NA(),INDEX(Anual!$B$2:$J$8,19,H$12)),IF(INDEX(Mensual!$B$2:$S$83,19,H$12)="",NA(),INDEX(Mensual!$B$2:$S$83,19,H$12)))) | I33: =IF(OR($A33="",I$12=0),NA(),IF($C$9="Anual",IF(INDEX(Anual!$B$2:$J$8,19,I$12)="",NA(),INDEX(Anual!$B$2:$J$8,19,I$12)),IF(INDEX(Mensual!$B$2:$S$83,19,I$12)="",NA(),INDEX(Mensual!$B$2:$S$83,19,I$12)))) | J33: =IF(OR($A33="",J$12=0),NA(),IF($C$9="Anual",IF(INDEX(Anual!$B$2:$J$8,19,J$12)="",NA(),INDEX(Anual!$B$2:$J$8,19,J$12)),IF(INDEX(Mensual!$B$2:$S$83,19,J$12)="",NA(),INDEX(Mensual!$B$2:$S$83,19,J$12)))) | K33: =IF(OR($A33="",K$12=0),NA(),IF($C$9="Anual",IF(INDEX(Anual!$B$2:$J$8,19,K$12)="",NA(),INDEX(Anual!$B$2:$J$8,19,K$12)),IF(INDEX(Mensual!$B$2:$S$83,19,K$12)="",NA(),INDEX(Mensual!$B$2:$S$83,19,K$12))))
A34: =IF($C$9="Anual",IF(20<=7,INDEX(Anual!$A$2:$A$8,20),""),IF(20<=82,INDEX(Mensual!$A$2:$A$83,20),"")) | B34: =IF($C$10="Sí",H34/H$13*100,H34) | C34: =IF($C$10="Sí",I34/I$13*100,I34) | D34: =IF($C$10="Sí",J34/J$13*100,J34) | E34: =IF($C$10="Sí",K34/K$13*100,K34) | H34: =IF(OR($A34="",H$12=0),NA(),IF($C$9="Anual",IF(INDEX(Anual!$B$2:$J$8,20,H$12)="",NA(),INDEX(Anual!$B$2:$J$8,20,H$12)),IF(INDEX(Mensual!$B$2:$S$83,20,H$12)="",NA(),INDEX(Mensual!$B$2:$S$83,20,H$12)))) | I34: =IF(OR($A34="",I$12=0),NA(),IF($C$9="Anual",IF(INDEX(Anual!$B$2:$J$8,20,I$12)="",NA(),INDEX(Anual!$B$2:$J$8,20,I$12)),IF(INDEX(Mensual!$B$2:$S$83,20,I$12)="",NA(),INDEX(Mensual!$B$2:$S$83,20,I$12)))) | J34: =IF(OR($A34="",J$12=0),NA(),IF($C$9="Anual",IF(INDEX(Anual!$B$2:$J$8,20,J$12)="",NA(),INDEX(Anual!$B$2:$J$8,20,J$12)),IF(INDEX(Mensual!$B$2:$S$83,20,J$12)="",NA(),INDEX(Mensual!$B$2:$S$83,20,J$12)))) | K34: =IF(OR($A34="",K$12=0),NA(),IF($C$9="Anual",IF(INDEX(Anual!$B$2:$J$8,20,K$12)="",NA(),INDEX(Anual!$B$2:$J$8,20,K$12)),IF(INDEX(Mensual!$B$2:$S$83,20,K$12)="",NA(),INDEX(Mensual!$B$2:$S$83,20,K$12))))
A35: =IF($C$9="Anual",IF(21<=7,INDEX(Anual!$A$2:$A$8,21),""),IF(21<=82,INDEX(Mensual!$A$2:$A$83,21),"")) | B35: =IF($C$10="Sí",H35/H$13*100,H35) | C35: =IF($C$10="Sí",I35/I$13*100,I35) | D35: =IF($C$10="Sí",J35/J$13*100,J35) | E35: =IF($C$10="Sí",K35/K$13*100,K35) | H35: =IF(OR($A35="",H$12=0),NA(),IF($C$9="Anual",IF(INDEX(Anual!$B$2:$J$8,21,H$12)="",NA(),INDEX(Anual!$B$2:$J$8,21,H$12)),IF(INDEX(Mensual!$B$2:$S$83,21,H$12)="",NA(),INDEX(Mensual!$B$2:$S$83,21,H$12)))) | I35: =IF(OR($A35="",I$12=0),NA(),IF($C$9="Anual",IF(INDEX(Anual!$B$2:$J$8,21,I$12)="",NA(),INDEX(Anual!$B$2:$J$8,21,I$12)),IF(INDEX(Mensual!$B$2:$S$83,21,I$12)="",NA(),INDEX(Mensual!$B$2:$S$83,21,I$12)))) | J35: =IF(OR($A35="",J$12=0),NA(),IF($C$9="Anual",IF(INDEX(Anual!$B$2:$J$8,21,J$12)="",NA(),INDEX(Anual!$B$2:$J$8,21,J$12)),IF(INDEX(Mensual!$B$2:$S$83,21,J$12)="",NA(),INDEX(Mensual!$B$2:$S$83,21,J$12)))) | K35: =IF(OR($A35="",K$12=0),NA(),IF($C$9="Anual",IF(INDEX(Anual!$B$2:$J$8,21,K$12)="",NA(),INDEX(Anual!$B$2:$J$8,21,K$12)),IF(INDEX(Mensual!$B$2:$S$83,21,K$12)="",NA(),INDEX(Mensual!$B$2:$S$83,21,K$12))))
A36: =IF($C$9="Anual",IF(22<=7,INDEX(Anual!$A$2:$A$8,22),""),IF(22<=82,INDEX(Mensual!$A$2:$A$83,22),"")) | B36: =IF($C$10="Sí",H36/H$13*100,H36) | C36: =IF($C$10="Sí",I36/I$13*100,I36) | D36: =IF($C$10="Sí",J36/J$13*100,J36) | E36: =IF($C$10="Sí",K36/K$13*100,K36) | H36: =IF(OR($A36="",H$12=0),NA(),IF($C$9="Anual",IF(INDEX(Anual!$B$2:$J$8,22,H$12)="",NA(),INDEX(Anual!$B$2:$J$8,22,H$12)),IF(INDEX(Mensual!$B$2:$S$83,22,H$12)="",NA(),INDEX(Mensual!$B$2:$S$83,22,H$12)))) | I36: =IF(OR($A36="",I$12=0),NA(),IF($C$9="Anual",IF(INDEX(Anual!$B$2:$J$8,22,I$12)="",NA(),INDEX(Anual!$B$2:$J$8,22,I$12)),IF(INDEX(Mensual!$B$2:$S$83,22,I$12)="",NA(),INDEX(Mensual!$B$2:$S$83,22,I$12)))) | J36: =IF(OR($A36="",J$12=0),NA(),IF($C$9="Anual",IF(INDEX(Anual!$B$2:$J$8,22,J$12)="",NA(),INDEX(Anual!$B$2:$J$8,22,J$12)),IF(INDEX(Mensual!$B$2:$S$83,22,J$12)="",NA(),INDEX(Mensual!$B$2:$S$83,22,J$12)))) | K36: =IF(OR($A36="",K$12=0),NA(),IF($C$9="Anual",IF(INDEX(Anual!$B$2:$J$8,22,K$12)="",NA(),INDEX(Anual!$B$2:$J$8,22,K$12)),IF(INDEX(Mensual!$B$2:$S$83,22,K$12)="",NA(),INDEX(Mensual!$B$2:$S$83,22,K$12))))
A37: =IF($C$9="Anual",IF(23<=7,INDEX(Anual!$A$2:$A$8,23),""),IF(23<=82,INDEX(Mensual!$A$2:$A$83,23),"")) | B37: =IF($C$10="Sí",H37/H$13*100,H37) | C37: =IF($C$10="Sí",I37/I$13*100,I37) | D37: =IF($C$10="Sí",J37/J$13*100,J37) | E37: =IF($C$10="Sí",K37/K$13*100,K37) | H37: =IF(OR($A37="",H$12=0),NA(),IF($C$9="Anual",IF(INDEX(Anual!$B$2:$J$8,23,H$12)="",NA(),INDEX(Anual!$B$2:$J$8,23,H$12)),IF(INDEX(Mensual!$B$2:$S$83,23,H$12)="",NA(),INDEX(Mensual!$B$2:$S$83,23,H$12)))) | I37: =IF(OR($A37="",I$12=0),NA(),IF($C$9="Anual",IF(INDEX(Anual!$B$2:$J$8,23,I$12)="",NA(),INDEX(Anual!$B$2:$J$8,23,I$12)),IF(INDEX(Mensual!$B$2:$S$83,23,I$12)="",NA(),INDEX(Mensual!$B$2:$S$83,23,I$12)))) | J37: =IF(OR($A37="",J$12=0),NA(),IF($C$9="Anual",IF(INDEX(Anual!$B$2:$J$8,23,J$12)="",NA(),INDEX(Anual!$B$2:$J$8,23,J$12)),IF(INDEX(Mensual!$B$2:$S$83,23,J$12)="",NA(),INDEX(Mensual!$B$2:$S$83,23,J$12)))) | K37: =IF(OR($A37="",K$12=0),NA(),IF($C$9="Anual",IF(INDEX(Anual!$B$2:$J$8,23,K$12)="",NA(),INDEX(Anual!$B$2:$J$8,23,K$12)),IF(INDEX(Mensual!$B$2:$S$83,23,K$12)="",NA(),INDEX(Mensual!$B$2:$S$83,23,K$12))))
A38: =IF($C$9="Anual",IF(24<=7,INDEX(Anual!$A$2:$A$8,24),""),IF(24<=82,INDEX(Mensual!$A$2:$A$83,24),"")) | B38: =IF($C$10="Sí",H38/H$13*100,H38) | C38: =IF($C$10="Sí",I38/I$13*100,I38) | D38: =IF($C$10="Sí",J38/J$13*100,J38) | E38: =IF($C$10="Sí",K38/K$13*100,K38) | H38: =IF(OR($A38="",H$12=0),NA(),IF($C$9="Anual",IF(INDEX(Anual!$B$2:$J$8,24,H$12)="",NA(),INDEX(Anual!$B$2:$J$8,24,H$12)),IF(INDEX(Mensual!$B$2:$S$83,24,H$12)="",NA(),INDEX(Mensual!$B$2:$S$83,24,H$12)))) | I38: =IF(OR($A38="",I$12=0),NA(),IF($C$9="Anual",IF(INDEX(Anual!$B$2:$J$8,24,I$12)="",NA(),INDEX(Anual!$B$2:$J$8,24,I$12)),IF(INDEX(Mensual!$B$2:$S$83,24,I$12)="",NA(),INDEX(Mensual!$B$2:$S$83,24,I$12)))) | J38: =IF(OR($A38="",J$12=0),NA(),IF($C$9="Anual",IF(INDEX(Anual!$B$2:$J$8,24,J$12)="",NA(),INDEX(Anual!$B$2:$J$8,24,J$12)),IF(INDEX(Mensual!$B$2:$S$83,24,J$12)="",NA(),INDEX(Mensual!$B$2:$S$83,24,J$12)))) | K38: =IF(OR($A38="",K$12=0),NA(),IF($C$9="Anual",IF(INDEX(Anual!$B$2:$J$8,24,K$12)="",NA(),INDEX(Anual!$B$2:$J$8,24,K$12)),IF(INDEX(Mensual!$B$2:$S$83,24,K$12)="",NA(),INDEX(Mensual!$B$2:$S$83,24,K$12))))
A39: =IF($C$9="Anual",IF(25<=7,INDEX(Anual!$A$2:$A$8,25),""),IF(25<=82,INDEX(Mensual!$A$2:$A$83,25),"")) | B39: =IF($C$10="Sí",H39/H$13*100,H39) | C39: =IF($C$10="Sí",I39/I$13*100,I39) | D39: =IF($C$10="Sí",J39/J$13*100,J39) | E39: =IF($C$10="Sí",K39/K$13*100,K39) | H39: =IF(OR($A39="",H$12=0),NA(),IF($C$9="Anual",IF(INDEX(Anual!$B$2:$J$8,25,H$12)="",NA(),INDEX(Anual!$B$2:$J$8,25,H$12)),IF(INDEX(Mensual!$B$2:$S$83,25,H$12)="",NA(),INDEX(Mensual!$B$2:$S$83,25,H$12)))) | I39: =IF(OR($A39="",I$12=0),NA(),IF($C$9="Anual",IF(INDEX(Anual!$B$2:$J$8,25,I$12)="",NA(),INDEX(Anual!$B$2:$J$8,25,I$12)),IF(INDEX(Mensual!$B$2:$S$83,25,I$12)="",NA(),INDEX(Mensual!$B$2:$S$83,25,I$12)))) | J39: =IF(OR($A39="",J$12=0),NA(),IF($C$9="Anual",IF(INDEX(Anual!$B$2:$J$8,25,J$12)="",NA(),INDEX(Anual!$B$2:$J$8,25,J$12)),IF(INDEX(Mensual!$B$2:$S$83,25,J$12)="",NA(),INDEX(Mensual!$B$2:$S$83,25,J$12)))) | K39: =IF(OR($A39="",K$12=0),NA(),IF($C$9="Anual",IF(INDEX(Anual!$B$2:$J$8,25,K$12)="",NA(),INDEX(Anual!$B$2:$J$8,25,K$12)),IF(INDEX(Mensual!$B$2:$S$83,25,K$12)="",NA(),INDEX(Mensual!$B$2:$S$83,25,K$12))))
A40: =IF($C$9="Anual",IF(26<=7,INDEX(Anual!$A$2:$A$8,26),""),IF(26<=82,INDEX(Mensual!$A$2:$A$83,26),"")) | B40: =IF($C$10="Sí",H40/H$13*100,H40) | C40: =IF($C$10="Sí",I40/I$13*100,I40) | D40: =IF($C$10="Sí",J40/J$13*100,J40) | E40: =IF($C$10="Sí",K40/K$13*100,K40) | H40: =IF(OR($A40="",H$12=0),NA(),IF($C$9="Anual",IF(INDEX(Anual!$B$2:$J$8,26,H$12)="",NA(),INDEX(Anual!$B$2:$J$8,26,H$12)),IF(INDEX(Mensual!$B$2:$S$83,26,H$12)="",NA(),INDEX(Mensual!$B$2:$S$83,26,H$12)))) | I40: =IF(OR($A40="",I$12=0),NA(),IF($C$9="Anual",IF(INDEX(Anual!$B$2:$J$8,26,I$12)="",NA(),INDEX(Anual!$B$2:$J$8,26,I$12)),IF(INDEX(Mensual!$B$2:$S$83,26,I$12)="",NA(),INDEX(Mensual!$B$2:$S$83,26,I$12)))) | J40: =IF(OR($A40="",J$12=0),NA(),IF($C$9="Anual",IF(INDEX(Anual!$B$2:$J$8,26,J$12)="",NA(),INDEX(Anual!$B$2:$J$8,26,J$12)),IF(INDEX(Mensual!$B$2:$S$83,26,J$12)="",NA(),INDEX(Mensual!$B$2:$S$83,26,J$12)))) | K40: =IF(OR($A40="",K$12=0),NA(),IF($C$9="Anual",IF(INDEX(Anual!$B$2:$J$8,26,K$12)="",NA(),INDEX(Anual!$B$2:$J$8,26,K$12)),IF(INDEX(Mensual!$B$2:$S$83,26,K$12)="",NA(),INDEX(Mensual!$B$2:$S$83,26,K$12))))
A41: =IF($C$9="Anual",IF(27<=7,INDEX(Anual!$A$2:$A$8,27),""),IF(27<=82,INDEX(Mensual!$A$2:$A$83,27),"")) | B41: =IF($C$10="Sí",H41/H$13*100,H41) | C41: =IF($C$10="Sí",I41/I$13*100,I41) | D41: =IF($C$10="Sí",J41/J$13*100,J41) | E41: =IF($C$10="Sí",K41/K$13*100,K41) | H41: =IF(OR($A41="",H$12=0),NA(),IF($C$9="Anual",IF(INDEX(Anual!$B$2:$J$8,27,H$12)="",NA(),INDEX(Anual!$B$2:$J$8,27,H$12)),IF(INDEX(Mensual!$B$2:$S$83,27,H$12)="",NA(),INDEX(Mensual!$B$2:$S$83,27,H$12)))) | I41: =IF(OR($A41="",I$12=0),NA(),IF($C$9="Anual",IF(INDEX(Anual!$B$2:$J$8,27,I$12)="",NA(),INDEX(Anual!$B$2:$J$8,27,I$12)),IF(INDEX(Mensual!$B$2:$S$83,27,I$12)="",NA(),INDEX(Mensual!$B$2:$S$83,27,I$12)))) | J41: =IF(OR($A41="",J$12=0),NA(),IF($C$9="Anual",IF(INDEX(Anual!$B$2:$J$8,27,J$12)="",NA(),INDEX(Anual!$B$2:$J$8,27,J$12)),IF(INDEX(Mensual!$B$2:$S$83,27,J$12)="",NA(),INDEX(Mensual!$B$2:$S$83,27,J$12)))) | K41: =IF(OR($A41="",K$12=0),NA(),IF($C$9="Anual",IF(INDEX(Anual!$B$2:$J$8,27,K$12)="",NA(),INDEX(Anual!$B$2:$J$8,27,K$12)),IF(INDEX(Mensual!$B$2:$S$83,27,K$12)="",NA(),INDEX(Mensual!$B$2:$S$83,27,K$12))))
A42: =IF($C$9="Anual",IF(28<=7,INDEX(Anual!$A$2:$A$8,28),""),IF(28<=82,INDEX(Mensual!$A$2:$A$83,28),"")) | B42: =IF($C$10="Sí",H42/H$13*100,H42) | C42: =IF($C$10="Sí",I42/I$13*100,I42) | D42: =IF($C$10="Sí",J42/J$13*100,J42) | E42: =IF($C$10="Sí",K42/K$13*100,K42) | H42: =IF(OR($A42="",H$12=0),NA(),IF($C$9="Anual",IF(INDEX(Anual!$B$2:$J$8,28,H$12)="",NA(),INDEX(Anual!$B$2:$J$8,28,H$12)),IF(INDEX(Mensual!$B$2:$S$83,28,H$12)="",NA(),INDEX(Mensual!$B$2:$S$83,28,H$12)))) | I42: =IF(OR($A42="",I$12=0),NA(),IF($C$9="Anual",IF(INDEX(Anual!$B$2:$J$8,28,I$12)="",NA(),INDEX(Anual!$B$2:$J$8,28,I$12)),IF(INDEX(Mensual!$B$2:$S$83,28,I$12)="",NA(),INDEX(Mensual!$B$2:$S$83,28,I$12)))) | J42: =IF(OR($A42="",J$12=0),NA(),IF($C$9="Anual",IF(INDEX(Anual!$B$2:$J$8,28,J$12)="",NA(),INDEX(Anual!$B$2:$J$8,28,J$12)),IF(INDEX(Mensual!$B$2:$S$83,28,J$12)="",NA(),INDEX(Mensual!$B$2:$S$83,28,J$12)))) | K42: =IF(OR($A42="",K$12=0),NA(),IF($C$9="Anual",IF(INDEX(Anual!$B$2:$J$8,28,K$12)="",NA(),INDEX(Anual!$B$2:$J$8,28,K$12)),IF(INDEX(Mensual!$B$2:$S$83,28,K$12)="",NA(),INDEX(Mensual!$B$2:$S$83,28,K$12))))
A43: =IF($C$9="Anual",IF(29<=7,INDEX(Anual!$A$2:$A$8,29),""),IF(29<=82,INDEX(Mensual!$A$2:$A$83,29),"")) | B43: =IF($C$10="Sí",H43/H$13*100,H43) | C43: =IF($C$10="Sí",I43/I$13*100,I43) | D43: =IF($C$10="Sí",J43/J$13*100,J43) | E43: =IF($C$10="Sí",K43/K$13*100,K43) | H43: =IF(OR($A43="",H$12=0),NA(),IF($C$9="Anual",IF(INDEX(Anual!$B$2:$J$8,29,H$12)="",NA(),INDEX(Anual!$B$2:$J$8,29,H$12)),IF(INDEX(Mensual!$B$2:$S$83,29,H$12)="",NA(),INDEX(Mensual!$B$2:$S$83,29,H$12)))) | I43: =IF(OR($A43="",I$12=0),NA(),IF($C$9="Anual",IF(INDEX(Anual!$B$2:$J$8,29,I$12)="",NA(),INDEX(Anual!$B$2:$J$8,29,I$12)),IF(INDEX(Mensual!$B$2:$S$83,29,I$12)="",NA(),INDEX(Mensual!$B$2:$S$83,29,I$12)))) | J43: =IF(OR($A43="",J$12=0),NA(),IF($C$9="Anual",IF(INDEX(Anual!$B$2:$J$8,29,J$12)="",NA(),INDEX(Anual!$B$2:$J$8,29,J$12)),IF(INDEX(Mensual!$B$2:$S$83,29,J$12)="",NA(),INDEX(Mensual!$B$2:$S$83,29,J$12)))) | K43: =IF(OR($A43="",K$12=0),NA(),IF($C$9="Anual",IF(INDEX(Anual!$B$2:$J$8,29,K$12)="",NA(),INDEX(Anual!$B$2:$J$8,29,K$12)),IF(INDEX(Mensual!$B$2:$S$83,29,K$12)="",NA(),INDEX(Mensual!$B$2:$S$83,29,K$12))))
A44: =IF($C$9="Anual",IF(30<=7,INDEX(Anual!$A$2:$A$8,30),""),IF(30<=82,INDEX(Mensual!$A$2:$A$83,30),"")) | B44: =IF($C$10="Sí",H44/H$13*100,H44) | C44: =IF($C$10="Sí",I44/I$13*100,I44) | D44: =IF($C$10="Sí",J44/J$13*100,J44) | E44: =IF($C$10="Sí",K44/K$13*100,K44) | H44: =IF(OR($A44="",H$12=0),NA(),IF($C$9="Anual",IF(INDEX(Anual!$B$2:$J$8,30,H$12)="",NA(),INDEX(Anual!$B$2:$J$8,30,H$12)),IF(INDEX(Mensual!$B$2:$S$83,30,H$12)="",NA(),INDEX(Mensual!$B$2:$S$83,30,H$12)))) | I44: =IF(OR($A44="",I$12=0),NA(),IF($C$9="Anual",IF(INDEX(Anual!$B$2:$J$8,30,I$12)="",NA(),INDEX(Anual!$B$2:$J$8,30,I$12)),IF(INDEX(Mensual!$B$2:$S$83,30,I$12)="",NA(),INDEX(Mensual!$B$2:$S$83,30,I$12)))) | J44: =IF(OR($A44="",J$12=0),NA(),IF($C$9="Anual",IF(INDEX(Anual!$B$2:$J$8,30,J$12)="",NA(),INDEX(Anual!$B$2:$J$8,30,J$12)),IF(INDEX(Mensual!$B$2:$S$83,30,J$12)="",NA(),INDEX(Mensual!$B$2:$S$83,30,J$12)))) | K44: =IF(OR($A44="",K$12=0),NA(),IF($C$9="Anual",IF(INDEX(Anual!$B$2:$J$8,30,K$12)="",NA(),INDEX(Anual!$B$2:$J$8,30,K$12)),IF(INDEX(Mensual!$B$2:$S$83,30,K$12)="",NA(),INDEX(Mensual!$B$2:$S$83,30,K$12))))
A45: =IF($C$9="Anual",IF(31<=7,INDEX(Anual!$A$2:$A$8,31),""),IF(31<=82,INDEX(Mensual!$A$2:$A$83,31),"")) | B45: =IF($C$10="Sí",H45/H$13*100,H45) | C45: =IF($C$10="Sí",I45/I$13*100,I45) | D45: =IF($C$10="Sí",J45/J$13*100,J45) | E45: =IF($C$10="Sí",K45/K$13*100,K45) | H45: =IF(OR($A45="",H$12=0),NA(),IF($C$9="Anual",IF(INDEX(Anual!$B$2:$J$8,31,H$12)="",NA(),INDEX(Anual!$B$2:$J$8,31,H$12)),IF(INDEX(Mensual!$B$2:$S$83,31,H$12)="",NA(),INDEX(Mensual!$B$2:$S$83,31,H$12)))) | I45: =IF(OR($A45="",I$12=0),NA(),IF($C$9="Anual",IF(INDEX(Anual!$B$2:$J$8,31,I$12)="",NA(),INDEX(Anual!$B$2:$J$8,31,I$12)),IF(INDEX(Mensual!$B$2:$S$83,31,I$12)="",NA(),INDEX(Mensual!$B$2:$S$83,31,I$12)))) | J45: =IF(OR($A45="",J$12=0),NA(),IF($C$9="Anual",IF(INDEX(Anual!$B$2:$J$8,31,J$12)="",NA(),INDEX(Anual!$B$2:$J$8,31,J$12)),IF(INDEX(Mensual!$B$2:$S$83,31,J$12)="",NA(),INDEX(Mensual!$B$2:$S$83,31,J$12)))) | K45: =IF(OR($A45="",K$12=0),NA(),IF($C$9="Anual",IF(INDEX(Anual!$B$2:$J$8,31,K$12)="",NA(),INDEX(Anual!$B$2:$J$8,31,K$12)),IF(INDEX(Mensual!$B$2:$S$83,31,K$12)="",NA(),INDEX(Mensual!$B$2:$S$83,31,K$12))))
A46: =IF($C$9="Anual",IF(32<=7,INDEX(Anual!$A$2:$A$8,32),""),IF(32<=82,INDEX(Mensual!$A$2:$A$83,32),"")) | B46: =IF($C$10="Sí",H46/H$13*100,H46) | C46: =IF($C$10="Sí",I46/I$13*100,I46) | D46: =IF($C$10="Sí",J46/J$13*100,J46) | E46: =IF($C$10="Sí",K46/K$13*100,K46) | H46: =IF(OR($A46="",H$12=0),NA(),IF($C$9="Anual",IF(INDEX(Anual!$B$2:$J$8,32,H$12)="",NA(),INDEX(Anual!$B$2:$J$8,32,H$12)),IF(INDEX(Mensual!$B$2:$S$83,32,H$12)="",NA(),INDEX(Mensual!$B$2:$S$83,32,H$12)))) | I46: =IF(OR($A46="",I$12=0),NA(),IF($C$9="Anual",IF(INDEX(Anual!$B$2:$J$8,32,I$12)="",NA(),INDEX(Anual!$B$2:$J$8,32,I$12)),IF(INDEX(Mensual!$B$2:$S$83,32,I$12)="",NA(),INDEX(Mensual!$B$2:$S$83,32,I$12)))) | J46: =IF(OR($A46="",J$12=0),NA(),IF($C$9="Anual",IF(INDEX(Anual!$B$2:$J$8,32,J$12)="",NA(),INDEX(Anual!$B$2:$J$8,32,J$12)),IF(INDEX(Mensual!$B$2:$S$83,32,J$12)="",NA(),INDEX(Mensual!$B$2:$S$83,32,J$12)))) | K46: =IF(OR($A46="",K$12=0),NA(),IF($C$9="Anual",IF(INDEX(Anual!$B$2:$J$8,32,K$12)="",NA(),INDEX(Anual!$B$2:$J$8,32,K$12)),IF(INDEX(Mensual!$B$2:$S$83,32,K$12)="",NA(),INDEX(Mensual!$B$2:$S$83,32,K$12))))
A47: =IF($C$9="Anual",IF(33<=7,INDEX(Anual!$A$2:$A$8,33),""),IF(33<=82,INDEX(Mensual!$A$2:$A$83,33),"")) | B47: =IF($C$10="Sí",H47/H$13*100,H47) | C47: =IF($C$10="Sí",I47/I$13*100,I47) | D47: =IF($C$10="Sí",J47/J$13*100,J47) | E47: =IF($C$10="Sí",K47/K$13*100,K47) | H47: =IF(OR($A47="",H$12=0),NA(),IF($C$9="Anual",IF(INDEX(Anual!$B$2:$J$8,33,H$12)="",NA(),INDEX(Anual!$B$2:$J$8,33,H$12)),IF(INDEX(Mensual!$B$2:$S$83,33,H$12)="",NA(),INDEX(Mensual!$B$2:$S$83,33,H$12)))) | I47: =IF(OR($A47="",I$12=0),NA(),IF($C$9="Anual",IF(INDEX(Anual!$B$2:$J$8,33,I$12)="",NA(),INDEX(Anual!$B$2:$J$8,33,I$12)),IF(INDEX(Mensual!$B$2:$S$83,33,I$12)="",NA(),INDEX(Mensual!$B$2:$S$83,33,I$12)))) | J47: =IF(OR($A47="",J$12=0),NA(),IF($C$9="Anual",IF(INDEX(Anual!$B$2:$J$8,33,J$12)="",NA(),INDEX(Anual!$B$2:$J$8,33,J$12)),IF(INDEX(Mensual!$B$2:$S$83,33,J$12)="",NA(),INDEX(Mensual!$B$2:$S$83,33,J$12)))) | K47: =IF(OR($A47="",K$12=0),NA(),IF($C$9="Anual",IF(INDEX(Anual!$B$2:$J$8,33,K$12)="",NA(),INDEX(Anual!$B$2:$J$8,33,K$12)),IF(INDEX(Mensual!$B$2:$S$83,33,K$12)="",NA(),INDEX(Mensual!$B$2:$S$83,33,K$12))))
A48: =IF($C$9="Anual",IF(34<=7,INDEX(Anual!$A$2:$A$8,34),""),IF(34<=82,INDEX(Mensual!$A$2:$A$83,34),"")) | B48: =IF($C$10="Sí",H48/H$13*100,H48) | C48: =IF($C$10="Sí",I48/I$13*100,I48) | D48: =IF($C$10="Sí",J48/J$13*100,J48) | E48: =IF($C$10="Sí",K48/K$13*100,K48) | H48: =IF(OR($A48="",H$12=0),NA(),IF($C$9="Anual",IF(INDEX(Anual!$B$2:$J$8,34,H$12)="",NA(),INDEX(Anual!$B$2:$J$8,34,H$12)),IF(INDEX(Mensual!$B$2:$S$83,34,H$12)="",NA(),INDEX(Mensual!$B$2:$S$83,34,H$12)))) | I48: =IF(OR($A48="",I$12=0),NA(),IF($C$9="Anual",IF(INDEX(Anual!$B$2:$J$8,34,I$12)="",NA(),INDEX(Anual!$B$2:$J$8,34,I$12)),IF(INDEX(Mensual!$B$2:$S$83,34,I$12)="",NA(),INDEX(Mensual!$B$2:$S$83,34,I$12)))) | J48: =IF(OR($A48="",J$12=0),NA(),IF($C$9="Anual",IF(INDEX(Anual!$B$2:$J$8,34,J$12)="",NA(),INDEX(Anual!$B$2:$J$8,34,J$12)),IF(INDEX(Mensual!$B$2:$S$83,34,J$12)="",NA(),INDEX(Mensual!$B$2:$S$83,34,J$12)))) | K48: =IF(OR($A48="",K$12=0),NA(),IF($C$9="Anual",IF(INDEX(Anual!$B$2:$J$8,34,K$12)="",NA(),INDEX(Anual!$B$2:$J$8,34,K$12)),IF(INDEX(Mensual!$B$2:$S$83,34,K$12)="",NA(),INDEX(Mensual!$B$2:$S$83,34,K$12))))
A49: =IF($C$9="Anual",IF(35<=7,INDEX(Anual!$A$2:$A$8,35),""),IF(35<=82,INDEX(Mensual!$A$2:$A$83,35),"")) | B49: =IF($C$10="Sí",H49/H$13*100,H49) | C49: =IF($C$10="Sí",I49/I$13*100,I49) | D49: =IF($C$10="Sí",J49/J$13*100,J49) | E49: =IF($C$10="Sí",K49/K$13*100,K49) | H49: =IF(OR($A49="",H$12=0),NA(),IF($C$9="Anual",IF(INDEX(Anual!$B$2:$J$8,35,H$12)="",NA(),INDEX(Anual!$B$2:$J$8,35,H$12)),IF(INDEX(Mensual!$B$2:$S$83,35,H$12)="",NA(),INDEX(Mensual!$B$2:$S$83,35,H$12)))) | I49: =IF(OR($A49="",I$12=0),NA(),IF($C$9="Anual",IF(INDEX(Anual!$B$2:$J$8,35,I$12)="",NA(),INDEX(Anual!$B$2:$J$8,35,I$12)),IF(INDEX(Mensual!$B$2:$S$83,35,I$12)="",NA(),INDEX(Mensual!$B$2:$S$83,35,I$12)))) | J49: =IF(OR($A49="",J$12=0),NA(),IF($C$9="Anual",IF(INDEX(Anual!$B$2:$J$8,35,J$12)="",NA(),INDEX(Anual!$B$2:$J$8,35,J$12)),IF(INDEX(Mensual!$B$2:$S$83,35,J$12)="",NA(),INDEX(Mensual!$B$2:$S$83,35,J$12)))) | K49: =IF(OR($A49="",K$12=0),NA(),IF($C$9="Anual",IF(INDEX(Anual!$B$2:$J$8,35,K$12)="",NA(),INDEX(Anual!$B$2:$J$8,35,K$12)),IF(INDEX(Mensual!$B$2:$S$83,35,K$12)="",NA(),INDEX(Mensual!$B$2:$S$83,35,K$12))))
A50: =IF($C$9="Anual",IF(36<=7,INDEX(Anual!$A$2:$A$8,36),""),IF(36<=82,INDEX(Mensual!$A$2:$A$83,36),"")) | B50: =IF($C$10="Sí",H50/H$13*100,H50) | C50: =IF($C$10="Sí",I50/I$13*100,I50) | D50: =IF($C$10="Sí",J50/J$13*100,J50) | E50: =IF($C$10="Sí",K50/K$13*100,K50) | H50: =IF(OR($A50="",H$12=0),NA(),IF($C$9="Anual",IF(INDEX(Anual!$B$2:$J$8,36,H$12)="",NA(),INDEX(Anual!$B$2:$J$8,36,H$12)),IF(INDEX(Mensual!$B$2:$S$83,36,H$12)="",NA(),INDEX(Mensual!$B$2:$S$83,36,H$12)))) | I50: =IF(OR($A50="",I$12=0),NA(),IF($C$9="Anual",IF(INDEX(Anual!$B$2:$J$8,36,I$12)="",NA(),INDEX(Anual!$B$2:$J$8,36,I$12)),IF(INDEX(Mensual!$B$2:$S$83,36,I$12)="",NA(),INDEX(Mensual!$B$2:$S$83,36,I$12)))) | J50: =IF(OR($A50="",J$12=0),NA(),IF($C$9="Anual",IF(INDEX(Anual!$B$2:$J$8,36,J$12)="",NA(),INDEX(Anual!$B$2:$J$8,36,J$12)),IF(INDEX(Mensual!$B$2:$S$83,36,J$12)="",NA(),INDEX(Mensual!$B$2:$S$83,36,J$12)))) | K50: =IF(OR($A50="",K$12=0),NA(),IF($C$9="Anual",IF(INDEX(Anual!$B$2:$J$8,36,K$12)="",NA(),INDEX(Anual!$B$2:$J$8,36,K$12)),IF(INDEX(Mensual!$B$2:$S$83,36,K$12)="",NA(),INDEX(Mensual!$B$2:$S$83,36,K$12))))
A51: =IF($C$9="Anual",IF(37<=7,INDEX(Anual!$A$2:$A$8,37),""),IF(37<=82,INDEX(Mensual!$A$2:$A$83,37),"")) | B51: =IF($C$10="Sí",H51/H$13*100,H51) | C51: =IF($C$10="Sí",I51/I$13*100,I51) | D51: =IF($C$10="Sí",J51/J$13*100,J51) | E51: =IF($C$10="Sí",K51/K$13*100,K51) | H51: =IF(OR($A51="",H$12=0),NA(),IF($C$9="Anual",IF(INDEX(Anual!$B$2:$J$8,37,H$12)="",NA(),INDEX(Anual!$B$2:$J$8,37,H$12)),IF(INDEX(Mensual!$B$2:$S$83,37,H$12)="",NA(),INDEX(Mensual!$B$2:$S$83,37,H$12)))) | I51: =IF(OR($A51="",I$12=0),NA(),IF($C$9="Anual",IF(INDEX(Anual!$B$2:$J$8,37,I$12)="",NA(),INDEX(Anual!$B$2:$J$8,37,I$12)),IF(INDEX(Mensual!$B$2:$S$83,37,I$12)="",NA(),INDEX(Mensual!$B$2:$S$83,37,I$12)))) | J51: =IF(OR($A51="",J$12=0),NA(),IF($C$9="Anual",IF(INDEX(Anual!$B$2:$J$8,37,J$12)="",NA(),INDEX(Anual!$B$2:$J$8,37,J$12)),IF(INDEX(Mensual!$B$2:$S$83,37,J$12)="",NA(),INDEX(Mensual!$B$2:$S$83,37,J$12)))) | K51: =IF(OR($A51="",K$12=0),NA(),IF($C$9="Anual",IF(INDEX(Anual!$B$2:$J$8,37,K$12)="",NA(),INDEX(Anual!$B$2:$J$8,37,K$12)),IF(INDEX(Mensual!$B$2:$S$83,37,K$12)="",NA(),INDEX(Mensual!$B$2:$S$83,37,K$12))))
A52: =IF($C$9="Anual",IF(38<=7,INDEX(Anual!$A$2:$A$8,38),""),IF(38<=82,INDEX(Mensual!$A$2:$A$83,38),"")) | B52: =IF($C$10="Sí",H52/H$13*100,H52) | C52: =IF($C$10="Sí",I52/I$13*100,I52) | D52: =IF($C$10="Sí",J52/J$13*100,J52) | E52: =IF($C$10="Sí",K52/K$13*100,K52) | H52: =IF(OR($A52="",H$12=0),NA(),IF($C$9="Anual",IF(INDEX(Anual!$B$2:$J$8,38,H$12)="",NA(),INDEX(Anual!$B$2:$J$8,38,H$12)),IF(INDEX(Mensual!$B$2:$S$83,38,H$12)="",NA(),INDEX(Mensual!$B$2:$S$83,38,H$12)))) | I52: =IF(OR($A52="",I$12=0),NA(),IF($C$9="Anual",IF(INDEX(Anual!$B$2:$J$8,38,I$12)="",NA(),INDEX(Anual!$B$2:$J$8,38,I$12)),IF(INDEX(Mensual!$B$2:$S$83,38,I$12)="",NA(),INDEX(Mensual!$B$2:$S$83,38,I$12)))) | J52: =IF(OR($A52="",J$12=0),NA(),IF($C$9="Anual",IF(INDEX(Anual!$B$2:$J$8,38,J$12)="",NA(),INDEX(Anual!$B$2:$J$8,38,J$12)),IF(INDEX(Mensual!$B$2:$S$83,38,J$12)="",NA(),INDEX(Mensual!$B$2:$S$83,38,J$12)))) | K52: =IF(OR($A52="",K$12=0),NA(),IF($C$9="Anual",IF(INDEX(Anual!$B$2:$J$8,38,K$12)="",NA(),INDEX(Anual!$B$2:$J$8,38,K$12)),IF(INDEX(Mensual!$B$2:$S$83,38,K$12)="",NA(),INDEX(Mensual!$B$2:$S$83,38,K$12))))
A53: =IF($C$9="Anual",IF(39<=7,INDEX(Anual!$A$2:$A$8,39),""),IF(39<=82,INDEX(Mensual!$A$2:$A$83,39),"")) | B53: =IF($C$10="Sí",H53/H$13*100,H53) | C53: =IF($C$10="Sí",I53/I$13*100,I53) | D53: =IF($C$10="Sí",J53/J$13*100,J53) | E53: =IF($C$10="Sí",K53/K$13*100,K53) | H53: =IF(OR($A53="",H$12=0),NA(),IF($C$9="Anual",IF(INDEX(Anual!$B$2:$J$8,39,H$12)="",NA(),INDEX(Anual!$B$2:$J$8,39,H$12)),IF(INDEX(Mensual!$B$2:$S$83,39,H$12)="",NA(),INDEX(Mensual!$B$2:$S$83,39,H$12)))) | I53: =IF(OR($A53="",I$12=0),NA(),IF($C$9="Anual",IF(INDEX(Anual!$B$2:$J$8,39,I$12)="",NA(),INDEX(Anual!$B$2:$J$8,39,I$12)),IF(INDEX(Mensual!$B$2:$S$83,39,I$12)="",NA(),INDEX(Mensual!$B$2:$S$83,39,I$12)))) | J53: =IF(OR($A53="",J$12=0),NA(),IF($C$9="Anual",IF(INDEX(Anual!$B$2:$J$8,39,J$12)="",NA(),INDEX(Anual!$B$2:$J$8,39,J$12)),IF(INDEX(Mensual!$B$2:$S$83,39,J$12)="",NA(),INDEX(Mensual!$B$2:$S$83,39,J$12)))) | K53: =IF(OR($A53="",K$12=0),NA(),IF($C$9="Anual",IF(INDEX(Anual!$B$2:$J$8,39,K$12)="",NA(),INDEX(Anual!$B$2:$J$8,39,K$12)),IF(INDEX(Mensual!$B$2:$S$83,39,K$12)="",NA(),INDEX(Mensual!$B$2:$S$83,39,K$12))))
A54: =IF($C$9="Anual",IF(40<=7,INDEX(Anual!$A$2:$A$8,40),""),IF(40<=82,INDEX(Mensual!$A$2:$A$83,40),"")) | B54: =IF($C$10="Sí",H54/H$13*100,H54) | C54: =IF($C$10="Sí",I54/I$13*100,I54) | D54: =IF($C$10="Sí",J54/J$13*100,J54) | E54: =IF($C$10="Sí",K54/K$13*100,K54) | H54: =IF(OR($A54="",H$12=0),NA(),IF($C$9="Anual",IF(INDEX(Anual!$B$2:$J$8,40,H$12)="",NA(),INDEX(Anual!$B$2:$J$8,40,H$12)),IF(INDEX(Mensual!$B$2:$S$83,40,H$12)="",NA(),INDEX(Mensual!$B$2:$S$83,40,H$12)))) | I54: =IF(OR($A54="",I$12=0),NA(),IF($C$9="Anual",IF(INDEX(Anual!$B$2:$J$8,40,I$12)="",NA(),INDEX(Anual!$B$2:$J$8,40,I$12)),IF(INDEX(Mensual!$B$2:$S$83,40,I$12)="",NA(),INDEX(Mensual!$B$2:$S$83,40,I$12)))) | J54: =IF(OR($A54="",J$12=0),NA(),IF($C$9="Anual",IF(INDEX(Anual!$B$2:$J$8,40,J$12)="",NA(),INDEX(Anual!$B$2:$J$8,40,J$12)),IF(INDEX(Mensual!$B$2:$S$83,40,J$12)="",NA(),INDEX(Mensual!$B$2:$S$83,40,J$12)))) | K54: =IF(OR($A54="",K$12=0),NA(),IF($C$9="Anual",IF(INDEX(Anual!$B$2:$J$8,40,K$12)="",NA(),INDEX(Anual!$B$2:$J$8,40,K$12)),IF(INDEX(Mensual!$B$2:$S$83,40,K$12)="",NA(),INDEX(Mensual!$B$2:$S$83,40,K$12))))
A55: =IF($C$9="Anual",IF(41<=7,INDEX(Anual!$A$2:$A$8,41),""),IF(41<=82,INDEX(Mensual!$A$2:$A$83,41),"")) | B55: =IF($C$10="Sí",H55/H$13*100,H55) | C55: =IF($C$10="Sí",I55/I$13*100,I55) | D55: =IF($C$10="Sí",J55/J$13*100,J55) | E55: =IF($C$10="Sí",K55/K$13*100,K55) | H55: =IF(OR($A55="",H$12=0),NA(),IF($C$9="Anual",IF(INDEX(Anual!$B$2:$J$8,41,H$12)="",NA(),INDEX(Anual!$B$2:$J$8,41,H$12)),IF(INDEX(Mensual!$B$2:$S$83,41,H$12)="",NA(),INDEX(Mensual!$B$2:$S$83,41,H$12)))) | I55: =IF(OR($A55="",I$12=0),NA(),IF($C$9="Anual",IF(INDEX(Anual!$B$2:$J$8,41,I$12)="",NA(),INDEX(Anual!$B$2:$J$8,41,I$12)),IF(INDEX(Mensual!$B$2:$S$83,41,I$12)="",NA(),INDEX(Mensual!$B$2:$S$83,41,I$12)))) | J55: =IF(OR($A55="",J$12=0),NA(),IF($C$9="Anual",IF(INDEX(Anual!$B$2:$J$8,41,J$12)="",NA(),INDEX(Anual!$B$2:$J$8,41,J$12)),IF(INDEX(Mensual!$B$2:$S$83,41,J$12)="",NA(),INDEX(Mensual!$B$2:$S$83,41,J$12)))) | K55: =IF(OR($A55="",K$12=0),NA(),IF($C$9="Anual",IF(INDEX(Anual!$B$2:$J$8,41,K$12)="",NA(),INDEX(Anual!$B$2:$J$8,41,K$12)),IF(INDEX(Mensual!$B$2:$S$83,41,K$12)="",NA(),INDEX(Mensual!$B$2:$S$83,41,K$12))))
A56: =IF($C$9="Anual",IF(42<=7,INDEX(Anual!$A$2:$A$8,42),""),IF(42<=82,INDEX(Mensual!$A$2:$A$83,42),"")) | B56: =IF($C$10="Sí",H56/H$13*100,H56) | C56: =IF($C$10="Sí",I56/I$13*100,I56) | D56: =IF($C$10="Sí",J56/J$13*100,J56) | E56: =IF($C$10="Sí",K56/K$13*100,K56) | H56: =IF(OR($A56="",H$12=0),NA(),IF($C$9="Anual",IF(INDEX(Anual!$B$2:$J$8,42,H$12)="",NA(),INDEX(Anual!$B$2:$J$8,42,H$12)),IF(INDEX(Mensual!$B$2:$S$83,42,H$12)="",NA(),INDEX(Mensual!$B$2:$S$83,42,H$12)))) | I56: =IF(OR($A56="",I$12=0),NA(),IF($C$9="Anual",IF(INDEX(Anual!$B$2:$J$8,42,I$12)="",NA(),INDEX(Anual!$B$2:$J$8,42,I$12)),IF(INDEX(Mensual!$B$2:$S$83,42,I$12)="",NA(),INDEX(Mensual!$B$2:$S$83,42,I$12)))) | J56: =IF(OR($A56="",J$12=0),NA(),IF($C$9="Anual",IF(INDEX(Anual!$B$2:$J$8,42,J$12)="",NA(),INDEX(Anual!$B$2:$J$8,42,J$12)),IF(INDEX(Mensual!$B$2:$S$83,42,J$12)="",NA(),INDEX(Mensual!$B$2:$S$83,42,J$12)))) | K56: =IF(OR($A56="",K$12=0),NA(),IF($C$9="Anual",IF(INDEX(Anual!$B$2:$J$8,42,K$12)="",NA(),INDEX(Anual!$B$2:$J$8,42,K$12)),IF(INDEX(Mensual!$B$2:$S$83,42,K$12)="",NA(),INDEX(Mensual!$B$2:$S$83,42,K$12))))
A57: =IF($C$9="Anual",IF(43<=7,INDEX(Anual!$A$2:$A$8,43),""),IF(43<=82,INDEX(Mensual!$A$2:$A$83,43),"")) | B57: =IF($C$10="Sí",H57/H$13*100,H57) | C57: =IF($C$10="Sí",I57/I$13*100,I57) | D57: =IF($C$10="Sí",J57/J$13*100,J57) | E57: =IF($C$10="Sí",K57/K$13*100,K57) | H57: =IF(OR($A57="",H$12=0),NA(),IF($C$9="Anual",IF(INDEX(Anual!$B$2:$J$8,43,H$12)="",NA(),INDEX(Anual!$B$2:$J$8,43,H$12)),IF(INDEX(Mensual!$B$2:$S$83,43,H$12)="",NA(),INDEX(Mensual!$B$2:$S$83,43,H$12)))) | I57: =IF(OR($A57="",I$12=0),NA(),IF($C$9="Anual",IF(INDEX(Anual!$B$2:$J$8,43,I$12)="",NA(),INDEX(Anual!$B$2:$J$8,43,I$12)),IF(INDEX(Mensual!$B$2:$S$83,43,I$12)="",NA(),INDEX(Mensual!$B$2:$S$83,43,I$12)))) | J57: =IF(OR($A57="",J$12=0),NA(),IF($C$9="Anual",IF(INDEX(Anual!$B$2:$J$8,43,J$12)="",NA(),INDEX(Anual!$B$2:$J$8,43,J$12)),IF(INDEX(Mensual!$B$2:$S$83,43,J$12)="",NA(),INDEX(Mensual!$B$2:$S$83,43,J$12)))) | K57: =IF(OR($A57="",K$12=0),NA(),IF($C$9="Anual",IF(INDEX(Anual!$B$2:$J$8,43,K$12)="",NA(),INDEX(Anual!$B$2:$J$8,43,K$12)),IF(INDEX(Mensual!$B$2:$S$83,43,K$12)="",NA(),INDEX(Mensual!$B$2:$S$83,43,K$12))))
A58: =IF($C$9="Anual",IF(44<=7,INDEX(Anual!$A$2:$A$8,44),""),IF(44<=82,INDEX(Mensual!$A$2:$A$83,44),"")) | B58: =IF($C$10="Sí",H58/H$13*100,H58) | C58: =IF($C$10="Sí",I58/I$13*100,I58) | D58: =IF($C$10="Sí",J58/J$13*100,J58) | E58: =IF($C$10="Sí",K58/K$13*100,K58) | H58: =IF(OR($A58="",H$12=0),NA(),IF($C$9="Anual",IF(INDEX(Anual!$B$2:$J$8,44,H$12)="",NA(),INDEX(Anual!$B$2:$J$8,44,H$12)),IF(INDEX(Mensual!$B$2:$S$83,44,H$12)="",NA(),INDEX(Mensual!$B$2:$S$83,44,H$12)))) | I58: =IF(OR($A58="",I$12=0),NA(),IF($C$9="Anual",IF(INDEX(Anual!$B$2:$J$8,44,I$12)="",NA(),INDEX(Anual!$B$2:$J$8,44,I$12)),IF(INDEX(Mensual!$B$2:$S$83,44,I$12)="",NA(),INDEX(Mensual!$B$2:$S$83,44,I$12)))) | J58: =IF(OR($A58="",J$12=0),NA(),IF($C$9="Anual",IF(INDEX(Anual!$B$2:$J$8,44,J$12)="",NA(),INDEX(Anual!$B$2:$J$8,44,J$12)),IF(INDEX(Mensual!$B$2:$S$83,44,J$12)="",NA(),INDEX(Mensual!$B$2:$S$83,44,J$12)))) | K58: =IF(OR($A58="",K$12=0),NA(),IF($C$9="Anual",IF(INDEX(Anual!$B$2:$J$8,44,K$12)="",NA(),INDEX(Anual!$B$2:$J$8,44,K$12)),IF(INDEX(Mensual!$B$2:$S$83,44,K$12)="",NA(),INDEX(Mensual!$B$2:$S$83,44,K$12))))
A59: =IF($C$9="Anual",IF(45<=7,INDEX(Anual!$A$2:$A$8,45),""),IF(45<=82,INDEX(Mensual!$A$2:$A$83,45),"")) | B59: =IF($C$10="Sí",H59/H$13*100,H59) | C59: =IF($C$10="Sí",I59/I$13*100,I59) | D59: =IF($C$10="Sí",J59/J$13*100,J59) | E59: =IF($C$10="Sí",K59/K$13*100,K59) | H59: =IF(OR($A59="",H$12=0),NA(),IF($C$9="Anual",IF(INDEX(Anual!$B$2:$J$8,45,H$12)="",NA(),INDEX(Anual!$B$2:$J$8,45,H$12)),IF(INDEX(Mensual!$B$2:$S$83,45,H$12)="",NA(),INDEX(Mensual!$B$2:$S$83,45,H$12)))) | I59: =IF(OR($A59="",I$12=0),NA(),IF($C$9="Anual",IF(INDEX(Anual!$B$2:$J$8,45,I$12)="",NA(),INDEX(Anual!$B$2:$J$8,45,I$12)),IF(INDEX(Mensual!$B$2:$S$83,45,I$12)="",NA(),INDEX(Mensual!$B$2:$S$83,45,I$12)))) | J59: =IF(OR($A59="",J$12=0),NA(),IF($C$9="Anual",IF(INDEX(Anual!$B$2:$J$8,45,J$12)="",NA(),INDEX(Anual!$B$2:$J$8,45,J$12)),IF(INDEX(Mensual!$B$2:$S$83,45,J$12)="",NA(),INDEX(Mensual!$B$2:$S$83,45,J$12)))) | K59: =IF(OR($A59="",K$12=0),NA(),IF($C$9="Anual",IF(INDEX(Anual!$B$2:$J$8,45,K$12)="",NA(),INDEX(Anual!$B$2:$J$8,45,K$12)),IF(INDEX(Mensual!$B$2:$S$83,45,K$12)="",NA(),INDEX(Mensual!$B$2:$S$83,45,K$12))))
A60: =IF($C$9="Anual",IF(46<=7,INDEX(Anual!$A$2:$A$8,46),""),IF(46<=82,INDEX(Mensual!$A$2:$A$83,46),"")) | B60: =IF($C$10="Sí",H60/H$13*100,H60) | C60: =IF($C$10="Sí",I60/I$13*100,I60) | D60: =IF($C$10="Sí",J60/J$13*100,J60) | E60: =IF($C$10="Sí",K60/K$13*100,K60) | H60: =IF(OR($A60="",H$12=0),NA(),IF($C$9="Anual",IF(INDEX(Anual!$B$2:$J$8,46,H$12)="",NA(),INDEX(Anual!$B$2:$J$8,46,H$12)),IF(INDEX(Mensual!$B$2:$S$83,46,H$12)="",NA(),INDEX(Mensual!$B$2:$S$83,46,H$12)))) | I60: =IF(OR($A60="",I$12=0),NA(),IF($C$9="Anual",IF(INDEX(Anual!$B$2:$J$8,46,I$12)="",NA(),INDEX(Anual!$B$2:$J$8,46,I$12)),IF(INDEX(Mensual!$B$2:$S$83,46,I$12)="",NA(),INDEX(Mensual!$B$2:$S$83,46,I$12)))) | J60: =IF(OR($A60="",J$12=0),NA(),IF($C$9="Anual",IF(INDEX(Anual!$B$2:$J$8,46,J$12)="",NA(),INDEX(Anual!$B$2:$J$8,46,J$12)),IF(INDEX(Mensual!$B$2:$S$83,46,J$12)="",NA(),INDEX(Mensual!$B$2:$S$83,46,J$12)))) | K60: =IF(OR($A60="",K$12=0),NA(),IF($C$9="Anual",IF(INDEX(Anual!$B$2:$J$8,46,K$12)="",NA(),INDEX(Anual!$B$2:$J$8,46,K$12)),IF(INDEX(Mensual!$B$2:$S$83,46,K$12)="",NA(),INDEX(Mensual!$B$2:$S$83,46,K$12))))
A61: =IF($C$9="Anual",IF(47<=7,INDEX(Anual!$A$2:$A$8,47),""),IF(47<=82,INDEX(Mensual!$A$2:$A$83,47),"")) | B61: =IF($C$10="Sí",H61/H$13*100,H61) | C61: =IF($C$10="Sí",I61/I$13*100,I61) | D61: =IF($C$10="Sí",J61/J$13*100,J61) | E61: =IF($C$10="Sí",K61/K$13*100,K61) | H61: =IF(OR($A61="",H$12=0),NA(),IF($C$9="Anual",IF(INDEX(Anual!$B$2:$J$8,47,H$12)="",NA(),INDEX(Anual!$B$2:$J$8,47,H$12)),IF(INDEX(Mensual!$B$2:$S$83,47,H$12)="",NA(),INDEX(Mensual!$B$2:$S$83,47,H$12)))) | I61: =IF(OR($A61="",I$12=0),NA(),IF($C$9="Anual",IF(INDEX(Anual!$B$2:$J$8,47,I$12)="",NA(),INDEX(Anual!$B$2:$J$8,47,I$12)),IF(INDEX(Mensual!$B$2:$S$83,47,I$12)="",NA(),INDEX(Mensual!$B$2:$S$83,47,I$12)))) | J61: =IF(OR($A61="",J$12=0),NA(),IF($C$9="Anual",IF(INDEX(Anual!$B$2:$J$8,47,J$12)="",NA(),INDEX(Anual!$B$2:$J$8,47,J$12)),IF(INDEX(Mensual!$B$2:$S$83,47,J$12)="",NA(),INDEX(Mensual!$B$2:$S$83,47,J$12)))) | K61: =IF(OR($A61="",K$12=0),NA(),IF($C$9="Anual",IF(INDEX(Anual!$B$2:$J$8,47,K$12)="",NA(),INDEX(Anual!$B$2:$J$8,47,K$12)),IF(INDEX(Mensual!$B$2:$S$83,47,K$12)="",NA(),INDEX(Mensual!$B$2:$S$83,47,K$12))))
A62: =IF($C$9="Anual",IF(48<=7,INDEX(Anual!$A$2:$A$8,48),""),IF(48<=82,INDEX(Mensual!$A$2:$A$83,48),"")) | B62: =IF($C$10="Sí",H62/H$13*100,H62) | C62: =IF($C$10="Sí",I62/I$13*100,I62) | D62: =IF($C$10="Sí",J62/J$13*100,J62) | E62: =IF($C$10="Sí",K62/K$13*100,K62) | H62: =IF(OR($A62="",H$12=0),NA(),IF($C$9="Anual",IF(INDEX(Anual!$B$2:$J$8,48,H$12)="",NA(),INDEX(Anual!$B$2:$J$8,48,H$12)),IF(INDEX(Mensual!$B$2:$S$83,48,H$12)="",NA(),INDEX(Mensual!$B$2:$S$83,48,H$12)))) | I62: =IF(OR($A62="",I$12=0),NA(),IF($C$9="Anual",IF(INDEX(Anual!$B$2:$J$8,48,I$12)="",NA(),INDEX(Anual!$B$2:$J$8,48,I$12)),IF(INDEX(Mensual!$B$2:$S$83,48,I$12)="",NA(),INDEX(Mensual!$B$2:$S$83,48,I$12)))) | J62: =IF(OR($A62="",J$12=0),NA(),IF($C$9="Anual",IF(INDEX(Anual!$B$2:$J$8,48,J$12)="",NA(),INDEX(Anual!$B$2:$J$8,48,J$12)),IF(INDEX(Mensual!$B$2:$S$83,48,J$12)="",NA(),INDEX(Mensual!$B$2:$S$83,48,J$12)))) | K62: =IF(OR($A62="",K$12=0),NA(),IF($C$9="Anual",IF(INDEX(Anual!$B$2:$J$8,48,K$12)="",NA(),INDEX(Anual!$B$2:$J$8,48,K$12)),IF(INDEX(Mensual!$B$2:$S$83,48,K$12)="",NA(),INDEX(Mensual!$B$2:$S$83,48,K$12))))
A63: =IF($C$9="Anual",IF(49<=7,INDEX(Anual!$A$2:$A$8,49),""),IF(49<=82,INDEX(Mensual!$A$2:$A$83,49),"")) | B63: =IF($C$10="Sí",H63/H$13*100,H63) | C63: =IF($C$10="Sí",I63/I$13*100,I63) | D63: =IF($C$10="Sí",J63/J$13*100,J63) | E63: =IF($C$10="Sí",K63/K$13*100,K63) | H63: =IF(OR($A63="",H$12=0),NA(),IF($C$9="Anual",IF(INDEX(Anual!$B$2:$J$8,49,H$12)="",NA(),INDEX(Anual!$B$2:$J$8,49,H$12)),IF(INDEX(Mensual!$B$2:$S$83,49,H$12)="",NA(),INDEX(Mensual!$B$2:$S$83,49,H$12)))) | I63: =IF(OR($A63="",I$12=0),NA(),IF($C$9="Anual",IF(INDEX(Anual!$B$2:$J$8,49,I$12)="",NA(),INDEX(Anual!$B$2:$J$8,49,I$12)),IF(INDEX(Mensual!$B$2:$S$83,49,I$12)="",NA(),INDEX(Mensual!$B$2:$S$83,49,I$12)))) | J63: =IF(OR($A63="",J$12=0),NA(),IF($C$9="Anual",IF(INDEX(Anual!$B$2:$J$8,49,J$12)="",NA(),INDEX(Anual!$B$2:$J$8,49,J$12)),IF(INDEX(Mensual!$B$2:$S$83,49,J$12)="",NA(),INDEX(Mensual!$B$2:$S$83,49,J$12)))) | K63: =IF(OR($A63="",K$12=0),NA(),IF($C$9="Anual",IF(INDEX(Anual!$B$2:$J$8,49,K$12)="",NA(),INDEX(Anual!$B$2:$J$8,49,K$12)),IF(INDEX(Mensual!$B$2:$S$83,49,K$12)="",NA(),INDEX(Mensual!$B$2:$S$83,49,K$12))))
A64: =IF($C$9="Anual",IF(50<=7,INDEX(Anual!$A$2:$A$8,50),""),IF(50<=82,INDEX(Mensual!$A$2:$A$83,50),"")) | B64: =IF($C$10="Sí",H64/H$13*100,H64) | C64: =IF($C$10="Sí",I64/I$13*100,I64) | D64: =IF($C$10="Sí",J64/J$13*100,J64) | E64: =IF($C$10="Sí",K64/K$13*100,K64) | H64: =IF(OR($A64="",H$12=0),NA(),IF($C$9="Anual",IF(INDEX(Anual!$B$2:$J$8,50,H$12)="",NA(),INDEX(Anual!$B$2:$J$8,50,H$12)),IF(INDEX(Mensual!$B$2:$S$83,50,H$12)="",NA(),INDEX(Mensual!$B$2:$S$83,50,H$12)))) | I64: =IF(OR($A64="",I$12=0),NA(),IF($C$9="Anual",IF(INDEX(Anual!$B$2:$J$8,50,I$12)="",NA(),INDEX(Anual!$B$2:$J$8,50,I$12)),IF(INDEX(Mensual!$B$2:$S$83,50,I$12)="",NA(),INDEX(Mensual!$B$2:$S$83,50,I$12)))) | J64: =IF(OR($A64="",J$12=0),NA(),IF($C$9="Anual",IF(INDEX(Anual!$B$2:$J$8,50,J$12)="",NA(),INDEX(Anual!$B$2:$J$8,50,J$12)),IF(INDEX(Mensual!$B$2:$S$83,50,J$12)="",NA(),INDEX(Mensual!$B$2:$S$83,50,J$12)))) | K64: =IF(OR($A64="",K$12=0),NA(),IF($C$9="Anual",IF(INDEX(Anual!$B$2:$J$8,50,K$12)="",NA(),INDEX(Anual!$B$2:$J$8,50,K$12)),IF(INDEX(Mensual!$B$2:$S$83,50,K$12)="",NA(),INDEX(Mensual!$B$2:$S$83,50,K$12))))
A65: =IF($C$9="Anual",IF(51<=7,INDEX(Anual!$A$2:$A$8,51),""),IF(51<=82,INDEX(Mensual!$A$2:$A$83,51),"")) | B65: =IF($C$10="Sí",H65/H$13*100,H65) | C65: =IF($C$10="Sí",I65/I$13*100,I65) | D65: =IF($C$10="Sí",J65/J$13*100,J65) | E65: =IF($C$10="Sí",K65/K$13*100,K65) | H65: =IF(OR($A65="",H$12=0),NA(),IF($C$9="Anual",IF(INDEX(Anual!$B$2:$J$8,51,H$12)="",NA(),INDEX(Anual!$B$2:$J$8,51,H$12)),IF(INDEX(Mensual!$B$2:$S$83,51,H$12)="",NA(),INDEX(Mensual!$B$2:$S$83,51,H$12)))) | I65: =IF(OR($A65="",I$12=0),NA(),IF($C$9="Anual",IF(INDEX(Anual!$B$2:$J$8,51,I$12)="",NA(),INDEX(Anual!$B$2:$J$8,51,I$12)),IF(INDEX(Mensual!$B$2:$S$83,51,I$12)="",NA(),INDEX(Mensual!$B$2:$S$83,51,I$12)))) | J65: =IF(OR($A65="",J$12=0),NA(),IF($C$9="Anual",IF(INDEX(Anual!$B$2:$J$8,51,J$12)="",NA(),INDEX(Anual!$B$2:$J$8,51,J$12)),IF(INDEX(Mensual!$B$2:$S$83,51,J$12)="",NA(),INDEX(Mensual!$B$2:$S$83,51,J$12)))) | K65: =IF(OR($A65="",K$12=0),NA(),IF($C$9="Anual",IF(INDEX(Anual!$B$2:$J$8,51,K$12)="",NA(),INDEX(Anual!$B$2:$J$8,51,K$12)),IF(INDEX(Mensual!$B$2:$S$83,51,K$12)="",NA(),INDEX(Mensual!$B$2:$S$83,51,K$12))))
A66: =IF($C$9="Anual",IF(52<=7,INDEX(Anual!$A$2:$A$8,52),""),IF(52<=82,INDEX(Mensual!$A$2:$A$83,52),"")) | B66: =IF($C$10="Sí",H66/H$13*100,H66) | C66: =IF($C$10="Sí",I66/I$13*100,I66) | D66: =IF($C$10="Sí",J66/J$13*100,J66) | E66: =IF($C$10="Sí",K66/K$13*100,K66) | H66: =IF(OR($A66="",H$12=0),NA(),IF($C$9="Anual",IF(INDEX(Anual!$B$2:$J$8,52,H$12)="",NA(),INDEX(Anual!$B$2:$J$8,52,H$12)),IF(INDEX(Mensual!$B$2:$S$83,52,H$12)="",NA(),INDEX(Mensual!$B$2:$S$83,52,H$12)))) | I66: =IF(OR($A66="",I$12=0),NA(),IF($C$9="Anual",IF(INDEX(Anual!$B$2:$J$8,52,I$12)="",NA(),INDEX(Anual!$B$2:$J$8,52,I$12)),IF(INDEX(Mensual!$B$2:$S$83,52,I$12)="",NA(),INDEX(Mensual!$B$2:$S$83,52,I$12)))) | J66: =IF(OR($A66="",J$12=0),NA(),IF($C$9="Anual",IF(INDEX(Anual!$B$2:$J$8,52,J$12)="",NA(),INDEX(Anual!$B$2:$J$8,52,J$12)),IF(INDEX(Mensual!$B$2:$S$83,52,J$12)="",NA(),INDEX(Mensual!$B$2:$S$83,52,J$12)))) | K66: =IF(OR($A66="",K$12=0),NA(),IF($C$9="Anual",IF(INDEX(Anual!$B$2:$J$8,52,K$12)="",NA(),INDEX(Anual!$B$2:$J$8,52,K$12)),IF(INDEX(Mensual!$B$2:$S$83,52,K$12)="",NA(),INDEX(Mensual!$B$2:$S$83,52,K$12))))
A67: =IF($C$9="Anual",IF(53<=7,INDEX(Anual!$A$2:$A$8,53),""),IF(53<=82,INDEX(Mensual!$A$2:$A$83,53),"")) | B67: =IF($C$10="Sí",H67/H$13*100,H67) | C67: =IF($C$10="Sí",I67/I$13*100,I67) | D67: =IF($C$10="Sí",J67/J$13*100,J67) | E67: =IF($C$10="Sí",K67/K$13*100,K67) | H67: =IF(OR($A67="",H$12=0),NA(),IF($C$9="Anual",IF(INDEX(Anual!$B$2:$J$8,53,H$12)="",NA(),INDEX(Anual!$B$2:$J$8,53,H$12)),IF(INDEX(Mensual!$B$2:$S$83,53,H$12)="",NA(),INDEX(Mensual!$B$2:$S$83,53,H$12)))) | I67: =IF(OR($A67="",I$12=0),NA(),IF($C$9="Anual",IF(INDEX(Anual!$B$2:$J$8,53,I$12)="",NA(),INDEX(Anual!$B$2:$J$8,53,I$12)),IF(INDEX(Mensual!$B$2:$S$83,53,I$12)="",NA(),INDEX(Mensual!$B$2:$S$83,53,I$12)))) | J67: =IF(OR($A67="",J$12=0),NA(),IF($C$9="Anual",IF(INDEX(Anual!$B$2:$J$8,53,J$12)="",NA(),INDEX(Anual!$B$2:$J$8,53,J$12)),IF(INDEX(Mensual!$B$2:$S$83,53,J$12)="",NA(),INDEX(Mensual!$B$2:$S$83,53,J$12)))) | K67: =IF(OR($A67="",K$12=0),NA(),IF($C$9="Anual",IF(INDEX(Anual!$B$2:$J$8,53,K$12)="",NA(),INDEX(Anual!$B$2:$J$8,53,K$12)),IF(INDEX(Mensual!$B$2:$S$83,53,K$12)="",NA(),INDEX(Mensual!$B$2:$S$83,53,K$12))))
A68: =IF($C$9="Anual",IF(54<=7,INDEX(Anual!$A$2:$A$8,54),""),IF(54<=82,INDEX(Mensual!$A$2:$A$83,54),"")) | B68: =IF($C$10="Sí",H68/H$13*100,H68) | C68: =IF($C$10="Sí",I68/I$13*100,I68) | D68: =IF($C$10="Sí",J68/J$13*100,J68) | E68: =IF($C$10="Sí",K68/K$13*100,K68) | H68: =IF(OR($A68="",H$12=0),NA(),IF($C$9="Anual",IF(INDEX(Anual!$B$2:$J$8,54,H$12)="",NA(),INDEX(Anual!$B$2:$J$8,54,H$12)),IF(INDEX(Mensual!$B$2:$S$83,54,H$12)="",NA(),INDEX(Mensual!$B$2:$S$83,54,H$12)))) | I68: =IF(OR($A68="",I$12=0),NA(),IF($C$9="Anual",IF(INDEX(Anual!$B$2:$J$8,54,I$12)="",NA(),INDEX(Anual!$B$2:$J$8,54,I$12)),IF(INDEX(Mensual!$B$2:$S$83,54,I$12)="",NA(),INDEX(Mensual!$B$2:$S$83,54,I$12)))) | J68: =IF(OR($A68="",J$12=0),NA(),IF($C$9="Anual",IF(INDEX(Anual!$B$2:$J$8,54,J$12)="",NA(),INDEX(Anual!$B$2:$J$8,54,J$12)),IF(INDEX(Mensual!$B$2:$S$83,54,J$12)="",NA(),INDEX(Mensual!$B$2:$S$83,54,J$12)))) | K68: =IF(OR($A68="",K$12=0),NA(),IF($C$9="Anual",IF(INDEX(Anual!$B$2:$J$8,54,K$12)="",NA(),INDEX(Anual!$B$2:$J$8,54,K$12)),IF(INDEX(Mensual!$B$2:$S$83,54,K$12)="",NA(),INDEX(Mensual!$B$2:$S$83,54,K$12))))
A69: =IF($C$9="Anual",IF(55<=7,INDEX(Anual!$A$2:$A$8,55),""),IF(55<=82,INDEX(Mensual!$A$2:$A$83,55),"")) | B69: =IF($C$10="Sí",H69/H$13*100,H69) | C69: =IF($C$10="Sí",I69/I$13*100,I69) | D69: =IF($C$10="Sí",J69/J$13*100,J69) | E69: =IF($C$10="Sí",K69/K$13*100,K69) | H69: =IF(OR($A69="",H$12=0),NA(),IF($C$9="Anual",IF(INDEX(Anual!$B$2:$J$8,55,H$12)="",NA(),INDEX(Anual!$B$2:$J$8,55,H$12)),IF(INDEX(Mensual!$B$2:$S$83,55,H$12)="",NA(),INDEX(Mensual!$B$2:$S$83,55,H$12)))) | I69: =IF(OR($A69="",I$12=0),NA(),IF($C$9="Anual",IF(INDEX(Anual!$B$2:$J$8,55,I$12)="",NA(),INDEX(Anual!$B$2:$J$8,55,I$12)),IF(INDEX(Mensual!$B$2:$S$83,55,I$12)="",NA(),INDEX(Mensual!$B$2:$S$83,55,I$12)))) | J69: =IF(OR($A69="",J$12=0),NA(),IF($C$9="Anual",IF(INDEX(Anual!$B$2:$J$8,55,J$12)="",NA(),INDEX(Anual!$B$2:$J$8,55,J$12)),IF(INDEX(Mensual!$B$2:$S$83,55,J$12)="",NA(),INDEX(Mensual!$B$2:$S$83,55,J$12)))) | K69: =IF(OR($A69="",K$12=0),NA(),IF($C$9="Anual",IF(INDEX(Anual!$B$2:$J$8,55,K$12)="",NA(),INDEX(Anual!$B$2:$J$8,55,K$12)),IF(INDEX(Mensual!$B$2:$S$83,55,K$12)="",NA(),INDEX(Mensual!$B$2:$S$83,55,K$12))))
A70: =IF($C$9="Anual",IF(56<=7,INDEX(Anual!$A$2:$A$8,56),""),IF(56<=82,INDEX(Mensual!$A$2:$A$83,56),"")) | B70: =IF($C$10="Sí",H70/H$13*100,H70) | C70: =IF($C$10="Sí",I70/I$13*100,I70) | D70: =IF($C$10="Sí",J70/J$13*100,J70) | E70: =IF($C$10="Sí",K70/K$13*100,K70) | H70: =IF(OR($A70="",H$12=0),NA(),IF($C$9="Anual",IF(INDEX(Anual!$B$2:$J$8,56,H$12)="",NA(),INDEX(Anual!$B$2:$J$8,56,H$12)),IF(INDEX(Mensual!$B$2:$S$83,56,H$12)="",NA(),INDEX(Mensual!$B$2:$S$83,56,H$12)))) | I70: =IF(OR($A70="",I$12=0),NA(),IF($C$9="Anual",IF(INDEX(Anual!$B$2:$J$8,56,I$12)="",NA(),INDEX(Anual!$B$2:$J$8,56,I$12)),IF(INDEX(Mensual!$B$2:$S$83,56,I$12)="",NA(),INDEX(Mensual!$B$2:$S$83,56,I$12)))) | J70: =IF(OR($A70="",J$12=0),NA(),IF($C$9="Anual",IF(INDEX(Anual!$B$2:$J$8,56,J$12)="",NA(),INDEX(Anual!$B$2:$J$8,56,J$12)),IF(INDEX(Mensual!$B$2:$S$83,56,J$12)="",NA(),INDEX(Mensual!$B$2:$S$83,56,J$12)))) | K70: =IF(OR($A70="",K$12=0),NA(),IF($C$9="Anual",IF(INDEX(Anual!$B$2:$J$8,56,K$12)="",NA(),INDEX(Anual!$B$2:$J$8,56,K$12)),IF(INDEX(Mensual!$B$2:$S$83,56,K$12)="",NA(),INDEX(Mensual!$B$2:$S$83,56,K$12))))
A71: =IF($C$9="Anual",IF(57<=7,INDEX(Anual!$A$2:$A$8,57),""),IF(57<=82,INDEX(Mensual!$A$2:$A$83,57),"")) | B71: =IF($C$10="Sí",H71/H$13*100,H71) | C71: =IF($C$10="Sí",I71/I$13*100,I71) | D71: =IF($C$10="Sí",J71/J$13*100,J71) | E71: =IF($C$10="Sí",K71/K$13*100,K71) | H71: =IF(OR($A71="",H$12=0),NA(),IF($C$9="Anual",IF(INDEX(Anual!$B$2:$J$8,57,H$12)="",NA(),INDEX(Anual!$B$2:$J$8,57,H$12)),IF(INDEX(Mensual!$B$2:$S$83,57,H$12)="",NA(),INDEX(Mensual!$B$2:$S$83,57,H$12)))) | I71: =IF(OR($A71="",I$12=0),NA(),IF($C$9="Anual",IF(INDEX(Anual!$B$2:$J$8,57,I$12)="",NA(),INDEX(Anual!$B$2:$J$8,57,I$12)),IF(INDEX(Mensual!$B$2:$S$83,57,I$12)="",NA(),INDEX(Mensual!$B$2:$S$83,57,I$12)))) | J71: =IF(OR($A71="",J$12=0),NA(),IF($C$9="Anual",IF(INDEX(Anual!$B$2:$J$8,57,J$12)="",NA(),INDEX(Anual!$B$2:$J$8,57,J$12)),IF(INDEX(Mensual!$B$2:$S$83,57,J$12)="",NA(),INDEX(Mensual!$B$2:$S$83,57,J$12)))) | K71: =IF(OR($A71="",K$12=0),NA(),IF($C$9="Anual",IF(INDEX(Anual!$B$2:$J$8,57,K$12)="",NA(),INDEX(Anual!$B$2:$J$8,57,K$12)),IF(INDEX(Mensual!$B$2:$S$83,57,K$12)="",NA(),INDEX(Mensual!$B$2:$S$83,57,K$12))))
A72: =IF($C$9="Anual",IF(58<=7,INDEX(Anual!$A$2:$A$8,58),""),IF(58<=82,INDEX(Mensual!$A$2:$A$83,58),"")) | B72: =IF($C$10="Sí",H72/H$13*100,H72) | C72: =IF($C$10="Sí",I72/I$13*100,I72) | D72: =IF($C$10="Sí",J72/J$13*100,J72) | E72: =IF($C$10="Sí",K72/K$13*100,K72) | H72: =IF(OR($A72="",H$12=0),NA(),IF($C$9="Anual",IF(INDEX(Anual!$B$2:$J$8,58,H$12)="",NA(),INDEX(Anual!$B$2:$J$8,58,H$12)),IF(INDEX(Mensual!$B$2:$S$83,58,H$12)="",NA(),INDEX(Mensual!$B$2:$S$83,58,H$12)))) | I72: =IF(OR($A72="",I$12=0),NA(),IF($C$9="Anual",IF(INDEX(Anual!$B$2:$J$8,58,I$12)="",NA(),INDEX(Anual!$B$2:$J$8,58,I$12)),IF(INDEX(Mensual!$B$2:$S$83,58,I$12)="",NA(),INDEX(Mensual!$B$2:$S$83,58,I$12)))) | J72: =IF(OR($A72="",J$12=0),NA(),IF($C$9="Anual",IF(INDEX(Anual!$B$2:$J$8,58,J$12)="",NA(),INDEX(Anual!$B$2:$J$8,58,J$12)),IF(INDEX(Mensual!$B$2:$S$83,58,J$12)="",NA(),INDEX(Mensual!$B$2:$S$83,58,J$12)))) | K72: =IF(OR($A72="",K$12=0),NA(),IF($C$9="Anual",IF(INDEX(Anual!$B$2:$J$8,58,K$12)="",NA(),INDEX(Anual!$B$2:$J$8,58,K$12)),IF(INDEX(Mensual!$B$2:$S$83,58,K$12)="",NA(),INDEX(Mensual!$B$2:$S$83,58,K$12))))
A73: =IF($C$9="Anual",IF(59<=7,INDEX(Anual!$A$2:$A$8,59),""),IF(59<=82,INDEX(Mensual!$A$2:$A$83,59),"")) | B73: =IF($C$10="Sí",H73/H$13*100,H73) | C73: =IF($C$10="Sí",I73/I$13*100,I73) | D73: =IF($C$10="Sí",J73/J$13*100,J73) | E73: =IF($C$10="Sí",K73/K$13*100,K73) | H73: =IF(OR($A73="",H$12=0),NA(),IF($C$9="Anual",IF(INDEX(Anual!$B$2:$J$8,59,H$12)="",NA(),INDEX(Anual!$B$2:$J$8,59,H$12)),IF(INDEX(Mensual!$B$2:$S$83,59,H$12)="",NA(),INDEX(Mensual!$B$2:$S$83,59,H$12)))) | I73: =IF(OR($A73="",I$12=0),NA(),IF($C$9="Anual",IF(INDEX(Anual!$B$2:$J$8,59,I$12)="",NA(),INDEX(Anual!$B$2:$J$8,59,I$12)),IF(INDEX(Mensual!$B$2:$S$83,59,I$12)="",NA(),INDEX(Mensual!$B$2:$S$83,59,I$12)))) | J73: =IF(OR($A73="",J$12=0),NA(),IF($C$9="Anual",IF(INDEX(Anual!$B$2:$J$8,59,J$12)="",NA(),INDEX(Anual!$B$2:$J$8,59,J$12)),IF(INDEX(Mensual!$B$2:$S$83,59,J$12)="",NA(),INDEX(Mensual!$B$2:$S$83,59,J$12)))) | K73: =IF(OR($A73="",K$12=0),NA(),IF($C$9="Anual",IF(INDEX(Anual!$B$2:$J$8,59,K$12)="",NA(),INDEX(Anual!$B$2:$J$8,59,K$12)),IF(INDEX(Mensual!$B$2:$S$83,59,K$12)="",NA(),INDEX(Mensual!$B$2:$S$83,59,K$12))))
A74: =IF($C$9="Anual",IF(60<=7,INDEX(Anual!$A$2:$A$8,60),""),IF(60<=82,INDEX(Mensual!$A$2:$A$83,60),"")) | B74: =IF($C$10="Sí",H74/H$13*100,H74) | C74: =IF($C$10="Sí",I74/I$13*100,I74) | D74: =IF($C$10="Sí",J74/J$13*100,J74) | E74: =IF($C$10="Sí",K74/K$13*100,K74) | H74: =IF(OR($A74="",H$12=0),NA(),IF($C$9="Anual",IF(INDEX(Anual!$B$2:$J$8,60,H$12)="",NA(),INDEX(Anual!$B$2:$J$8,60,H$12)),IF(INDEX(Mensual!$B$2:$S$83,60,H$12)="",NA(),INDEX(Mensual!$B$2:$S$83,60,H$12)))) | I74: =IF(OR($A74="",I$12=0),NA(),IF($C$9="Anual",IF(INDEX(Anual!$B$2:$J$8,60,I$12)="",NA(),INDEX(Anual!$B$2:$J$8,60,I$12)),IF(INDEX(Mensual!$B$2:$S$83,60,I$12)="",NA(),INDEX(Mensual!$B$2:$S$83,60,I$12)))) | J74: =IF(OR($A74="",J$12=0),NA(),IF($C$9="Anual",IF(INDEX(Anual!$B$2:$J$8,60,J$12)="",NA(),INDEX(Anual!$B$2:$J$8,60,J$12)),IF(INDEX(Mensual!$B$2:$S$83,60,J$12)="",NA(),INDEX(Mensual!$B$2:$S$83,60,J$12)))) | K74: =IF(OR($A74="",K$12=0),NA(),IF($C$9="Anual",IF(INDEX(Anual!$B$2:$J$8,60,K$12)="",NA(),INDEX(Anual!$B$2:$J$8,60,K$12)),IF(INDEX(Mensual!$B$2:$S$83,60,K$12)="",NA(),INDEX(Mensual!$B$2:$S$83,60,K$12))))
A75: =IF($C$9="Anual",IF(61<=7,INDEX(Anual!$A$2:$A$8,61),""),IF(61<=82,INDEX(Mensual!$A$2:$A$83,61),"")) | B75: =IF($C$10="Sí",H75/H$13*100,H75) | C75: =IF($C$10="Sí",I75/I$13*100,I75) | D75: =IF($C$10="Sí",J75/J$13*100,J75) | E75: =IF($C$10="Sí",K75/K$13*100,K75) | H75: =IF(OR($A75="",H$12=0),NA(),IF($C$9="Anual",IF(INDEX(Anual!$B$2:$J$8,61,H$12)="",NA(),INDEX(Anual!$B$2:$J$8,61,H$12)),IF(INDEX(Mensual!$B$2:$S$83,61,H$12)="",NA(),INDEX(Mensual!$B$2:$S$83,61,H$12)))) | I75: =IF(OR($A75="",I$12=0),NA(),IF($C$9="Anual",IF(INDEX(Anual!$B$2:$J$8,61,I$12)="",NA(),INDEX(Anual!$B$2:$J$8,61,I$12)),IF(INDEX(Mensual!$B$2:$S$83,61,I$12)="",NA(),INDEX(Mensual!$B$2:$S$83,61,I$12)))) | J75: =IF(OR($A75="",J$12=0),NA(),IF($C$9="Anual",IF(INDEX(Anual!$B$2:$J$8,61,J$12)="",NA(),INDEX(Anual!$B$2:$J$8,61,J$12)),IF(INDEX(Mensual!$B$2:$S$83,61,J$12)="",NA(),INDEX(Mensual!$B$2:$S$83,61,J$12)))) | K75: =IF(OR($A75="",K$12=0),NA(),IF($C$9="Anual",IF(INDEX(Anual!$B$2:$J$8,61,K$12)="",NA(),INDEX(Anual!$B$2:$J$8,61,K$12)),IF(INDEX(Mensual!$B$2:$S$83,61,K$12)="",NA(),INDEX(Mensual!$B$2:$S$83,61,K$12))))
A76: =IF($C$9="Anual",IF(62<=7,INDEX(Anual!$A$2:$A$8,62),""),IF(62<=82,INDEX(Mensual!$A$2:$A$83,62),"")) | B76: =IF($C$10="Sí",H76/H$13*100,H76) | C76: =IF($C$10="Sí",I76/I$13*100,I76) | D76: =IF($C$10="Sí",J76/J$13*100,J76) | E76: =IF($C$10="Sí",K76/K$13*100,K76) | H76: =IF(OR($A76="",H$12=0),NA(),IF($C$9="Anual",IF(INDEX(Anual!$B$2:$J$8,62,H$12)="",NA(),INDEX(Anual!$B$2:$J$8,62,H$12)),IF(INDEX(Mensual!$B$2:$S$83,62,H$12)="",NA(),INDEX(Mensual!$B$2:$S$83,62,H$12)))) | I76: =IF(OR($A76="",I$12=0),NA(),IF($C$9="Anual",IF(INDEX(Anual!$B$2:$J$8,62,I$12)="",NA(),INDEX(Anual!$B$2:$J$8,62,I$12)),IF(INDEX(Mensual!$B$2:$S$83,62,I$12)="",NA(),INDEX(Mensual!$B$2:$S$83,62,I$12)))) | J76: =IF(OR($A76="",J$12=0),NA(),IF($C$9="Anual",IF(INDEX(Anual!$B$2:$J$8,62,J$12)="",NA(),INDEX(Anual!$B$2:$J$8,62,J$12)),IF(INDEX(Mensual!$B$2:$S$83,62,J$12)="",NA(),INDEX(Mensual!$B$2:$S$83,62,J$12)))) | K76: =IF(OR($A76="",K$12=0),NA(),IF($C$9="Anual",IF(INDEX(Anual!$B$2:$J$8,62,K$12)="",NA(),INDEX(Anual!$B$2:$J$8,62,K$12)),IF(INDEX(Mensual!$B$2:$S$83,62,K$12)="",NA(),INDEX(Mensual!$B$2:$S$83,62,K$12))))
A77: =IF($C$9="Anual",IF(63<=7,INDEX(Anual!$A$2:$A$8,63),""),IF(63<=82,INDEX(Mensual!$A$2:$A$83,63),"")) | B77: =IF($C$10="Sí",H77/H$13*100,H77) | C77: =IF($C$10="Sí",I77/I$13*100,I77) | D77: =IF($C$10="Sí",J77/J$13*100,J77) | E77: =IF($C$10="Sí",K77/K$13*100,K77) | H77: =IF(OR($A77="",H$12=0),NA(),IF($C$9="Anual",IF(INDEX(Anual!$B$2:$J$8,63,H$12)="",NA(),INDEX(Anual!$B$2:$J$8,63,H$12)),IF(INDEX(Mensual!$B$2:$S$83,63,H$12)="",NA(),INDEX(Mensual!$B$2:$S$83,63,H$12)))) | I77: =IF(OR($A77="",I$12=0),NA(),IF($C$9="Anual",IF(INDEX(Anual!$B$2:$J$8,63,I$12)="",NA(),INDEX(Anual!$B$2:$J$8,63,I$12)),IF(INDEX(Mensual!$B$2:$S$83,63,I$12)="",NA(),INDEX(Mensual!$B$2:$S$83,63,I$12)))) | J77: =IF(OR($A77="",J$12=0),NA(),IF($C$9="Anual",IF(INDEX(Anual!$B$2:$J$8,63,J$12)="",NA(),INDEX(Anual!$B$2:$J$8,63,J$12)),IF(INDEX(Mensual!$B$2:$S$83,63,J$12)="",NA(),INDEX(Mensual!$B$2:$S$83,63,J$12)))) | K77: =IF(OR($A77="",K$12=0),NA(),IF($C$9="Anual",IF(INDEX(Anual!$B$2:$J$8,63,K$12)="",NA(),INDEX(Anual!$B$2:$J$8,63,K$12)),IF(INDEX(Mensual!$B$2:$S$83,63,K$12)="",NA(),INDEX(Mensual!$B$2:$S$83,63,K$12))))
A78: =IF($C$9="Anual",IF(64<=7,INDEX(Anual!$A$2:$A$8,64),""),IF(64<=82,INDEX(Mensual!$A$2:$A$83,64),"")) | B78: =IF($C$10="Sí",H78/H$13*100,H78) | C78: =IF($C$10="Sí",I78/I$13*100,I78) | D78: =IF($C$10="Sí",J78/J$13*100,J78) | E78: =IF($C$10="Sí",K78/K$13*100,K78) | H78: =IF(OR($A78="",H$12=0),NA(),IF($C$9="Anual",IF(INDEX(Anual!$B$2:$J$8,64,H$12)="",NA(),INDEX(Anual!$B$2:$J$8,64,H$12)),IF(INDEX(Mensual!$B$2:$S$83,64,H$12)="",NA(),INDEX(Mensual!$B$2:$S$83,64,H$12)))) | I78: =IF(OR($A78="",I$12=0),NA(),IF($C$9="Anual",IF(INDEX(Anual!$B$2:$J$8,64,I$12)="",NA(),INDEX(Anual!$B$2:$J$8,64,I$12)),IF(INDEX(Mensual!$B$2:$S$83,64,I$12)="",NA(),INDEX(Mensual!$B$2:$S$83,64,I$12)))) | J78: =IF(OR($A78="",J$12=0),NA(),IF($C$9="Anual",IF(INDEX(Anual!$B$2:$J$8,64,J$12)="",NA(),INDEX(Anual!$B$2:$J$8,64,J$12)),IF(INDEX(Mensual!$B$2:$S$83,64,J$12)="",NA(),INDEX(Mensual!$B$2:$S$83,64,J$12)))) | K78: =IF(OR($A78="",K$12=0),NA(),IF($C$9="Anual",IF(INDEX(Anual!$B$2:$J$8,64,K$12)="",NA(),INDEX(Anual!$B$2:$J$8,64,K$12)),IF(INDEX(Mensual!$B$2:$S$83,64,K$12)="",NA(),INDEX(Mensual!$B$2:$S$83,64,K$12))))
A79: =IF($C$9="Anual",IF(65<=7,INDEX(Anual!$A$2:$A$8,65),""),IF(65<=82,INDEX(Mensual!$A$2:$A$83,65),"")) | B79: =IF($C$10="Sí",H79/H$13*100,H79) | C79: =IF($C$10="Sí",I79/I$13*100,I79) | D79: =IF($C$10="Sí",J79/J$13*100,J79) | E79: =IF($C$10="Sí",K79/K$13*100,K79) | H79: =IF(OR($A79="",H$12=0),NA(),IF($C$9="Anual",IF(INDEX(Anual!$B$2:$J$8,65,H$12)="",NA(),INDEX(Anual!$B$2:$J$8,65,H$12)),IF(INDEX(Mensual!$B$2:$S$83,65,H$12)="",NA(),INDEX(Mensual!$B$2:$S$83,65,H$12)))) | I79: =IF(OR($A79="",I$12=0),NA(),IF($C$9="Anual",IF(INDEX(Anual!$B$2:$J$8,65,I$12)="",NA(),INDEX(Anual!$B$2:$J$8,65,I$12)),IF(INDEX(Mensual!$B$2:$S$83,65,I$12)="",NA(),INDEX(Mensual!$B$2:$S$83,65,I$12)))) | J79: =IF(OR($A79="",J$12=0),NA(),IF($C$9="Anual",IF(INDEX(Anual!$B$2:$J$8,65,J$12)="",NA(),INDEX(Anual!$B$2:$J$8,65,J$12)),IF(INDEX(Mensual!$B$2:$S$83,65,J$12)="",NA(),INDEX(Mensual!$B$2:$S$83,65,J$12)))) | K79: =IF(OR($A79="",K$12=0),NA(),IF($C$9="Anual",IF(INDEX(Anual!$B$2:$J$8,65,K$12)="",NA(),INDEX(Anual!$B$2:$J$8,65,K$12)),IF(INDEX(Mensual!$B$2:$S$83,65,K$12)="",NA(),INDEX(Mensual!$B$2:$S$83,65,K$12))))
A80: =IF($C$9="Anual",IF(66<=7,INDEX(Anual!$A$2:$A$8,66),""),IF(66<=82,INDEX(Mensual!$A$2:$A$83,66),"")) | B80: =IF($C$10="Sí",H80/H$13*100,H80) | C80: =IF($C$10="Sí",I80/I$13*100,I80) | D80: =IF($C$10="Sí",J80/J$13*100,J80) | E80: =IF($C$10="Sí",K80/K$13*100,K80) | H80: =IF(OR($A80="",H$12=0),NA(),IF($C$9="Anual",IF(INDEX(Anual!$B$2:$J$8,66,H$12)="",NA(),INDEX(Anual!$B$2:$J$8,66,H$12)),IF(INDEX(Mensual!$B$2:$S$83,66,H$12)="",NA(),INDEX(Mensual!$B$2:$S$83,66,H$12)))) | I80: =IF(OR($A80="",I$12=0),NA(),IF($C$9="Anual",IF(INDEX(Anual!$B$2:$J$8,66,I$12)="",NA(),INDEX(Anual!$B$2:$J$8,66,I$12)),IF(INDEX(Mensual!$B$2:$S$83,66,I$12)="",NA(),INDEX(Mensual!$B$2:$S$83,66,I$12)))) | J80: =IF(OR($A80="",J$12=0),NA(),IF($C$9="Anual",IF(INDEX(Anual!$B$2:$J$8,66,J$12)="",NA(),INDEX(Anual!$B$2:$J$8,66,J$12)),IF(INDEX(Mensual!$B$2:$S$83,66,J$12)="",NA(),INDEX(Mensual!$B$2:$S$83,66,J$12)))) | K80: =IF(OR($A80="",K$12=0),NA(),IF($C$9="Anual",IF(INDEX(Anual!$B$2:$J$8,66,K$12)="",NA(),INDEX(Anual!$B$2:$J$8,66,K$12)),IF(INDEX(Mensual!$B$2:$S$83,66,K$12)="",NA(),INDEX(Mensual!$B$2:$S$83,66,K$12))))
A81: =IF($C$9="Anual",IF(67<=7,INDEX(Anual!$A$2:$A$8,67),""),IF(67<=82,INDEX(Mensual!$A$2:$A$83,67),"")) | B81: =IF($C$10="Sí",H81/H$13*100,H81) | C81: =IF($C$10="Sí",I81/I$13*100,I81) | D81: =IF($C$10="Sí",J81/J$13*100,J81) | E81: =IF($C$10="Sí",K81/K$13*100,K81) | H81: =IF(OR($A81="",H$12=0),NA(),IF($C$9="Anual",IF(INDEX(Anual!$B$2:$J$8,67,H$12)="",NA(),INDEX(Anual!$B$2:$J$8,67,H$12)),IF(INDEX(Mensual!$B$2:$S$83,67,H$12)="",NA(),INDEX(Mensual!$B$2:$S$83,67,H$12)))) | I81: =IF(OR($A81="",I$12=0),NA(),IF($C$9="Anual",IF(INDEX(Anual!$B$2:$J$8,67,I$12)="",NA(),INDEX(Anual!$B$2:$J$8,67,I$12)),IF(INDEX(Mensual!$B$2:$S$83,67,I$12)="",NA(),INDEX(Mensual!$B$2:$S$83,67,I$12)))) | J81: =IF(OR($A81="",J$12=0),NA(),IF($C$9="Anual",IF(INDEX(Anual!$B$2:$J$8,67,J$12)="",NA(),INDEX(Anual!$B$2:$J$8,67,J$12)),IF(INDEX(Mensual!$B$2:$S$83,67,J$12)="",NA(),INDEX(Mensual!$B$2:$S$83,67,J$12)))) | K81: =IF(OR($A81="",K$12=0),NA(),IF($C$9="Anual",IF(INDEX(Anual!$B$2:$J$8,67,K$12)="",NA(),INDEX(Anual!$B$2:$J$8,67,K$12)),IF(INDEX(Mensual!$B$2:$S$83,67,K$12)="",NA(),INDEX(Mensual!$B$2:$S$83,67,K$12))))
A82: =IF($C$9="Anual",IF(68<=7,INDEX(Anual!$A$2:$A$8,68),""),IF(68<=82,INDEX(Mensual!$A$2:$A$83,68),"")) | B82: =IF($C$10="Sí",H82/H$13*100,H82) | C82: =IF($C$10="Sí",I82/I$13*100,I82) | D82: =IF($C$10="Sí",J82/J$13*100,J82) | E82: =IF($C$10="Sí",K82/K$13*100,K82) | H82: =IF(OR($A82="",H$12=0),NA(),IF($C$9="Anual",IF(INDEX(Anual!$B$2:$J$8,68,H$12)="",NA(),INDEX(Anual!$B$2:$J$8,68,H$12)),IF(INDEX(Mensual!$B$2:$S$83,68,H$12)="",NA(),INDEX(Mensual!$B$2:$S$83,68,H$12)))) | I82: =IF(OR($A82="",I$12=0),NA(),IF($C$9="Anual",IF(INDEX(Anual!$B$2:$J$8,68,I$12)="",NA(),INDEX(Anual!$B$2:$J$8,68,I$12)),IF(INDEX(Mensual!$B$2:$S$83,68,I$12)="",NA(),INDEX(Mensual!$B$2:$S$83,68,I$12)))) | J82: =IF(OR($A82="",J$12=0),NA(),IF($C$9="Anual",IF(INDEX(Anual!$B$2:$J$8,68,J$12)="",NA(),INDEX(Anual!$B$2:$J$8,68,J$12)),IF(INDEX(Mensual!$B$2:$S$83,68,J$12)="",NA(),INDEX(Mensual!$B$2:$S$83,68,J$12)))) | K82: =IF(OR($A82="",K$12=0),NA(),IF($C$9="Anual",IF(INDEX(Anual!$B$2:$J$8,68,K$12)="",NA(),INDEX(Anual!$B$2:$J$8,68,K$12)),IF(INDEX(Mensual!$B$2:$S$83,68,K$12)="",NA(),INDEX(Mensual!$B$2:$S$83,68,K$12))))
A83: =IF($C$9="Anual",IF(69<=7,INDEX(Anual!$A$2:$A$8,69),""),IF(69<=82,INDEX(Mensual!$A$2:$A$83,69),"")) | B83: =IF($C$10="Sí",H83/H$13*100,H83) | C83: =IF($C$10="Sí",I83/I$13*100,I83) | D83: =IF($C$10="Sí",J83/J$13*100,J83) | E83: =IF($C$10="Sí",K83/K$13*100,K83) | H83: =IF(OR($A83="",H$12=0),NA(),IF($C$9="Anual",IF(INDEX(Anual!$B$2:$J$8,69,H$12)="",NA(),INDEX(Anual!$B$2:$J$8,69,H$12)),IF(INDEX(Mensual!$B$2:$S$83,69,H$12)="",NA(),INDEX(Mensual!$B$2:$S$83,69,H$12)))) | I83: =IF(OR($A83="",I$12=0),NA(),IF($C$9="Anual",IF(INDEX(Anual!$B$2:$J$8,69,I$12)="",NA(),INDEX(Anual!$B$2:$J$8,69,I$12)),IF(INDEX(Mensual!$B$2:$S$83,69,I$12)="",NA(),INDEX(Mensual!$B$2:$S$83,69,I$12)))) | J83: =IF(OR($A83="",J$12=0),NA(),IF($C$9="Anual",IF(INDEX(Anual!$B$2:$J$8,69,J$12)="",NA(),INDEX(Anual!$B$2:$J$8,69,J$12)),IF(INDEX(Mensual!$B$2:$S$83,69,J$12)="",NA(),INDEX(Mensual!$B$2:$S$83,69,J$12)))) | K83: =IF(OR($A83="",K$12=0),NA(),IF($C$9="Anual",IF(INDEX(Anual!$B$2:$J$8,69,K$12)="",NA(),INDEX(Anual!$B$2:$J$8,69,K$12)),IF(INDEX(Mensual!$B$2:$S$83,69,K$12)="",NA(),INDEX(Mensual!$B$2:$S$83,69,K$12))))
A84: =IF($C$9="Anual",IF(70<=7,INDEX(Anual!$A$2:$A$8,70),""),IF(70<=82,INDEX(Mensual!$A$2:$A$83,70),"")) | B84: =IF($C$10="Sí",H84/H$13*100,H84) | C84: =IF($C$10="Sí",I84/I$13*100,I84) | D84: =IF($C$10="Sí",J84/J$13*100,J84) | E84: =IF($C$10="Sí",K84/K$13*100,K84) | H84: =IF(OR($A84="",H$12=0),NA(),IF($C$9="Anual",IF(INDEX(Anual!$B$2:$J$8,70,H$12)="",NA(),INDEX(Anual!$B$2:$J$8,70,H$12)),IF(INDEX(Mensual!$B$2:$S$83,70,H$12)="",NA(),INDEX(Mensual!$B$2:$S$83,70,H$12)))) | I84: =IF(OR($A84="",I$12=0),NA(),IF($C$9="Anual",IF(INDEX(Anual!$B$2:$J$8,70,I$12)="",NA(),INDEX(Anual!$B$2:$J$8,70,I$12)),IF(INDEX(Mensual!$B$2:$S$83,70,I$12)="",NA(),INDEX(Mensual!$B$2:$S$83,70,I$12)))) | J84: =IF(OR($A84="",J$12=0),NA(),IF($C$9="Anual",IF(INDEX(Anual!$B$2:$J$8,70,J$12)="",NA(),INDEX(Anual!$B$2:$J$8,70,J$12)),IF(INDEX(Mensual!$B$2:$S$83,70,J$12)="",NA(),INDEX(Mensual!$B$2:$S$83,70,J$12)))) | K84: =IF(OR($A84="",K$12=0),NA(),IF($C$9="Anual",IF(INDEX(Anual!$B$2:$J$8,70,K$12)="",NA(),INDEX(Anual!$B$2:$J$8,70,K$12)),IF(INDEX(Mensual!$B$2:$S$83,70,K$12)="",NA(),INDEX(Mensual!$B$2:$S$83,70,K$12))))
A85: =IF($C$9="Anual",IF(71<=7,INDEX(Anual!$A$2:$A$8,71),""),IF(71<=82,INDEX(Mensual!$A$2:$A$83,71),"")) | B85: =IF($C$10="Sí",H85/H$13*100,H85) | C85: =IF($C$10="Sí",I85/I$13*100,I85) | D85: =IF($C$10="Sí",J85/J$13*100,J85) | E85: =IF($C$10="Sí",K85/K$13*100,K85) | H85: =IF(OR($A85="",H$12=0),NA(),IF($C$9="Anual",IF(INDEX(Anual!$B$2:$J$8,71,H$12)="",NA(),INDEX(Anual!$B$2:$J$8,71,H$12)),IF(INDEX(Mensual!$B$2:$S$83,71,H$12)="",NA(),INDEX(Mensual!$B$2:$S$83,71,H$12)))) | I85: =IF(OR($A85="",I$12=0),NA(),IF($C$9="Anual",IF(INDEX(Anual!$B$2:$J$8,71,I$12)="",NA(),INDEX(Anual!$B$2:$J$8,71,I$12)),IF(INDEX(Mensual!$B$2:$S$83,71,I$12)="",NA(),INDEX(Mensual!$B$2:$S$83,71,I$12)))) | J85: =IF(OR($A85="",J$12=0),NA(),IF($C$9="Anual",IF(INDEX(Anual!$B$2:$J$8,71,J$12)="",NA(),INDEX(Anual!$B$2:$J$8,71,J$12)),IF(INDEX(Mensual!$B$2:$S$83,71,J$12)="",NA(),INDEX(Mensual!$B$2:$S$83,71,J$12)))) | K85: =IF(OR($A85="",K$12=0),NA(),IF($C$9="Anual",IF(INDEX(Anual!$B$2:$J$8,71,K$12)="",NA(),INDEX(Anual!$B$2:$J$8,71,K$12)),IF(INDEX(Mensual!$B$2:$S$83,71,K$12)="",NA(),INDEX(Mensual!$B$2:$S$83,71,K$12))))
A86: =IF($C$9="Anual",IF(72<=7,INDEX(Anual!$A$2:$A$8,72),""),IF(72<=82,INDEX(Mensual!$A$2:$A$83,72),"")) | B86: =IF($C$10="Sí",H86/H$13*100,H86) | C86: =IF($C$10="Sí",I86/I$13*100,I86) | D86: =IF($C$10="Sí",J86/J$13*100,J86) | E86: =IF($C$10="Sí",K86/K$13*100,K86) | H86: =IF(OR($A86="",H$12=0),NA(),IF($C$9="Anual",IF(INDEX(Anual!$B$2:$J$8,72,H$12)="",NA(),INDEX(Anual!$B$2:$J$8,72,H$12)),IF(INDEX(Mensual!$B$2:$S$83,72,H$12)="",NA(),INDEX(Mensual!$B$2:$S$83,72,H$12)))) | I86: =IF(OR($A86="",I$12=0),NA(),IF($C$9="Anual",IF(INDEX(Anual!$B$2:$J$8,72,I$12)="",NA(),INDEX(Anual!$B$2:$J$8,72,I$12)),IF(INDEX(Mensual!$B$2:$S$83,72,I$12)="",NA(),INDEX(Mensual!$B$2:$S$83,72,I$12)))) | J86: =IF(OR($A86="",J$12=0),NA(),IF($C$9="Anual",IF(INDEX(Anual!$B$2:$J$8,72,J$12)="",NA(),INDEX(Anual!$B$2:$J$8,72,J$12)),IF(INDEX(Mensual!$B$2:$S$83,72,J$12)="",NA(),INDEX(Mensual!$B$2:$S$83,72,J$12)))) | K86: =IF(OR($A86="",K$12=0),NA(),IF($C$9="Anual",IF(INDEX(Anual!$B$2:$J$8,72,K$12)="",NA(),INDEX(Anual!$B$2:$J$8,72,K$12)),IF(INDEX(Mensual!$B$2:$S$83,72,K$12)="",NA(),INDEX(Mensual!$B$2:$S$83,72,K$12))))
A87: =IF($C$9="Anual",IF(73<=7,INDEX(Anual!$A$2:$A$8,73),""),IF(73<=82,INDEX(Mensual!$A$2:$A$83,73),"")) | B87: =IF($C$10="Sí",H87/H$13*100,H87) | C87: =IF($C$10="Sí",I87/I$13*100,I87) | D87: =IF($C$10="Sí",J87/J$13*100,J87) | E87: =IF($C$10="Sí",K87/K$13*100,K87) | H87: =IF(OR($A87="",H$12=0),NA(),IF($C$9="Anual",IF(INDEX(Anual!$B$2:$J$8,73,H$12)="",NA(),INDEX(Anual!$B$2:$J$8,73,H$12)),IF(INDEX(Mensual!$B$2:$S$83,73,H$12)="",NA(),INDEX(Mensual!$B$2:$S$83,73,H$12)))) | I87: =IF(OR($A87="",I$12=0),NA(),IF($C$9="Anual",IF(INDEX(Anual!$B$2:$J$8,73,I$12)="",NA(),INDEX(Anual!$B$2:$J$8,73,I$12)),IF(INDEX(Mensual!$B$2:$S$83,73,I$12)="",NA(),INDEX(Mensual!$B$2:$S$83,73,I$12)))) | J87: =IF(OR($A87="",J$12=0),NA(),IF($C$9="Anual",IF(INDEX(Anual!$B$2:$J$8,73,J$12)="",NA(),INDEX(Anual!$B$2:$J$8,73,J$12)),IF(INDEX(Mensual!$B$2:$S$83,73,J$12)="",NA(),INDEX(Mensual!$B$2:$S$83,73,J$12)))) | K87: =IF(OR($A87="",K$12=0),NA(),IF($C$9="Anual",IF(INDEX(Anual!$B$2:$J$8,73,K$12)="",NA(),INDEX(Anual!$B$2:$J$8,73,K$12)),IF(INDEX(Mensual!$B$2:$S$83,73,K$12)="",NA(),INDEX(Mensual!$B$2:$S$83,73,K$12))))
A88: =IF($C$9="Anual",IF(74<=7,INDEX(Anual!$A$2:$A$8,74),""),IF(74<=82,INDEX(Mensual!$A$2:$A$83,74),"")) | B88: =IF($C$10="Sí",H88/H$13*100,H88) | C88: =IF($C$10="Sí",I88/I$13*100,I88) | D88: =IF($C$10="Sí",J88/J$13*100,J88) | E88: =IF($C$10="Sí",K88/K$13*100,K88) | H88: =IF(OR($A88="",H$12=0),NA(),IF($C$9="Anual",IF(INDEX(Anual!$B$2:$J$8,74,H$12)="",NA(),INDEX(Anual!$B$2:$J$8,74,H$12)),IF(INDEX(Mensual!$B$2:$S$83,74,H$12)="",NA(),INDEX(Mensual!$B$2:$S$83,74,H$12)))) | I88: =IF(OR($A88="",I$12=0),NA(),IF($C$9="Anual",IF(INDEX(Anual!$B$2:$J$8,74,I$12)="",NA(),INDEX(Anual!$B$2:$J$8,74,I$12)),IF(INDEX(Mensual!$B$2:$S$83,74,I$12)="",NA(),INDEX(Mensual!$B$2:$S$83,74,I$12)))) | J88: =IF(OR($A88="",J$12=0),NA(),IF($C$9="Anual",IF(INDEX(Anual!$B$2:$J$8,74,J$12)="",NA(),INDEX(Anual!$B$2:$J$8,74,J$12)),IF(INDEX(Mensual!$B$2:$S$83,74,J$12)="",NA(),INDEX(Mensual!$B$2:$S$83,74,J$12)))) | K88: =IF(OR($A88="",K$12=0),NA(),IF($C$9="Anual",IF(INDEX(Anual!$B$2:$J$8,74,K$12)="",NA(),INDEX(Anual!$B$2:$J$8,74,K$12)),IF(INDEX(Mensual!$B$2:$S$83,74,K$12)="",NA(),INDEX(Mensual!$B$2:$S$83,74,K$12))))
A89: =IF($C$9="Anual",IF(75<=7,INDEX(Anual!$A$2:$A$8,75),""),IF(75<=82,INDEX(Mensual!$A$2:$A$83,75),"")) | B89: =IF($C$10="Sí",H89/H$13*100,H89) | C89: =IF($C$10="Sí",I89/I$13*100,I89) | D89: =IF($C$10="Sí",J89/J$13*100,J89) | E89: =IF($C$10="Sí",K89/K$13*100,K89) | H89: =IF(OR($A89="",H$12=0),NA(),IF($C$9="Anual",IF(INDEX(Anual!$B$2:$J$8,75,H$12)="",NA(),INDEX(Anual!$B$2:$J$8,75,H$12)),IF(INDEX(Mensual!$B$2:$S$83,75,H$12)="",NA(),INDEX(Mensual!$B$2:$S$83,75,H$12)))) | I89: =IF(OR($A89="",I$12=0),NA(),IF($C$9="Anual",IF(INDEX(Anual!$B$2:$J$8,75,I$12)="",NA(),INDEX(Anual!$B$2:$J$8,75,I$12)),IF(INDEX(Mensual!$B$2:$S$83,75,I$12)="",NA(),INDEX(Mensual!$B$2:$S$83,75,I$12)))) | J89: =IF(OR($A89="",J$12=0),NA(),IF($C$9="Anual",IF(INDEX(Anual!$B$2:$J$8,75,J$12)="",NA(),INDEX(Anual!$B$2:$J$8,75,J$12)),IF(INDEX(Mensual!$B$2:$S$83,75,J$12)="",NA(),INDEX(Mensual!$B$2:$S$83,75,J$12)))) | K89: =IF(OR($A89="",K$12=0),NA(),IF($C$9="Anual",IF(INDEX(Anual!$B$2:$J$8,75,K$12)="",NA(),INDEX(Anual!$B$2:$J$8,75,K$12)),IF(INDEX(Mensual!$B$2:$S$83,75,K$12)="",NA(),INDEX(Mensual!$B$2:$S$83,75,K$12))))
A90: =IF($C$9="Anual",IF(76<=7,INDEX(Anual!$A$2:$A$8,76),""),IF(76<=82,INDEX(Mensual!$A$2:$A$83,76),"")) | B90: =IF($C$10="Sí",H90/H$13*100,H90) | C90: =IF($C$10="Sí",I90/I$13*100,I90) | D90: =IF($C$10="Sí",J90/J$13*100,J90) | E90: =IF($C$10="Sí",K90/K$13*100,K90) | H90: =IF(OR($A90="",H$12=0),NA(),IF($C$9="Anual",IF(INDEX(Anual!$B$2:$J$8,76,H$12)="",NA(),INDEX(Anual!$B$2:$J$8,76,H$12)),IF(INDEX(Mensual!$B$2:$S$83,76,H$12)="",NA(),INDEX(Mensual!$B$2:$S$83,76,H$12)))) | I90: =IF(OR($A90="",I$12=0),NA(),IF($C$9="Anual",IF(INDEX(Anual!$B$2:$J$8,76,I$12)="",NA(),INDEX(Anual!$B$2:$J$8,76,I$12)),IF(INDEX(Mensual!$B$2:$S$83,76,I$12)="",NA(),INDEX(Mensual!$B$2:$S$83,76,I$12)))) | J90: =IF(OR($A90="",J$12=0),NA(),IF($C$9="Anual",IF(INDEX(Anual!$B$2:$J$8,76,J$12)="",NA(),INDEX(Anual!$B$2:$J$8,76,J$12)),IF(INDEX(Mensual!$B$2:$S$83,76,J$12)="",NA(),INDEX(Mensual!$B$2:$S$83,76,J$12)))) | K90: =IF(OR($A90="",K$12=0),NA(),IF($C$9="Anual",IF(INDEX(Anual!$B$2:$J$8,76,K$12)="",NA(),INDEX(Anual!$B$2:$J$8,76,K$12)),IF(INDEX(Mensual!$B$2:$S$83,76,K$12)="",NA(),INDEX(Mensual!$B$2:$S$83,76,K$12))))
A91: =IF($C$9="Anual",IF(77<=7,INDEX(Anual!$A$2:$A$8,77),""),IF(77<=82,INDEX(Mensual!$A$2:$A$83,77),"")) | B91: =IF($C$10="Sí",H91/H$13*100,H91) | C91: =IF($C$10="Sí",I91/I$13*100,I91) | D91: =IF($C$10="Sí",J91/J$13*100,J91) | E91: =IF($C$10="Sí",K91/K$13*100,K91) | H91: =IF(OR($A91="",H$12=0),NA(),IF($C$9="Anual",IF(INDEX(Anual!$B$2:$J$8,77,H$12)="",NA(),INDEX(Anual!$B$2:$J$8,77,H$12)),IF(INDEX(Mensual!$B$2:$S$83,77,H$12)="",NA(),INDEX(Mensual!$B$2:$S$83,77,H$12)))) | I91: =IF(OR($A91="",I$12=0),NA(),IF($C$9="Anual",IF(INDEX(Anual!$B$2:$J$8,77,I$12)="",NA(),INDEX(Anual!$B$2:$J$8,77,I$12)),IF(INDEX(Mensual!$B$2:$S$83,77,I$12)="",NA(),INDEX(Mensual!$B$2:$S$83,77,I$12)))) | J91: =IF(OR($A91="",J$12=0),NA(),IF($C$9="Anual",IF(INDEX(Anual!$B$2:$J$8,77,J$12)="",NA(),INDEX(Anual!$B$2:$J$8,77,J$12)),IF(INDEX(Mensual!$B$2:$S$83,77,J$12)="",NA(),INDEX(Mensual!$B$2:$S$83,77,J$12)))) | K91: =IF(OR($A91="",K$12=0),NA(),IF($C$9="Anual",IF(INDEX(Anual!$B$2:$J$8,77,K$12)="",NA(),INDEX(Anual!$B$2:$J$8,77,K$12)),IF(INDEX(Mensual!$B$2:$S$83,77,K$12)="",NA(),INDEX(Mensual!$B$2:$S$83,77,K$12))))
A92: =IF($C$9="Anual",IF(78<=7,INDEX(Anual!$A$2:$A$8,78),""),IF(78<=82,INDEX(Mensual!$A$2:$A$83,78),"")) | B92: =IF($C$10="Sí",H92/H$13*100,H92) | C92: =IF($C$10="Sí",I92/I$13*100,I92) | D92: =IF($C$10="Sí",J92/J$13*100,J92) | E92: =IF($C$10="Sí",K92/K$13*100,K92) | H92: =IF(OR($A92="",H$12=0),NA(),IF($C$9="Anual",IF(INDEX(Anual!$B$2:$J$8,78,H$12)="",NA(),INDEX(Anual!$B$2:$J$8,78,H$12)),IF(INDEX(Mensual!$B$2:$S$83,78,H$12)="",NA(),INDEX(Mensual!$B$2:$S$83,78,H$12)))) | I92: =IF(OR($A92="",I$12=0),NA(),IF($C$9="Anual",IF(INDEX(Anual!$B$2:$J$8,78,I$12)="",NA(),INDEX(Anual!$B$2:$J$8,78,I$12)),IF(INDEX(Mensual!$B$2:$S$83,78,I$12)="",NA(),INDEX(Mensual!$B$2:$S$83,78,I$12)))) | J92: =IF(OR($A92="",J$12=0),NA(),IF($C$9="Anual",IF(INDEX(Anual!$B$2:$J$8,78,J$12)="",NA(),INDEX(Anual!$B$2:$J$8,78,J$12)),IF(INDEX(Mensual!$B$2:$S$83,78,J$12)="",NA(),INDEX(Mensual!$B$2:$S$83,78,J$12)))) | K92: =IF(OR($A92="",K$12=0),NA(),IF($C$9="Anual",IF(INDEX(Anual!$B$2:$J$8,78,K$12)="",NA(),INDEX(Anual!$B$2:$J$8,78,K$12)),IF(INDEX(Mensual!$B$2:$S$83,78,K$12)="",NA(),INDEX(Mensual!$B$2:$S$83,78,K$12))))
A93: =IF($C$9="Anual",IF(79<=7,INDEX(Anual!$A$2:$A$8,79),""),IF(79<=82,INDEX(Mensual!$A$2:$A$83,79),"")) | B93: =IF($C$10="Sí",H93/H$13*100,H93) | C93: =IF($C$10="Sí",I93/I$13*100,I93) | D93: =IF($C$10="Sí",J93/J$13*100,J93) | E93: =IF($C$10="Sí",K93/K$13*100,K93) | H93: =IF(OR($A93="",H$12=0),NA(),IF($C$9="Anual",IF(INDEX(Anual!$B$2:$J$8,79,H$12)="",NA(),INDEX(Anual!$B$2:$J$8,79,H$12)),IF(INDEX(Mensual!$B$2:$S$83,79,H$12)="",NA(),INDEX(Mensual!$B$2:$S$83,79,H$12)))) | I93: =IF(OR($A93="",I$12=0),NA(),IF($C$9="Anual",IF(INDEX(Anual!$B$2:$J$8,79,I$12)="",NA(),INDEX(Anual!$B$2:$J$8,79,I$12)),IF(INDEX(Mensual!$B$2:$S$83,79,I$12)="",NA(),INDEX(Mensual!$B$2:$S$83,79,I$12)))) | J93: =IF(OR($A93="",J$12=0),NA(),IF($C$9="Anual",IF(INDEX(Anual!$B$2:$J$8,79,J$12)="",NA(),INDEX(Anual!$B$2:$J$8,79,J$12)),IF(INDEX(Mensual!$B$2:$S$83,79,J$12)="",NA(),INDEX(Mensual!$B$2:$S$83,79,J$12)))) | K93: =IF(OR($A93="",K$12=0),NA(),IF($C$9="Anual",IF(INDEX(Anual!$B$2:$J$8,79,K$12)="",NA(),INDEX(Anual!$B$2:$J$8,79,K$12)),IF(INDEX(Mensual!$B$2:$S$83,79,K$12)="",NA(),INDEX(Mensual!$B$2:$S$83,79,K$12))))
A94: =IF($C$9="Anual",IF(80<=7,INDEX(Anual!$A$2:$A$8,80),""),IF(80<=82,INDEX(Mensual!$A$2:$A$83,80),"")) | B94: =IF($C$10="Sí",H94/H$13*100,H94) | C94: =IF($C$10="Sí",I94/I$13*100,I94) | D94: =IF($C$10="Sí",J94/J$13*100,J94) | E94: =IF($C$10="Sí",K94/K$13*100,K94) | H94: =IF(OR($A94="",H$12=0),NA(),IF($C$9="Anual",IF(INDEX(Anual!$B$2:$J$8,80,H$12)="",NA(),INDEX(Anual!$B$2:$J$8,80,H$12)),IF(INDEX(Mensual!$B$2:$S$83,80,H$12)="",NA(),INDEX(Mensual!$B$2:$S$83,80,H$12)))) | I94: =IF(OR($A94="",I$12=0),NA(),IF($C$9="Anual",IF(INDEX(Anual!$B$2:$J$8,80,I$12)="",NA(),INDEX(Anual!$B$2:$J$8,80,I$12)),IF(INDEX(Mensual!$B$2:$S$83,80,I$12)="",NA(),INDEX(Mensual!$B$2:$S$83,80,I$12)))) | J94: =IF(OR($A94="",J$12=0),NA(),IF($C$9="Anual",IF(INDEX(Anual!$B$2:$J$8,80,J$12)="",NA(),INDEX(Anual!$B$2:$J$8,80,J$12)),IF(INDEX(Mensual!$B$2:$S$83,80,J$12)="",NA(),INDEX(Mensual!$B$2:$S$83,80,J$12)))) | K94: =IF(OR($A94="",K$12=0),NA(),IF($C$9="Anual",IF(INDEX(Anual!$B$2:$J$8,80,K$12)="",NA(),INDEX(Anual!$B$2:$J$8,80,K$12)),IF(INDEX(Mensual!$B$2:$S$83,80,K$12)="",NA(),INDEX(Mensual!$B$2:$S$83,80,K$12))))
A95: =IF($C$9="Anual",IF(81<=7,INDEX(Anual!$A$2:$A$8,81),""),IF(81<=82,INDEX(Mensual!$A$2:$A$83,81),"")) | B95: =IF($C$10="Sí",H95/H$13*100,H95) | C95: =IF($C$10="Sí",I95/I$13*100,I95) | D95: =IF($C$10="Sí",J95/J$13*100,J95) | E95: =IF($C$10="Sí",K95/K$13*100,K95) | H95: =IF(OR($A95="",H$12=0),NA(),IF($C$9="Anual",IF(INDEX(Anual!$B$2:$J$8,81,H$12)="",NA(),INDEX(Anual!$B$2:$J$8,81,H$12)),IF(INDEX(Mensual!$B$2:$S$83,81,H$12)="",NA(),INDEX(Mensual!$B$2:$S$83,81,H$12)))) | I95: =IF(OR($A95="",I$12=0),NA(),IF($C$9="Anual",IF(INDEX(Anual!$B$2:$J$8,81,I$12)="",NA(),INDEX(Anual!$B$2:$J$8,81,I$12)),IF(INDEX(Mensual!$B$2:$S$83,81,I$12)="",NA(),INDEX(Mensual!$B$2:$S$83,81,I$12)))) | J95: =IF(OR($A95="",J$12=0),NA(),IF($C$9="Anual",IF(INDEX(Anual!$B$2:$J$8,81,J$12)="",NA(),INDEX(Anual!$B$2:$J$8,81,J$12)),IF(INDEX(Mensual!$B$2:$S$83,81,J$12)="",NA(),INDEX(Mensual!$B$2:$S$83,81,J$12)))) | K95: =IF(OR($A95="",K$12=0),NA(),IF($C$9="Anual",IF(INDEX(Anual!$B$2:$J$8,81,K$12)="",NA(),INDEX(Anual!$B$2:$J$8,81,K$12)),IF(INDEX(Mensual!$B$2:$S$83,81,K$12)="",NA(),INDEX(Mensual!$B$2:$S$83,81,K$12))))
A96: =IF($C$9="Anual",IF(82<=7,INDEX(Anual!$A$2:$A$8,82),""),IF(82<=82,INDEX(Mensual!$A$2:$A$83,82),"")) | B96: =IF($C$10="Sí",H96/H$13*100,H96) | C96: =IF($C$10="Sí",I96/I$13*100,I96) | D96: =IF($C$10="Sí",J96/J$13*100,J96) | E96: =IF($C$10="Sí",K96/K$13*100,K96) | H96: =IF(OR($A96="",H$12=0),NA(),IF($C$9="Anual",IF(INDEX(Anual!$B$2:$J$8,82,H$12)="",NA(),INDEX(Anual!$B$2:$J$8,82,H$12)),IF(INDEX(Mensual!$B$2:$S$83,82,H$12)="",NA(),INDEX(Mensual!$B$2:$S$83,82,H$12)))) | I96: =IF(OR($A96="",I$12=0),NA(),IF($C$9="Anual",IF(INDEX(Anual!$B$2:$J$8,82,I$12)="",NA(),INDEX(Anual!$B$2:$J$8,82,I$12)),IF(INDEX(Mensual!$B$2:$S$83,82,I$12)="",NA(),INDEX(Mensual!$B$2:$S$83,82,I$12)))) | J96: =IF(OR($A96="",J$12=0),NA(),IF($C$9="Anual",IF(INDEX(Anual!$B$2:$J$8,82,J$12)="",NA(),INDEX(Anual!$B$2:$J$8,82,J$12)),IF(INDEX(Mensual!$B$2:$S$83,82,J$12)="",NA(),INDEX(Mensual!$B$2:$S$83,82,J$12)))) | K96: =IF(OR($A96="",K$12=0),NA(),IF($C$9="Anual",IF(INDEX(Anual!$B$2:$J$8,82,K$12)="",NA(),INDEX(Anual!$B$2:$J$8,82,K$12)),IF(INDEX(Mensual!$B$2:$S$83,82,K$12)="",NA(),INDEX(Mensual!$B$2:$S$83,82,K$12))))

Sheet Datos 1 OMIE
A1: 1. Electricidad: precio del mercado diario OMIE, España
A2: Fuente: OMIE, ficheros marginalpdbc (precio marginal del mercado diario). Unidad original: €/MWh. Frecuencia: diaria (media aritmética de los periodos horarios o cuarto-horarios del día). Impuestos del dato original: sin impuestos (precio mayorista). Conversión: €/MWh ÷ 1.000 = €/kWh
A4: Fecha | B4: Periodo | C4: Valor original | D4: Unidad | E4: €/kWh sin impuestos | F4: €/kWh con impuestos | G4: Origen del precio con impuestos | H4: Impuestos aplicados | I4: Pendiente | J4: Fecha de publicación | K4: Referencia (fichero / BOE / PDF) | L4: Nota
A5: 43831 | B5: 2020-01-01 | C5: 35.5404 | D5: €/MWh | E5: 0.03554 | G5: no aplica (precio mayorista) | J5: 2019-12-31 | K5: marginalpdbc_20200101.1 | L5: 24 periodos; mín 30.00, máx 46.16 €/MWh
A6: 43832 | B6: 2020-01-02 | C6: 39.995 | D6: €/MWh | E6: 0.039995 | G6: no aplica (precio mayorista) | J6: 2020-01-01 | K6: marginalpdbc_20200102.1 | L6: 24 periodos; mín 28.42, máx 46.72 €/MWh
A7: 43833 | B7: 2020-01-03 | C7: 39.5063 | D7: €/MWh | E7: 0.039506 | G7: no aplica (precio mayorista) | J7: 2020-01-02 | K7: marginalpdbc_20200103.1 | L7: 24 periodos; mín 29.74, máx 47.23 €/MWh
A8: 43834 | B8: 2020-01-04 | C8: 35.6708 | D8: €/MWh | E8: 0.035671 | G8: no aplica (precio mayorista) | J8: 2020-01-03 | K8: marginalpdbc_20200104.1 | L8: 24 periodos; mín 29.84, máx 44.44 €/MWh
A9: 43835 | B9: 2020-01-05 | C9: 38.1754 | D9: €/MWh | E9: 0.038175 | G9: no aplica (precio mayorista) | J9: 2020-01-04 | K9: marginalpdbc_20200105.1 | L9: 24 periodos; mín 29.88, máx 53.29 €/MWh
A10: 43836 | B10: 2020-01-06 | C10: 42.1662 | D10: €/MWh | E10: 0.042166 | G10: no aplica (precio mayorista) | J10: 2020-01-05 | K10: marginalpdbc_20200106.1 | L10: 24 periodos; mín 31.50, máx 49.01 €/MWh
A11: 43837 | B11: 2020-01-07 | C11: 47.0125 | D11: €/MWh | E11: 0.047012 | G11: no aplica (precio mayorista) | J11: 2020-01-06 | K11: marginalpdbc_20200107.1 | L11: 24 periodos; mín 33.01, máx 56.26 €/MWh
A12: 43838 | B12: 2020-01-08 | C12: 46.8062 | D12: €/MWh | E12: 0.046806 | G12: no aplica (precio mayorista) | J12: 2020-01-07 | K12: marginalpdbc_20200108.1 | L12: 24 periodos; mín 33.07, máx 55.92 €/MWh
A13: 43839 | B13: 2020-01-09 | C13: 44.2058 | D13: €/MWh | E13: 0.044206 | G13: no aplica (precio mayorista) | J13: 2020-01-08 | K13: marginalpdbc_20200109.1 | L13: 24 periodos; mín 33.56, máx 53.31 €/MWh
A14: 43840 | B14: 2020-01-10 | C14: 40.5692 | D14: €/MWh | E14: 0.040569 | G14: no aplica (precio mayorista) | J14: 2020-01-09 | K14: marginalpdbc_20200110.1 | L14: 24 periodos; mín 27.65, máx 50.85 €/MWh
A15: 43841 | B15: 2020-01-11 | C15: 41.8392 | D15: €/MWh | E15: 0.041839 | G15: no aplica (precio mayorista) | J15: 2020-01-10 | K15: marginalpdbc_20200111.1 | L15: 24 periodos; mín 34.13, máx 56.26 €/MWh
A16: 43842 | B16: 2020-01-12 | C16: 42.3596 | D16: €/MWh | E16: 0.04236 | G16: no aplica (precio mayorista) | J16: 2020-01-11 | K16: marginalpdbc_20200112.1 | L16: 24 periodos; mín 37.03, máx 55.98 €/MWh
... A2493: 46322 | B2493: 2026-10-27 | C2493: 206.8894 | D2493: €/MWh | E2493: 0.206889 | G2493: no aplica (precio mayorista) | J2493: 2026-10-26 | K2493: marginalpdbc_20261027.1 | L2493: 96 periodos; mín 100.00, máx 290.00 €/MWh

Sheet Datos 2 MIBGAS
A1: 2. Gas natural: MIBGAS-ES Index
A2: Fuente: MIBGAS, fichero anual MIBGAS_Data (hoja de índices), MIBGAS-ES Index. Unidad original: €/MWh. Frecuencia: diaria (por día de gas). Impuestos del dato original: sin impuestos (precio mayorista). Conversión: €/MWh ÷ 1.000 = €/kWh (el índice se expresa sobre PCS, como todo el mercado gasista)
A4: Fecha | B4: Periodo | C4: Valor original | D4: Unidad | E4: €/kWh sin impuestos | F4: €/kWh con impuestos | G4: Origen del precio con impuestos | H4: Impuestos aplicados | I4: Pendiente | J4: Fecha de publicación | K4: Referencia (fichero / BOE / PDF) | L4: Nota
A5: 43831 | B5: 2020-01-01 | C5: 11.27 | D5: €/MWh | E5: 0.01127 | G5: no aplica (precio mayorista) | J5: 2020-01-01 | K5: MIBGAS_Data_2020.xlsx | L5: volumen 91328 MWh
A6: 43832 | B6: 2020-01-02 | C6: 11.61 | D6: €/MWh | E6: 0.01161 | G6: no aplica (precio mayorista) | J6: 2020-01-02 | K6: MIBGAS_Data_2020.xlsx | L6: volumen 79149 MWh
A7: 43833 | B7: 2020-01-03 | C7: 11.68 | D7: €/MWh | E7: 0.01168 | G7: no aplica (precio mayorista) | J7: 2020-01-03 | K7: MIBGAS_Data_2020.xlsx | L7: volumen 95254 MWh
A8: 43834 | B8: 2020-01-04 | C8: 11.77 | D8: €/MWh | E8: 0.01177 | G8: no aplica (precio mayorista) | J8: 2020-01-04 | K8: MIBGAS_Data_2020.xlsx | L8: volumen 95479 MWh
A9: 43835 | B9: 2020-01-05 | C9: 11.77 | D9: €/MWh | E9: 0.01177 | G9: no aplica (precio mayorista) | J9: 2020-01-05 | K9: MIBGAS_Data_2020.xlsx | L9: volumen 97181 MWh
A10: 43836 | B10: 2020-01-06 | C10: 11.99 | D10: €/MWh | E10: 0.01199 | G10: no aplica (precio mayorista) | J10: 2020-01-06 | K10: MIBGAS_Data_2020.xlsx | L10: volumen 92656 MWh
A11: 43837 | B11: 2020-01-07 | C11: 13.34 | D11: €/MWh | E11: 0.01334 | G11: no aplica (precio mayorista) | J11: 2020-01-07 | K11: MIBGAS_Data_2020.xlsx | L11: volumen 101084 MWh
A12: 43838 | B12: 2020-01-08 | C12: 14.48 | D12: €/MWh | E12: 0.01448 | G12: no aplica (precio mayorista) | J12: 2020-01-08 | K12: MIBGAS_Data_2020.xlsx | L12: volumen 148954 MWh
A13: 43839 | B13: 2020-01-09 | C13: 13.56 | D13: €/MWh | E13: 0.01356 | G13: no aplica (precio mayorista) | J13: 2020-01-09 | K13: MIBGAS_Data_2020.xlsx | L13: volumen 142949 MWh
A14: 43840 | B14: 2020-01-10 | C14: 12.15 | D14: €/MWh | E14: 0.01215 | G14: no aplica (precio mayorista) | J14: 2020-01-10 | K14: MIBGAS_Data_2020.xlsx | L14: volumen 64454 MWh
A15: 43841 | B15: 2020-01-11 | C15: 11.61 | D15: €/MWh | E15: 0.01161 | G15: no aplica (precio mayorista) | J15: 2020-01-11 | K15: MIBGAS_Data_2020.xlsx | L15: volumen 46540 MWh
A16: 43842 | B16: 2020-01-12 | C16: 11.87 | D16: €/MWh | E16: 0.01187 | G16: no aplica (precio mayorista) | J16: 2020-01-12 | K16: MIBGAS_Data_2020.xlsx | L16: volumen 53278 MWh
... A1100: 44926 | B1100: 2022-12-31 | C1100: 57.91 | D1100: €/MWh | E1100: 0.05791 | G1100: no aplica (precio mayorista) | J1100: 2022-12-31 | K1100: MIBGAS_Data_2022.xlsx | L1100: volumen 265020 MWh
A1101: 44927 | B1101: 2023-01-01 | C1101: 59.42 | D1101: €/MWh | E1101: 0.05942 | G1101: no aplica (precio mayorista) | J1101: 2023-01-01 | K1101: MIBGAS_Data_2023.xlsx
A1102: 44928 | B1102: 2023-01-02 | C1102: 62.71 | D1102: €/MWh | E1102: 0.06271 | G1102: no aplica (precio mayorista) | J1102: 2023-01-02 | K1102: MIBGAS_Data_2023.xlsx
A1103: 44929 | B1103: 2023-01-03 | C1103: 67 | D1103: €/MWh | E1103: 0.067 | G1103: no aplica (precio mayorista) | J1103: 2023-01-03 | K1103: MIBGAS_Data_2023.xlsx
A1104: 44930 | B1104: 2023-01-04 | C1104: 64.91 | D1104: €/MWh | E1104: 0.06491 | G1104: no aplica (precio mayorista) | J1104: 2023-01-04 | K1104: MIBGAS_Data_2023.xlsx
A1105: 44931 | B1105: 2023-01-05 | C1105: 58.74 | D1105: €/MWh | E1105: 0.05874 | G1105: no aplica (precio mayorista) | J1105: 2023-01-05 | K1105: MIBGAS_Data_2023.xlsx
A1106: 44932 | B1106: 2023-01-06 | C1106: 59.74 | D1106: €/MWh | E1106: 0.05974 | G1106: no aplica (precio mayorista) | J1106: 2023-01-06 | K1106: MIBGAS_Data_2023.xlsx
A1107: 44933 | B1107: 2023-01-07 | C1107: 60.69 | D1107: €/MWh | E1107: 0.06069 | G1107: no aplica (precio mayorista) | J1107: 2023-01-07 | K1107: MIBGAS_Data_2023.xlsx
A1108: 44934 | B1108: 2023-01-08 | C1108: 61.28 | D1108: €/MWh | E1108: 0.06128 | G1108: no aplica (precio mayorista) | J1108: 2023-01-08 | K1108: MIBGAS_Data_2023.xlsx
A1109: 44935 | B1109: 2023-01-09 | C1109: 63.09 | D1109: €/MWh | E1109: 0.06309 | G1109: no aplica (precio mayorista) | J1109: 2023-01-09 | K1109: MIBGAS_Data_2023.xlsx
A1110: 44936 | B1110: 2023-01-10 | C1110: 66.33 | D1110: €/MWh | E1110: 0.06633 | G1110: no aplica (precio mayorista) | J1110: 2023-01-10 | K1110: MIBGAS_Data_2023.xlsx
A1111: 44937 | B1111: 2023-01-11 | C1111: 64.67 | D1111: €/MWh | E1111: 0.06467 | G1111: no aplica (precio mayorista) | J1111: 2023-01-11 | K1111: MIBGAS_Data_2023.xlsx
A1112: 44938 | B1112: 2023-01-12 | C1112: 62.28 | D1112: €/MWh | E1112: 0.06228 | G1112: no aplica (precio mayorista) | J1112: 2023-01-12 | K1112: MIBGAS_Data_2023.xlsx
... A2495: 46321 | B2495: 2026-10-26 | C2495: 94.69 | D2495: €/MWh | E2495: 0.09469 | G2495: no aplica (precio mayorista) | J2495: 2026-10-26 | K2495: MIBGAS_Data_2026.xlsx

Sheet Datos 3 Gasóleo A
A1: 3. Gasóleo de automoción: precio medio en España
A2: Fuente: Comisión Europea, Weekly Oil Bulletin (fichero histórico de precios). Unidad original: €/l. Frecuencia: semanal (precio del lunes). Impuestos del dato original: con impuestos (y también sin impuestos). Conversión: €/l ÷ 10.28 kWh/l (PCI; decisión 10)
A4: Fecha | B4: Periodo | C4: Valor original | D4: Unidad | E4: €/kWh sin impuestos | F4: €/kWh con impuestos | G4: Origen del precio con impuestos | H4: Impuestos aplicados | I4: Pendiente | J4: Fecha de publicación | K4: Referencia (fichero / BOE / PDF) | L4: Nota
A5: 43836 | B5: 2020-01-06 | C5: 1.24707 | D5: €/l | E5: 0.063389 | F5: 0.12131 | G5: original (el Boletín publica con y sin impuestos) | H5: IVA e impuesto sobre hidrocarburos incluidos por la fuente | K5: Weekly_Oil_Bulletin_Prices_History_maticni_4web.xlsx
A6: 43843 | B6: 2020-01-13 | C6: 1.25395 | D6: €/l | E6: 0.063942 | F6: 0.12198 | G6: original (el Boletín publica con y sin impuestos) | H6: IVA e impuesto sobre hidrocarburos incluidos por la fuente | K6: Weekly_Oil_Bulletin_Prices_History_maticni_4web.xlsx
A7: 43850 | B7: 2020-01-20 | C7: 1.24658 | D7: €/l | E7: 0.063349 | F7: 0.121263 | G7: original (el Boletín publica con y sin impuestos) | H7: IVA e impuesto sobre hidrocarburos incluidos por la fuente | K7: Weekly_Oil_Bulletin_Prices_History_maticni_4web.xlsx
A8: 43857 | B8: 2020-01-27 | C8: 1.23597 | D8: €/l | E8: 0.062496 | F8: 0.120231 | G8: original (el Boletín publica con y sin impuestos) | H8: IVA e impuesto sobre hidrocarburos incluidos por la fuente | K8: Weekly_Oil_Bulletin_Prices_History_maticni_4web.xlsx
A9: 43864 | B9: 2020-02-03 | C9: 1.2214 | D9: €/l | E9: 0.061325 | F9: 0.118813 | G9: original (el Boletín publica con y sin impuestos) | H9: IVA e impuesto sobre hidrocarburos incluidos por la fuente | K9: Weekly_Oil_Bulletin_Prices_History_maticni_4web.xlsx
A10: 43871 | B10: 2020-02-10 | C10: 1.20624 | D10: €/l | E10: 0.060106 | F10: 0.117339 | G10: original (el Boletín publica con y sin impuestos) | H10: IVA e impuesto sobre hidrocarburos incluidos por la fuente | K10: Weekly_Oil_Bulletin_Prices_History_maticni_4web.xlsx
A11: 43878 | B11: 2020-02-17 | C11: 1.20035 | D11: €/l | E11: 0.059632 | F11: 0.116766 | G11: original (el Boletín publica con y sin impuestos) | H11: IVA e impuesto sobre hidrocarburos incluidos por la fuente | K11: Weekly_Oil_Bulletin_Prices_History_maticni_4web.xlsx
A12: 43885 | B12: 2020-02-24 | C12: 1.20155 | D12: €/l | E12: 0.05973 | F12: 0.116882 | G12: original (el Boletín publica con y sin impuestos) | H12: IVA e impuesto sobre hidrocarburos incluidos por la fuente | K12: Weekly_Oil_Bulletin_Prices_History_maticni_4web.xlsx
A13: 43892 | B13: 2020-03-02 | C13: 1.19006 | D13: €/l | E13: 0.058805 | F13: 0.115765 | G13: original (el Boletín publica con y sin impuestos) | H13: IVA e impuesto sobre hidrocarburos incluidos por la fuente | K13: Weekly_Oil_Bulletin_Prices_History_maticni_4web.xlsx
A14: 43899 | B14: 2020-03-09 | C14: 1.17108 | D14: €/l | E14: 0.057279 | F14: 0.113918 | G14: original (el Boletín publica con y sin impuestos) | H14: IVA e impuesto sobre hidrocarburos incluidos por la fuente | K14: Weekly_Oil_Bulletin_Prices_History_maticni_4web.xlsx
A15: 43906 | B15: 2020-03-16 | C15: 1.1278 | D15: €/l | E15: 0.053801 | F15: 0.109708 | G15: original (el Boletín publica con y sin impuestos) | H15: IVA e impuesto sobre hidrocarburos incluidos por la fuente | K15: Weekly_Oil_Bulletin_Prices_History_maticni_4web.xlsx
A16: 43913 | B16: 2020-03-23 | C16: 1.08489 | D16: €/l | E16: 0.05035 | F16: 0.105534 | G16: original (el Boletín publica con y sin impuestos) | H16: IVA e impuesto sobre hidrocarburos incluidos por la fuente | K16: Weekly_Oil_Bulletin_Prices_History_maticni_4web.xlsx
... A116: 44648 | B116: 2022-03-28 | C116: 1.83719 | D116: €/l | E116: 0.110831 | F116: 0.178715 | G116: original (el Boletín publica con y sin impuestos) | H116: IVA e impuesto sobre hidrocarburos incluidos por la fuente | K116: Weekly_Oil_Bulletin_Prices_History_maticni_4web.xlsx
A117: 44655 | B117: 2022-04-04 | C117: 1.84703 | D117: €/l | E117: 0.111622 | F117: 0.179672 | G117: original (el Boletín publica con y sin impuestos) | H117: IVA e impuesto sobre hidrocarburos incluidos por la fuente | K117: Weekly_Oil_Bulletin_Prices_History_maticni_4web.xlsx | L117: precio antes de la bonificación de 20 c€/l (RDL 6/2022), que el Boletín no descuenta
A118: 44662 | B118: 2022-04-11 | C118: 1.81387 | D118: €/l | E118: 0.108956 | F118: 0.176446 | G118: original (el Boletín publica con y sin impuestos) | H118: IVA e impuesto sobre hidrocarburos incluidos por la fuente | K118: Weekly_Oil_Bulletin_Prices_History_maticni_4web.xlsx | L118: precio antes de la bonificación de 20 c€/l (RDL 6/2022), que el Boletín no descuenta
A119: 44676 | B119: 2022-04-25 | C119: 1.84741 | D119: €/l | E119: 0.111653 | F119: 0.179709 | G119: original (el Boletín publica con y sin impuestos) | H119: IVA e impuesto sobre hidrocarburos incluidos por la fuente | K119: Weekly_Oil_Bulletin_Prices_History_maticni_4web.xlsx | L119: precio antes de la bonificación de 20 c€/l (RDL 6/2022), que el Boletín no descuenta
A120: 44683 | B120: 2022-05-02 | C120: 1.87279 | D120: €/l | E120: 0.113693 | F120: 0.182178 | G120: original (el Boletín publica con y sin impuestos) | H120: IVA e impuesto sobre hidrocarburos incluidos por la fuente | K120: Weekly_Oil_Bulletin_Prices_History_maticni_4web.xlsx | L120: precio antes de la bonificación de 20 c€/l (RDL 6/2022), que el Boletín no descuenta
A121: 44690 | B121: 2022-05-09 | C121: 1.91149 | D121: €/l | E121: 0.116804 | F121: 0.185943 | G121: original (el Boletín publica con y sin impuestos) | H121: IVA e impuesto sobre hidrocarburos incluidos por la fuente | K121: Weekly_Oil_Bulletin_Prices_History_maticni_4web.xlsx | L121: precio antes de la bonificación de 20 c€/l (RDL 6/2022), que el Boletín no descuenta
A122: 44697 | B122: 2022-05-16 | C122: 1.88707 | D122: €/l | E122: 0.11484 | F122: 0.183567 | G122: original (el Boletín publica con y sin impuestos) | H122: IVA e impuesto sobre hidrocarburos incluidos por la fuente | K122: Weekly_Oil_Bulletin_Prices_History_maticni_4web.xlsx | L122: precio antes de la bonificación de 20 c€/l (RDL 6/2022), que el Boletín no descuenta
A123: 44704 | B123: 2022-05-23 | C123: 1.86703 | D123: €/l | E123: 0.11323 | F123: 0.181618 | G123: original (el Boletín publica con y sin impuestos) | H123: IVA e impuesto sobre hidrocarburos incluidos por la fuente | K123: Weekly_Oil_Bulletin_Prices_History_maticni_4web.xlsx | L123: precio antes de la bonificación de 20 c€/l (RDL 6/2022), que el Boletín no descuenta
A124: 44711 | B124: 2022-05-30 | C124: 1.85221 | D124: €/l | E124: 0.112038 | F124: 0.180176 | G124: original (el Boletín publica con y sin impuestos) | H124: IVA e impuesto sobre hidrocarburos incluidos por la fuente | K124: Weekly_Oil_Bulletin_Prices_History_maticni_4web.xlsx | L124: precio antes de la bonificación de 20 c€/l (RDL 6/2022), que el Boletín no descuenta
A125: 44718 | B125: 2022-06-06 | C125: 1.9169 | D125: €/l | E125: 0.117238 | F125: 0.186469 | G125: original (el Boletín publica con y sin impuestos) | H125: IVA e impuesto sobre hidrocarburos incluidos por la fuente | K125: Weekly_Oil_Bulletin_Prices_History_maticni_4web.xlsx | L125: precio antes de la bonificación de 20 c€/l (RDL 6/2022), que el Boletín no descuenta
A126: 44725 | B126: 2022-06-13 | C126: 2.00373 | D126: €/l | E126: 0.12422 | F126: 0.194915 | G126: original (el Boletín publica con y sin impuestos) | H126: IVA e impuesto sobre hidrocarburos incluidos por la fuente | K126: Weekly_Oil_Bulletin_Prices_History_maticni_4web.xlsx | L126: precio antes de la bonificación de 20 c€/l (RDL 6/2022), que el Boletín no descuenta
A127: 44732 | B127: 2022-06-20 | C127: 2.07653 | D127: €/l | E127: 0.130072 | F127: 0.201997 | G127: original (el Boletín publica con y sin impuestos) | H127: IVA e impuesto sobre hidrocarburos incluidos por la fuente | K127: Weekly_Oil_Bulletin_Prices_History_maticni_4web.xlsx | L127: precio antes de la bonificación de 20 c€/l (RDL 6/2022), que el Boletín no descuenta
A128: 44739 | B128: 2022-06-27 | C128: 2.10048 | D128: €/l | E128: 0.131997 | F128: 0.204327 | G128: original (el Boletín publica con y sin impuestos) | H128: IVA e impuesto sobre hidrocarburos incluidos por la fuente | K128: Weekly_Oil_Bulletin_Prices_History_maticni_4web.xlsx | L128: precio antes de la bonificación de 20 c€/l (RDL 6/2022), que el Boletín no descuenta
... A154: 44921 | B154: 2022-12-26 | C154: 1.64335 | D154: €/l | E154: 0.095247 | F154: 0.159859 | G154: original (el Boletín publica con y sin impuestos) | H154: IVA e impuesto sobre hidrocarburos incluidos por la fuente | K154: Weekly_Oil_Bulletin_Prices_History_maticni_4web.xlsx | L154: precio antes de la bonificación de 20 c€/l (RDL 6/2022), que el Boletín no descuenta
A155: 44928 | B155: 2023-01-02 | C155: 1.66081 | D155: €/l | E155: 0.096651 | F155: 0.161557 | G155: original (el Boletín publica con y sin impuestos) | H155: IVA e impuesto sobre hidrocarburos incluidos por la fuente | K155: Weekly_Oil_Bulletin_Prices_History_maticni_4web.xlsx
A156: 44935 | B156: 2023-01-09 | C156: 1.68194 | D156: €/l | E156: 0.098349 | F156: 0.163613 | G156: original (el Boletín publica con y sin impuestos) | H156: IVA e impuesto sobre hidrocarburos incluidos por la fuente | K156: Weekly_Oil_Bulletin_Prices_History_maticni_4web.xlsx
A157: 44942 | B157: 2023-01-16 | C157: 1.67908 | D157: €/l | E157: 0.09812 | F157: 0.163335 | G157: original (el Boletín publica con y sin impuestos) | H157: IVA e impuesto sobre hidrocarburos incluidos por la fuente | K157: Weekly_Oil_Bulletin_Prices_History_maticni_4web.xlsx
A158: 44949 | B158: 2023-01-23 | C158: 1.68831 | D158: €/l | E158: 0.098862 | F158: 0.164232 | G158: original (el Boletín publica con y sin impuestos) | H158: IVA e impuesto sobre hidrocarburos incluidos por la fuente | K158: Weekly_Oil_Bulletin_Prices_History_maticni_4web.xlsx
A159: 44956 | B159: 2023-01-30 | C159: 1.70404 | D159: €/l | E159: 0.100126 | F159: 0.165763 | G159: original (el Boletín publica con y sin impuestos) | H159: IVA e impuesto sobre hidrocarburos incluidos por la fuente | K159: Weekly_Oil_Bulletin_Prices_History_maticni_4web.xlsx
A160: 44963 | B160: 2023-02-06 | C160: 1.67742 | D160: €/l | E160: 0.097986 | F160: 0.163173 | G160: original (el Boletín publica con y sin impuestos) | H160: IVA e impuesto sobre hidrocarburos incluidos por la fuente | K160: Weekly_Oil_Bulletin_Prices_History_maticni_4web.xlsx
A161: 44970 | B161: 2023-02-13 | C161: 1.62875 | D161: €/l | E161: 0.094073 | F161: 0.158439 | G161: original (el Boletín publica con y sin impuestos) | H161: IVA e impuesto sobre hidrocarburos incluidos por la fuente | K161: Weekly_Oil_Bulletin_Prices_History_maticni_4web.xlsx
A162: 44977 | B162: 2023-02-20 | C162: 1.6114 | D162: €/l | E162: 0.092679 | F162: 0.156751 | G162: original (el Boletín publica con y sin impuestos) | H162: IVA e impuesto sobre hidrocarburos incluidos por la fuente | K162: Weekly_Oil_Bulletin_Prices_History_maticni_4web.xlsx
A163: 44984 | B163: 2023-02-27 | C163: 1.5891 | D163: €/l | E163: 0.090886 | F163: 0.154582 | G163: original (el Boletín publica con y sin impuestos) | H163: IVA e impuesto sobre hidrocarburos incluidos por la fuente | K163: Weekly_Oil_Bulletin_Prices_History_maticni_4web.xlsx
A164: 44991 | B164: 2023-03-06 | C164: 1.5888 | D164: €/l | E164: 0.090862 | F164: 0.154553 | G164: original (el Boletín publica con y sin impuestos) | H164: IVA e impuesto sobre hidrocarburos incluidos por la fuente | K164: Weekly_Oil_Bulletin_Prices_History_maticni_4web.xlsx
A165: 44998 | B165: 2023-03-13 | C165: 1.59266 | D165: €/l | E165: 0.091172 | F165: 0.154928 | G165: original (el Boletín publica con y sin impuestos) | H165: IVA e impuesto sobre hidrocarburos incluidos por la fuente | K165: Weekly_Oil_Bulletin_Prices_History_maticni_4web.xlsx
A166: 45005 | B166: 2023-03-20 | C166: 1.57104 | D166: €/l | E166: 0.089434 | F166: 0.152825 | G166: original (el Boletín publica con y sin impuestos) | H166: IVA e impuesto sobre hidrocarburos incluidos por la fuente | K166: Weekly_Oil_Bulletin_Prices_History_maticni_4web.xlsx
... A353: 46314 | B353: 2026-10-19 | C353: 1.88922 | D353: €/l | E353: 0.134469 | F353: 0.183776 | G353: original (el Boletín publica con y sin impuestos) | H353: IVA e impuesto sobre hidrocarburos incluidos por la fuente | K353: Weekly_Oil_Bulletin_Prices_History_maticni_4web.xlsx

Sheet Datos 4 PVPC 2.0TD
A1: 4. Electricidad PVPC: término de energía, tarifa 2.0TD (Península)
A2: Fuente: REE/ESIOS, indicador 1001 (término de facturación de energía activa del PVPC 2.0TD, Península). Unidad original: €/MWh. Frecuencia: diaria (media aritmética de los valores horarios o cuarto-horarios del día). Impuestos del dato original: sin impuestos. Conversión: €/MWh ÷ 1.000 = €/kWh; con impuestos: (precio + cuota IEE) × (1 + IVA) vigentes en la fecha
A4: Fecha | B4: Periodo | C4: Valor original | D4: Unidad | E4: €/kWh sin impuestos | F4: €/kWh con impuestos | G4: Origen del precio con impuestos | H4: Impuestos aplicados | I4: Pendiente | J4: Fecha de publicación | K4: Referencia (fichero / BOE / PDF) | L4: Nota
A5: 44348 | B5: 2021-06-01 | C5: 166.7713 | D5: €/MWh | E5: 0.166771 | F5: 0.21211 | G5: calculado | H5: IEE 5.1127 % con cuota mínima 1 €/MWh (Ley 38/1992 art. 99) + IVA 21 % (Ley 37/1992 art. 90) | J5: 2021-05-31 | K5: ESIOS 1001 geo 8741 | L5: 24 valores; mín 114.84, máx 248.08 €/MWh
A6: 44349 | B6: 2021-06-02 | C6: 164.775 | D6: €/MWh | E6: 0.164775 | F6: 0.209571 | G6: calculado | H6: IEE 5.1127 % con cuota mínima 1 €/MWh (Ley 38/1992 art. 99) + IVA 21 % (Ley 37/1992 art. 90) | J6: 2021-06-01 | K6: ESIOS 1001 geo 8741 | L6: 24 valores; mín 111.85, máx 245.00 €/MWh
A7: 44350 | B7: 2021-06-03 | C7: 159.23 | D7: €/MWh | E7: 0.15923 | F7: 0.202519 | G7: calculado | H7: IEE 5.1127 % con cuota mínima 1 €/MWh (Ley 38/1992 art. 99) + IVA 21 % (Ley 37/1992 art. 90) | J7: 2021-06-02 | K7: ESIOS 1001 geo 8741 | L7: 24 valores; mín 102.96, máx 242.13 €/MWh
A8: 44351 | B8: 2021-06-04 | C8: 160.5546 | D8: €/MWh | E8: 0.160555 | F8: 0.204204 | G8: calculado | H8: IEE 5.1127 % con cuota mínima 1 €/MWh (Ley 38/1992 art. 99) + IVA 21 % (Ley 37/1992 art. 90) | J8: 2021-06-03 | K8: ESIOS 1001 geo 8741 | L8: 24 valores; mín 102.52, máx 239.39 €/MWh
A9: 44352 | B9: 2021-06-05 | C9: 101.65 | D9: €/MWh | E9: 0.10165 | F9: 0.129285 | G9: calculado | H9: IEE 5.1127 % con cuota mínima 1 €/MWh (Ley 38/1992 art. 99) + IVA 21 % (Ley 37/1992 art. 90) | J9: 2021-06-04 | K9: ESIOS 1001 geo 8741 | L9: 24 valores; mín 93.76, máx 111.30 €/MWh
A10: 44353 | B10: 2021-06-06 | C10: 96.0046 | D10: €/MWh | E10: 0.096005 | F10: 0.122105 | G10: calculado | H10: IEE 5.1127 % con cuota mínima 1 €/MWh (Ley 38/1992 art. 99) + IVA 21 % (Ley 37/1992 art. 90) | J10: 2021-06-05 | K10: ESIOS 1001 geo 8741 | L10: 24 valores; mín 61.50, máx 114.14 €/MWh
A11: 44354 | B11: 2021-06-07 | C11: 160.1188 | D11: €/MWh | E11: 0.160119 | F11: 0.203649 | G11: calculado | H11: IEE 5.1127 % con cuota mínima 1 €/MWh (Ley 38/1992 art. 99) + IVA 21 % (Ley 37/1992 art. 90) | J11: 2021-06-06 | K11: ESIOS 1001 geo 8741 | L11: 24 valores; mín 94.41, máx 244.94 €/MWh
A12: 44355 | B12: 2021-06-08 | C12: 161.8713 | D12: €/MWh | E12: 0.161871 | F12: 0.205878 | G12: calculado | H12: IEE 5.1127 % con cuota mínima 1 €/MWh (Ley 38/1992 art. 99) + IVA 21 % (Ley 37/1992 art. 90) | J12: 2021-06-07 | K12: ESIOS 1001 geo 8741 | L12: 24 valores; mín 105.46, máx 241.82 €/MWh
A13: 44356 | B13: 2021-06-09 | C13: 161.1729 | D13: €/MWh | E13: 0.161173 | F13: 0.20499 | G13: calculado | H13: IEE 5.1127 % con cuota mínima 1 €/MWh (Ley 38/1992 art. 99) + IVA 21 % (Ley 37/1992 art. 90) | J13: 2021-06-08 | K13: ESIOS 1001 geo 8741 | L13: 24 valores; mín 101.76, máx 241.90 €/MWh
A14: 44357 | B14: 2021-06-10 | C14: 162.5275 | D14: €/MWh | E14: 0.162527 | F14: 0.206713 | G14: calculado | H14: IEE 5.1127 % con cuota mínima 1 €/MWh (Ley 38/1992 art. 99) + IVA 21 % (Ley 37/1992 art. 90) | J14: 2021-06-09 | K14: ESIOS 1001 geo 8741 | L14: 24 valores; mín 100.41, máx 243.48 €/MWh
A15: 44358 | B15: 2021-06-11 | C15: 161.7896 | D15: €/MWh | E15: 0.16179 | F15: 0.205774 | G15: calculado | H15: IEE 5.1127 % con cuota mínima 1 €/MWh (Ley 38/1992 art. 99) + IVA 21 % (Ley 37/1992 art. 90) | J15: 2021-06-10 | K15: ESIOS 1001 geo 8741 | L15: 24 valores; mín 96.14, máx 244.23 €/MWh
A16: 44359 | B16: 2021-06-12 | C16: 102.7267 | D16: €/MWh | E16: 0.102727 | F16: 0.130654 | G16: calculado | H16: IEE 5.1127 % con cuota mínima 1 €/MWh (Ley 38/1992 art. 99) + IVA 21 % (Ley 37/1992 art. 90) | J16: 2021-06-11 | K16: ESIOS 1001 geo 8741 | L16: 24 valores; mín 91.21, máx 119.33 €/MWh
... A1979: 46322 | B1979: 2026-10-27 | C1979: 231.6446 | D1979: €/MWh | E1979: 0.231645 | F1979: 0.29462 | G1979: calculado | H1979: IEE 5.1127 % con cuota mínima 1 €/MWh (Ley 38/1992 art. 99 (RDL 25/2026 no reduce el IEE en octubre)) + IVA 21 % (Ley 37/1992 art. 90 (RDL 25/2026 no reduce el IVA en octubre)) | J1979: 2026-10-26 | K1979: ESIOS 1001 geo 8741 | L1979: 24 valores; mín 103.23, máx 378.15 €/MWh

Sheet Datos 5 TUR 2
A1: 5. Gas natural TUR 2: término variable
A2: Fuente: BOE, resoluciones de la DGPEM por las que se publica la tarifa de último recurso de gas natural. Unidad original: c€/kWh (PCS). Frecuencia: trimestral (valor vigente desde la fecha de efectos de cada resolución). Impuestos del dato original: sin impuestos. Conversión: c€/kWh (PCS) ÷ 100 ÷ 0.904 = €/kWh (PCI); con impuestos: (precio + IH gas) × (1 + IVA) vigentes
A4: Fecha | B4: Periodo | C4: Valor original | D4: Unidad | E4: €/kWh sin impuestos | F4: €/kWh con impuestos | G4: Origen del precio con impuestos | H4: Impuestos aplicados | I4: Pendiente | J4: Fecha de publicación | K4: Referencia (fichero / BOE / PDF) | L4: Nota
A5: 43831 | B5: 2020-01-01 | C5: 4.275044 | D5: c€/kWh (PCS) | E5: 0.04729 | F5: 0.060353 | G5: calculado | H5: IH gas natural 0.2340 c€/kWh (Ley 38/1992 art. 50, epígrafe 1.10.1) + IVA 21 % (Ley 37/1992 art. 90) | J5: 2019-12-30 | K5: BOE-A-2019-18676 | L5: TUR.2: Consumo superior a 5.000 kWh/año e inferior o igual a 50.000 kWh/año.; término fijo 8.35 €/cliente/mes; impuestos aplicados los vigentes en la fecha de efectos
A6: 44013 | B6: 2020-07-01 | C6: 3.9694 | D6: c€/kWh (PCS) | E6: 0.043909 | F6: 0.056262 | G6: calculado | H6: IH gas natural 0.2340 c€/kWh (Ley 38/1992 art. 50, epígrafe 1.10.1) + IVA 21 % (Ley 37/1992 art. 90) | J6: 2020-06-30 | K6: BOE-A-2020-6904 | L6: TUR.2: Consumo superior a 5.000 kWh/año e inferior o igual a 50.000 a kWh/año.; término fijo 8.35 €/cliente/mes; impuestos aplicados los vigentes en la fecha de efectos
A7: 44105 | B7: 2020-10-01 | C7: 3.73238 | D7: c€/kWh (PCS) | E7: 0.041287 | F7: 0.05309 | G7: calculado | H7: IH gas natural 0.2340 c€/kWh (Ley 38/1992 art. 50, epígrafe 1.10.1) + IVA 21 % (Ley 37/1992 art. 90) | J7: 2020-09-30 | K7: BOE-A-2020-11426 | L7: TUR.2: Consumo superior a 5.000 kWh/año e inferior o igual a 50.000 a kWh/año.; término fijo 8.02 €/cliente/mes; impuestos aplicados los vigentes en la fecha de efectos
A8: 44197 | B8: 2021-01-01 | C8: 4.036244 | D8: c€/kWh (PCS) | E8: 0.044649 | F8: 0.057157 | G8: calculado | H8: IH gas natural 0.2340 c€/kWh (Ley 38/1992 art. 50, epígrafe 1.10.1) + IVA 21 % (Ley 37/1992 art. 90) | J8: 2020-12-29 | K8: BOE-A-2020-17207 | L8: TUR.2: Consumo superior a 5.000 kWh/año e inferior o igual a 50.000 a kWh/año.; término fijo 8.02 €/cliente/mes; impuestos aplicados los vigentes en la fecha de efectos
A9: 44378 | B9: 2021-07-01 | C9: 4.234768 | D9: c€/kWh (PCS) | E9: 0.046845 | F9: 0.059814 | G9: calculado | H9: IH gas natural 0.2340 c€/kWh (Ley 38/1992 art. 50, epígrafe 1.10.1) + IVA 21 % (Ley 37/1992 art. 90) | J9: 2021-06-30 | K9: BOE-A-2021-10825 | L9: TUR.2: Consumo superior a 5.000 kWh/año e inferior o igual a 50.000 a kWh/año.; término fijo 8.02 €/cliente/mes; impuestos aplicados los vigentes en la fecha de efectos
A10: 44470 | B10: 2021-10-01 | C10: 4.127554 | D10: c€/kWh (PCS) | E10: 0.045659 | F10: 0.058379 | G10: calculado | H10: IH gas natural 0.2340 c€/kWh (Ley 38/1992 art. 50, epígrafe 1.10.1) + IVA 21 % (Ley 37/1992 art. 90) | J10: 2021-09-29 | K10: BOE-A-2021-15778 | L10: TUR.2: Consumo superior a 5.000 kWh/año e inferior o igual a 15.000 a kWh/año.; término fijo 10.23 €/cliente/mes; impuestos aplicados los vigentes en la fecha de efectos
A11: 44562 | B11: 2022-01-01 | C11: 4.520114 | D11: c€/kWh (PCS) | E11: 0.050001 | F11: 0.063634 | G11: calculado | H11: IH gas natural 0.2340 c€/kWh (Ley 38/1992 art. 50, epígrafe 1.10.1) + IVA 21 % (Ley 37/1992 art. 90) | J11: 2021-12-25 | K11: BOE-A-2021-21356 | L11: TUR.2: Consumo superior a 5.000 kWh/año e inferior o igual a 15.000 a kWh/año.; término fijo 10.24 €/cliente/mes; impuestos aplicados los vigentes en la fecha de efectos
A12: 44652 | B12: 2022-04-01 | C12: 4.969479 | D12: c€/kWh (PCS) | E12: 0.054972 | F12: 0.069648 | G12: calculado | H12: IH gas natural 0.2340 c€/kWh (Ley 38/1992 art. 50, epígrafe 1.10.1) + IVA 21 % (Ley 37/1992 art. 90) | J12: 2022-03-31 | K12: BOE-A-2022-5064 | L12: TUR.2: Consumo superior a 5.000 kWh/año e inferior o igual a 15.000 kWh/año.; término fijo 10.24 €/cliente/mes; impuestos aplicados los vigentes en la fecha de efectos
A13: 44743 | B13: 2022-07-01 | C13: 5.486249 | D13: c€/kWh (PCS) | E13: 0.060689 | F13: 0.076565 | G13: calculado | H13: IH gas natural 0.2340 c€/kWh (Ley 38/1992 art. 50, epígrafe 1.10.1) + IVA 21 % (Ley 37/1992 art. 90) | J13: 2022-06-29 | K13: BOE-A-2022-10760 | L13: TUR.2: Consumo superior a 5.000 kWh/año e inferior o igual 15.000 kWh/año.; término fijo 10.24 €/cliente/mes; impuestos aplicados los vigentes en la fecha de efectos
A14: 44835 | B14: 2022-10-01 | C14: 6.069581 | D14: c€/kWh (PCS) | E14: 0.067141 | F14: 0.073216 | G14: calculado | H14: IH gas natural 0.2340 c€/kWh (Ley 38/1992 art. 50, epígrafe 1.10.1) + IVA 5 % (RDL 17/2022 art. 5 (prorrogado por RDL 20/2022 art. 1)) | J14: 2022-09-29 | K14: BOE-A-2022-15820 | L14: TUR.2: Consumo superior a 5.000 kWh/año e inferior o igual a 15.000 kWh/año.; término fijo 9.52 €/cliente/mes; impuestos aplicados los vigentes en la fecha de efectos
A15: 44927 | B15: 2023-01-01 | C15: 6.753009 | D15: c€/kWh (PCS) | E15: 0.074701 | F15: 0.081154 | G15: calculado | H15: IH gas natural 0.2340 c€/kWh (Ley 38/1992 art. 50, epígrafe 1.10.1) + IVA 5 % (RDL 17/2022 art. 5 (prorrogado por RDL 20/2022 art. 1)) | J15: 2022-12-28 | K15: BOE-A-2022-22692 | L15: TUR.2: Consumo superior a 5.000 kWh/año e inferior o igual a 15.000 kWh/año.; término fijo 9.52 €/cliente/mes; impuestos aplicados los vigentes en la fecha de efectos
A16: 45017 | B16: 2023-04-01 | C16: 4.187549 | D16: c€/kWh (PCS) | E16: 0.046322 | F16: 0.051356 | G16: calculado | H16: IH gas natural 0.2340 c€/kWh (Ley 38/1992 art. 50, epígrafe 1.10.1) + IVA 5 % (RDL 17/2022 art. 5 (prorrogado por RDL 20/2022 art. 1)) | J16: 2023-03-30 | K16: BOE-A-2023-8053 | L16: TUR.2: Consumo superior a 5.000 kWh/año e inferior o igual a 15.000 kWh/año.; término fijo 9.48 €/cliente/mes; impuestos aplicados los vigentes en la fecha de efectos
... A29: 46296 | B29: 2026-10-01 | C29: 5.042762 | D29: c€/kWh (PCS) | E29: 0.055783 | F29: 0.070629 | G29: calculado | H29: IH gas natural 0.2340 c€/kWh (RDL 25/2026 art. 13) + IVA 21 % (Ley 37/1992 art. 90 (RDL 25/2026 no reduce el IVA en octubre)) | J29: 2026-10-01 | K29: BOE-A-2026-20389 | L29: TUR.2: Consumo superior a 5.000 kWh/año e inferior o igual a 15.000 kWh/año.; término fijo 8.17 €/cliente/mes; impuestos aplicados los vigentes en la fecha de efectos

Sheet Datos 6 Gasóleo C
A1: 6. Gasóleo de calefacción: precio medio en España
A2: Fuente: Comisión Europea, Weekly Oil Bulletin (fichero histórico de precios). Unidad original: €/l. Frecuencia: semanal (precio del lunes). Impuestos del dato original: con impuestos (y también sin impuestos). Conversión: €/l ÷ 10.28 kWh/l (PCI)
A4: Fecha | B4: Periodo | C4: Valor original | D4: Unidad | E4: €/kWh sin impuestos | F4: €/kWh con impuestos | G4: Origen del precio con impuestos | H4: Impuestos aplicados | I4: Pendiente | J4: Fecha de publicación | K4: Referencia (fichero / BOE / PDF) | L4: Nota
A5: 43836 | B5: 2020-01-06 | C5: 0.80608 | D5: €/l | E5: 0.055396 | F5: 0.078412 | G5: original (el Boletín publica con y sin impuestos) | H5: IVA e impuesto sobre hidrocarburos incluidos por la fuente | K5: Weekly_Oil_Bulletin_Prices_History_maticni_4web.xlsx
A6: 43843 | B6: 2020-01-13 | C6: 0.79527 | D6: €/l | E6: 0.054527 | F6: 0.077361 | G6: original (el Boletín publica con y sin impuestos) | H6: IVA e impuesto sobre hidrocarburos incluidos por la fuente | K6: Weekly_Oil_Bulletin_Prices_History_maticni_4web.xlsx
A7: 43850 | B7: 2020-01-20 | C7: 0.77917 | D7: €/l | E7: 0.053232 | F7: 0.075795 | G7: original (el Boletín publica con y sin impuestos) | H7: IVA e impuesto sobre hidrocarburos incluidos por la fuente | K7: Weekly_Oil_Bulletin_Prices_History_maticni_4web.xlsx
A8: 43857 | B8: 2020-01-27 | C8: 0.76383 | D8: €/l | E8: 0.051999 | F8: 0.074303 | G8: original (el Boletín publica con y sin impuestos) | H8: IVA e impuesto sobre hidrocarburos incluidos por la fuente | K8: Weekly_Oil_Bulletin_Prices_History_maticni_4web.xlsx
A9: 43864 | B9: 2020-02-03 | C9: 0.73937 | D9: €/l | E9: 0.050033 | F9: 0.071923 | G9: original (el Boletín publica con y sin impuestos) | H9: IVA e impuesto sobre hidrocarburos incluidos por la fuente | K9: Weekly_Oil_Bulletin_Prices_History_maticni_4web.xlsx
A10: 43871 | B10: 2020-02-10 | C10: 0.70978 | D10: €/l | E10: 0.047655 | F10: 0.069045 | G10: original (el Boletín publica con y sin impuestos) | H10: IVA e impuesto sobre hidrocarburos incluidos por la fuente | K10: Weekly_Oil_Bulletin_Prices_History_maticni_4web.xlsx
A11: 43878 | B11: 2020-02-17 | C11: 0.7106 | D11: €/l | E11: 0.04772 | F11: 0.069125 | G11: original (el Boletín publica con y sin impuestos) | H11: IVA e impuesto sobre hidrocarburos incluidos por la fuente | K11: Weekly_Oil_Bulletin_Prices_History_maticni_4web.xlsx
A12: 43885 | B12: 2020-02-24 | C12: 0.71487 | D12: €/l | E12: 0.048063 | F12: 0.06954 | G12: original (el Boletín publica con y sin impuestos) | H12: IVA e impuesto sobre hidrocarburos incluidos por la fuente | K12: Weekly_Oil_Bulletin_Prices_History_maticni_4web.xlsx
A13: 43892 | B13: 2020-03-02 | C13: 0.68404 | D13: €/l | E13: 0.045585 | F13: 0.066541 | G13: original (el Boletín publica con y sin impuestos) | H13: IVA e impuesto sobre hidrocarburos incluidos por la fuente | K13: Weekly_Oil_Bulletin_Prices_History_maticni_4web.xlsx
A14: 43899 | B14: 2020-03-09 | C14: 0.65824 | D14: €/l | E14: 0.043511 | F14: 0.064031 | G14: original (el Boletín publica con y sin impuestos) | H14: IVA e impuesto sobre hidrocarburos incluidos por la fuente | K14: Weekly_Oil_Bulletin_Prices_History_maticni_4web.xlsx
A15: 43906 | B15: 2020-03-16 | C15: 0.59722 | D15: €/l | E15: 0.038605 | F15: 0.058095 | G15: original (el Boletín publica con y sin impuestos) | H15: IVA e impuesto sobre hidrocarburos incluidos por la fuente | K15: Weekly_Oil_Bulletin_Prices_History_maticni_4web.xlsx
A16: 43913 | B16: 2020-03-23 | C16: 0.56374 | D16: €/l | E16: 0.035913 | F16: 0.054839 | G16: original (el Boletín publica con y sin impuestos) | H16: IVA e impuesto sobre hidrocarburos incluidos por la fuente | K16: Weekly_Oil_Bulletin_Prices_History_maticni_4web.xlsx
... A116: 44648 | B116: 2022-03-28 | C116: 1.39098 | D116: €/l | E116: 0.102418 | F116: 0.135309 | G116: original (el Boletín publica con y sin impuestos) | H116: IVA e impuesto sobre hidrocarburos incluidos por la fuente | K116: Weekly_Oil_Bulletin_Prices_History_maticni_4web.xlsx
A117: 44655 | B117: 2022-04-04 | C117: 1.31533 | D117: €/l | E117: 0.096337 | F117: 0.12795 | G117: original (el Boletín publica con y sin impuestos) | H117: IVA e impuesto sobre hidrocarburos incluidos por la fuente | K117: Weekly_Oil_Bulletin_Prices_History_maticni_4web.xlsx | L117: precio antes de la bonificación de 20 c€/l (RDL 6/2022), que el Boletín no descuenta
A118: 44662 | B118: 2022-04-11 | C118: 1.3144 | D118: €/l | E118: 0.096262 | F118: 0.12786 | G118: original (el Boletín publica con y sin impuestos) | H118: IVA e impuesto sobre hidrocarburos incluidos por la fuente | K118: Weekly_Oil_Bulletin_Prices_History_maticni_4web.xlsx | L118: precio antes de la bonificación de 20 c€/l (RDL 6/2022), que el Boletín no descuenta
A119: 44676 | B119: 2022-04-25 | C119: 1.37468 | D119: €/l | E119: 0.101108 | F119: 0.133724 | G119: original (el Boletín publica con y sin impuestos) | H119: IVA e impuesto sobre hidrocarburos incluidos por la fuente | K119: Weekly_Oil_Bulletin_Prices_History_maticni_4web.xlsx | L119: precio antes de la bonificación de 20 c€/l (RDL 6/2022), que el Boletín no descuenta
A120: 44683 | B120: 2022-05-02 | C120: 1.35215 | D120: €/l | E120: 0.099297 | F120: 0.131532 | G120: original (el Boletín publica con y sin impuestos) | H120: IVA e impuesto sobre hidrocarburos incluidos por la fuente | K120: Weekly_Oil_Bulletin_Prices_History_maticni_4web.xlsx | L120: precio antes de la bonificación de 20 c€/l (RDL 6/2022), que el Boletín no descuenta
A121: 44690 | B121: 2022-05-09 | C121: 1.39274 | D121: €/l | E121: 0.102559 | F121: 0.135481 | G121: original (el Boletín publica con y sin impuestos) | H121: IVA e impuesto sobre hidrocarburos incluidos por la fuente | K121: Weekly_Oil_Bulletin_Prices_History_maticni_4web.xlsx | L121: precio antes de la bonificación de 20 c€/l (RDL 6/2022), que el Boletín no descuenta
A122: 44697 | B122: 2022-05-16 | C122: 1.35456 | D122: €/l | E122: 0.09949 | F122: 0.131767 | G122: original (el Boletín publica con y sin impuestos) | H122: IVA e impuesto sobre hidrocarburos incluidos por la fuente | K122: Weekly_Oil_Bulletin_Prices_History_maticni_4web.xlsx | L122: precio antes de la bonificación de 20 c€/l (RDL 6/2022), que el Boletín no descuenta
A123: 44704 | B123: 2022-05-23 | C123: 1.33562 | D123: €/l | E123: 0.097968 | F123: 0.129924 | G123: original (el Boletín publica con y sin impuestos) | H123: IVA e impuesto sobre hidrocarburos incluidos por la fuente | K123: Weekly_Oil_Bulletin_Prices_History_maticni_4web.xlsx | L123: precio antes de la bonificación de 20 c€/l (RDL 6/2022), que el Boletín no descuenta
A124: 44711 | B124: 2022-05-30 | C124: 1.36892 | D124: €/l | E124: 0.100645 | F124: 0.133163 | G124: original (el Boletín publica con y sin impuestos) | H124: IVA e impuesto sobre hidrocarburos incluidos por la fuente | K124: Weekly_Oil_Bulletin_Prices_History_maticni_4web.xlsx | L124: precio antes de la bonificación de 20 c€/l (RDL 6/2022), que el Boletín no descuenta
A125: 44718 | B125: 2022-06-06 | C125: 1.43242 | D125: €/l | E125: 0.10575 | F125: 0.13934 | G125: original (el Boletín publica con y sin impuestos) | H125: IVA e impuesto sobre hidrocarburos incluidos por la fuente | K125: Weekly_Oil_Bulletin_Prices_History_maticni_4web.xlsx | L125: precio antes de la bonificación de 20 c€/l (RDL 6/2022), que el Boletín no descuenta
A126: 44725 | B126: 2022-06-13 | C126: 1.52343 | D126: €/l | E126: 0.113066 | F126: 0.148194 | G126: original (el Boletín publica con y sin impuestos) | H126: IVA e impuesto sobre hidrocarburos incluidos por la fuente | K126: Weekly_Oil_Bulletin_Prices_History_maticni_4web.xlsx | L126: precio antes de la bonificación de 20 c€/l (RDL 6/2022), que el Boletín no descuenta
A127: 44732 | B127: 2022-06-20 | C127: 1.59373 | D127: €/l | E127: 0.118718 | F127: 0.155032 | G127: original (el Boletín publica con y sin impuestos) | H127: IVA e impuesto sobre hidrocarburos incluidos por la fuente | K127: Weekly_Oil_Bulletin_Prices_History_maticni_4web.xlsx | L127: precio antes de la bonificación de 20 c€/l (RDL 6/2022), que el Boletín no descuenta
A128: 44739 | B128: 2022-06-27 | C128: 1.58552 | D128: €/l | E128: 0.118058 | F128: 0.154233 | G128: original (el Boletín publica con y sin impuestos) | H128: IVA e impuesto sobre hidrocarburos incluidos por la fuente | K128: Weekly_Oil_Bulletin_Prices_History_maticni_4web.xlsx | L128: precio antes de la bonificación de 20 c€/l (RDL 6/2022), que el Boletín no descuenta
... A154: 44921 | B154: 2022-12-26 | C154: 1.13629 | D154: €/l | E154: 0.081943 | F154: 0.110534 | G154: original (el Boletín publica con y sin impuestos) | H154: IVA e impuesto sobre hidrocarburos incluidos por la fuente | K154: Weekly_Oil_Bulletin_Prices_History_maticni_4web.xlsx | L154: precio antes de la bonificación de 20 c€/l (RDL 6/2022), que el Boletín no descuenta
A155: 44928 | B155: 2023-01-02 | C155: 1.18091 | D155: €/l | E155: 0.08553 | F155: 0.114875 | G155: original (el Boletín publica con y sin impuestos) | H155: IVA e impuesto sobre hidrocarburos incluidos por la fuente | K155: Weekly_Oil_Bulletin_Prices_History_maticni_4web.xlsx
A156: 44935 | B156: 2023-01-09 | C156: 1.19221 | D156: €/l | E156: 0.086439 | F156: 0.115974 | G156: original (el Boletín publica con y sin impuestos) | H156: IVA e impuesto sobre hidrocarburos incluidos por la fuente | K156: Weekly_Oil_Bulletin_Prices_History_maticni_4web.xlsx
A157: 44942 | B157: 2023-01-16 | C157: 1.16273 | D157: €/l | E157: 0.084068 | F157: 0.113106 | G157: original (el Boletín publica con y sin impuestos) | H157: IVA e impuesto sobre hidrocarburos incluidos por la fuente | K157: Weekly_Oil_Bulletin_Prices_History_maticni_4web.xlsx
A158: 44949 | B158: 2023-01-23 | C158: 1.15649 | D158: €/l | E158: 0.083567 | F158: 0.112499 | G158: original (el Boletín publica con y sin impuestos) | H158: IVA e impuesto sobre hidrocarburos incluidos por la fuente | K158: Weekly_Oil_Bulletin_Prices_History_maticni_4web.xlsx
A159: 44956 | B159: 2023-01-30 | C159: 1.16875 | D159: €/l | E159: 0.084553 | F159: 0.113692 | G159: original (el Boletín publica con y sin impuestos) | H159: IVA e impuesto sobre hidrocarburos incluidos por la fuente | K159: Weekly_Oil_Bulletin_Prices_History_maticni_4web.xlsx
A160: 44963 | B160: 2023-02-06 | C160: 1.11096 | D160: €/l | E160: 0.079907 | F160: 0.10807 | G160: original (el Boletín publica con y sin impuestos) | H160: IVA e impuesto sobre hidrocarburos incluidos por la fuente | K160: Weekly_Oil_Bulletin_Prices_History_maticni_4web.xlsx
A161: 44970 | B161: 2023-02-13 | C161: 1.09291 | D161: €/l | E161: 0.078455 | F161: 0.106314 | G161: original (el Boletín publica con y sin impuestos) | H161: IVA e impuesto sobre hidrocarburos incluidos por la fuente | K161: Weekly_Oil_Bulletin_Prices_History_maticni_4web.xlsx
A162: 44977 | B162: 2023-02-20 | C162: 1.09651 | D162: €/l | E162: 0.078745 | F162: 0.106664 | G162: original (el Boletín publica con y sin impuestos) | H162: IVA e impuesto sobre hidrocarburos incluidos por la fuente | K162: Weekly_Oil_Bulletin_Prices_History_maticni_4web.xlsx
A163: 44984 | B163: 2023-02-27 | C163: 1.07139 | D163: €/l | E163: 0.076726 | F163: 0.104221 | G163: original (el Boletín publica con y sin impuestos) | H163: IVA e impuesto sobre hidrocarburos incluidos por la fuente | K163: Weekly_Oil_Bulletin_Prices_History_maticni_4web.xlsx
A164: 44991 | B164: 2023-03-06 | C164: 1.09768 | D164: €/l | E164: 0.078839 | F164: 0.106778 | G164: original (el Boletín publica con y sin impuestos) | H164: IVA e impuesto sobre hidrocarburos incluidos por la fuente | K164: Weekly_Oil_Bulletin_Prices_History_maticni_4web.xlsx
A165: 44998 | B165: 2023-03-13 | C165: 1.08547 | D165: €/l | E165: 0.077857 | F165: 0.10559 | G165: original (el Boletín publica con y sin impuestos) | H165: IVA e impuesto sobre hidrocarburos incluidos por la fuente | K165: Weekly_Oil_Bulletin_Prices_History_maticni_4web.xlsx
A166: 45005 | B166: 2023-03-20 | C166: 1.05801 | D166: €/l | E166: 0.07565 | F166: 0.102919 | G166: original (el Boletín publica con y sin impuestos) | H166: IVA e impuesto sobre hidrocarburos incluidos por la fuente | K166: Weekly_Oil_Bulletin_Prices_History_maticni_4web.xlsx
... A353: 46314 | B353: 2026-10-19 | C353: 1.52133 | D353: €/l | E353: 0.120263 | F353: 0.147989 | G353: original (el Boletín publica con y sin impuestos) | H353: IVA e impuesto sobre hidrocarburos incluidos por la fuente | K353: Weekly_Oil_Bulletin_Prices_History_maticni_4web.xlsx

Sheet Datos 7 Butano
A1: 7. Butano: bombona regulada de 12,5 kg
A2: Fuente: BOE, resoluciones de la DGPEM con los precios máximos de venta, antes de impuestos, de los GLP envasados. Unidad original: c€/kg (antes de impuestos). Frecuencia: bimestral (valor vigente desde el tercer martes de ene/mar/may/jul/sep/nov). Impuestos del dato original: sin impuestos. Conversión: bombona: c€/kg ÷ 100 × 12,5 kg (+ IH GLP, × (1 + IVA)); €/kWh = € ÷ 12,5 kg ÷ 12.73 kWh/kg (PCI)
A4: Fecha | B4: Periodo | C4: Valor original | D4: Unidad | E4: €/kWh sin impuestos | F4: €/kWh con impuestos | G4: Origen del precio con impuestos | H4: Impuestos aplicados | I4: Pendiente | J4: Fecha de publicación | K4: Referencia (fichero / BOE / PDF) | L4: Nota
A5: 43788 | B5: 2019-11-19 | C5: 82.784 | D5: c€/kg (antes de impuestos) | E5: 0.065031 | F5: 0.080113 | G5: calculado | H5: IH GLP 15.0 €/t (Ley 38/1992 art. 50, epígrafe 1.8) + IVA 21 % (Ley 37/1992 art. 90) | J5: 2019-11-18 | K5: BOE-A-2019-16520 | L5: bombona 12,5 kg: 10.35 € antes de impuestos; 12.75 € con impuestos (calculado)
A6: 43851 | B6: 2020-01-21 | C6: 86.9232 | D6: c€/kg (antes de impuestos) | E6: 0.068282 | F6: 0.084047 | G6: calculado | H6: IH GLP 15.0 €/t (Ley 38/1992 art. 50, epígrafe 1.8) + IVA 21 % (Ley 37/1992 art. 90) | J6: 2020-01-20 | K6: BOE-A-2020-791 | L6: bombona 12,5 kg: 10.87 € antes de impuestos; 13.37 € con impuestos (calculado)
A7: 44033 | B7: 2020-07-21 | C7: 82.577 | D7: c€/kg (antes de impuestos) | E7: 0.064868 | F7: 0.079916 | G7: calculado | H7: IH GLP 15.0 €/t (Ley 38/1992 art. 50, epígrafe 1.8) + IVA 21 % (Ley 37/1992 art. 90) | J7: 2020-07-20 | K7: BOE-A-2020-8154 | L7: bombona 12,5 kg: 10.32 € antes de impuestos; 12.72 € con impuestos (calculado)
A8: 44089 | B8: 2020-09-15 | C8: 78.4482 | D8: c€/kg (antes de impuestos) | E8: 0.061625 | F8: 0.075992 | G8: calculado | H8: IH GLP 15.0 €/t (Ley 38/1992 art. 50, epígrafe 1.8) + IVA 21 % (Ley 37/1992 art. 90) | J8: 2020-09-14 | K8: BOE-A-2020-10592 | L8: bombona 12,5 kg: 9.81 € antes de impuestos; 12.09 € con impuestos (calculado)
A9: 44152 | B9: 2020-11-17 | C9: 82.3706 | D9: c€/kg (antes de impuestos) | E9: 0.064706 | F9: 0.07972 | G9: calculado | H9: IH GLP 15.0 €/t (Ley 38/1992 art. 50, epígrafe 1.8) + IVA 21 % (Ley 37/1992 art. 90) | J9: 2020-11-16 | K9: BOE-A-2020-14249 | L9: bombona 12,5 kg: 10.30 € antes de impuestos; 12.69 € con impuestos (calculado)
A10: 44215 | B10: 2021-01-19 | C10: 86.4891 | D10: c€/kg (antes de impuestos) | E10: 0.067941 | F10: 0.083635 | G10: calculado | H10: IH GLP 15.0 €/t (Ley 38/1992 art. 50, epígrafe 1.8) + IVA 21 % (Ley 37/1992 art. 90) | J10: 2021-01-18 | K10: BOE-A-2021-712 | L10: bombona 12,5 kg: 10.81 € antes de impuestos; 13.31 € con impuestos (calculado)
A11: 44271 | B11: 2021-03-16 | C11: 90.8136 | D11: c€/kg (antes de impuestos) | E11: 0.071338 | F11: 0.087745 | G11: calculado | H11: IH GLP 15.0 €/t (Ley 38/1992 art. 50, epígrafe 1.8) + IVA 21 % (Ley 37/1992 art. 90) | J11: 2021-03-15 | K11: BOE-A-2021-3986 | L11: bombona 12,5 kg: 11.35 € antes de impuestos; 13.96 € con impuestos (calculado)
A12: 44334 | B12: 2021-05-18 | C12: 95.3543 | D12: c€/kg (antes de impuestos) | E12: 0.074905 | F12: 0.092061 | G12: calculado | H12: IH GLP 15.0 €/t (Ley 38/1992 art. 50, epígrafe 1.8) + IVA 21 % (Ley 37/1992 art. 90) | J12: 2021-05-17 | K12: BOE-A-2021-8103 | L12: bombona 12,5 kg: 11.92 € antes de impuestos; 14.65 € con impuestos (calculado)
A13: 44397 | B13: 2021-07-20 | C13: 100.122 | D13: c€/kg (antes de impuestos) | E13: 0.07865 | F13: 0.096593 | G13: calculado | H13: IH GLP 15.0 €/t (Ley 38/1992 art. 50, epígrafe 1.8) + IVA 21 % (Ley 37/1992 art. 90) | J13: 2021-07-19 | K13: BOE-A-2021-11961 | L13: bombona 12,5 kg: 12.52 € antes de impuestos; 15.37 € con impuestos (calculado)
A14: 44460 | B14: 2021-09-21 | C14: 105.1281 | D14: c€/kg (antes de impuestos) | E14: 0.082583 | F14: 0.101351 | G14: calculado | H14: IH GLP 15.0 €/t (Ley 38/1992 art. 50, epígrafe 1.8) + IVA 21 % (Ley 37/1992 art. 90) | J14: 2021-09-20 | K14: BOE-A-2021-15175 | L14: bombona 12,5 kg: 13.14 € antes de impuestos; 16.13 € con impuestos (calculado)
A15: 44516 | B15: 2021-11-16 | C15: 110.3845 | D15: c€/kg (antes de impuestos) | E15: 0.086712 | F15: 0.106347 | G15: calculado | H15: IH GLP 15.0 €/t (Ley 38/1992 art. 50, epígrafe 1.8) + IVA 21 % (Ley 37/1992 art. 90) | J15: 2021-11-15 | K15: BOE-A-2021-18614 | L15: bombona 12,5 kg: 13.80 € antes de impuestos; 16.92 € con impuestos (calculado)
A16: 44579 | B16: 2022-01-18 | C16: 115.9037 | D16: c€/kg (antes de impuestos) | E16: 0.091048 | F16: 0.111593 | G16: calculado | H16: IH GLP 15.0 €/t (Ley 38/1992 art. 50, epígrafe 1.8) + IVA 21 % (Ley 37/1992 art. 90) | J16: 2022-01-17 | K16: BOE-A-2022-665 | L16: bombona 12,5 kg: 14.49 € antes de impuestos; 17.76 € con impuestos (calculado)
... A44: 46280 | B44: 2026-09-15 | C44: 123.4447 | D44: c€/kg (antes de impuestos) | E44: 0.096971 | F44: 0.118405 | G44: calculado | H44: IH GLP 11.25 €/t (RDL 18/2026 art. 7) + IVA 21 % (Ley 37/1992 art. 90) | J44: 2026-09-14 | K44: BOE-A-2026-19115 | L44: bombona 12,5 kg: 15.43 € antes de impuestos; 18.84 € con impuestos (calculado)

Sheet Datos 8 Pellet saco 15 kg
A1: 8. Pellet: precio medio en España del saco de 15 kg
A2: Fuente: AVEBIOM, Índice de Precios de Biomasa al Consumidor (pellet de madera). Unidad original: €/saco. Frecuencia: trimestral (medias anuales antes de 4T2024). Impuestos del dato original: con impuestos (IVA incluido según AVEBIOM). Conversión: €/saco ÷ 15 kg ÷ 4.8 kWh/kg (PCI; decisión 9). Se guarda también el c€/kWh de AVEBIOM (4,76 kWh/kg).
A4: Fecha | B4: Periodo | C4: Valor original | D4: Unidad | E4: €/kWh sin impuestos | F4: €/kWh con impuestos | G4: Origen del precio con impuestos | H4: Impuestos aplicados | I4: Pendiente | J4: Fecha de publicación | K4: Referencia (fichero / BOE / PDF) | L4: Nota
A5: 43831 | B5: 2020 | C5: 4.39 | D5: €/saco | F5: 0.060972 | G5: original (IVA incluido según AVEBIOM) | H5: IVA incluido por la fuente (AVEBIOM indica el 21 % en el 3T2026; el tipo aplicado en trimestres con IVA reducido no está detallado) | J5: 2026-10-20 | K5: IPB-indice-precios-PELLET-3T2026.pdf | L5: media anual publicada por AVEBIOM (no hay dato trimestral descargable); c€/kWh según AVEBIOM (4,76 kWh/kg): 6.14
A6: 44197 | B6: 2021 | C6: 4.34 | D6: €/saco | F6: 0.060278 | G6: original (IVA incluido según AVEBIOM) | H6: IVA incluido por la fuente (AVEBIOM indica el 21 % en el 3T2026; el tipo aplicado en trimestres con IVA reducido no está detallado) | J6: 2026-10-20 | K6: IPB-indice-precios-PELLET-3T2026.pdf | L6: media anual publicada por AVEBIOM (no hay dato trimestral descargable); c€/kWh según AVEBIOM (4,76 kWh/kg): 6.07
A7: 44562 | B7: 2022 | C7: 6.53 | D7: €/saco | F7: 0.090694 | G7: original (IVA incluido según AVEBIOM) | H7: IVA incluido por la fuente (AVEBIOM indica el 21 % en el 3T2026; el tipo aplicado en trimestres con IVA reducido no está detallado) | J7: 2026-10-20 | K7: IPB-indice-precios-PELLET-3T2026.pdf | L7: media anual publicada por AVEBIOM (no hay dato trimestral descargable); c€/kWh según AVEBIOM (4,76 kWh/kg): 9.14
A8: 44927 | B8: 2023 | C8: 6.21 | D8: €/saco | F8: 0.08625 | G8: original (IVA incluido según AVEBIOM) | H8: IVA incluido por la fuente (AVEBIOM indica el 21 % en el 3T2026; el tipo aplicado en trimestres con IVA reducido no está detallado) | J8: 2026-10-20 | K8: IPB-indice-precios-PELLET-3T2026.pdf | L8: media anual publicada por AVEBIOM (no hay dato trimestral descargable); c€/kWh según AVEBIOM (4,76 kWh/kg): 8.68
A9: 45292 | B9: 2024 | C9: 5.25 | D9: €/saco | F9: 0.072917 | G9: original (IVA incluido según AVEBIOM) | H9: IVA incluido por la fuente (AVEBIOM indica el 21 % en el 3T2026; el tipo aplicado en trimestres con IVA reducido no está detallado) | J9: 2026-10-20 | K9: IPB-indice-precios-PELLET-3T2026.pdf | L9: media anual publicada por AVEBIOM (no hay dato trimestral descargable); c€/kWh según AVEBIOM (4,76 kWh/kg): 7.35
A10: 45566 | B10: 2024T4 | C10: 5.17 | D10: €/saco | F10: 0.071806 | G10: original (IVA incluido según AVEBIOM) | H10: IVA incluido por la fuente (AVEBIOM indica el 21 % en el 3T2026; el tipo aplicado en trimestres con IVA reducido no está detallado) | J10: 2026-02-04 | K10: IPB-indice-precios-PELLET-4T2025-1.pdf | L10: precio medio trimestral; c€/kWh según AVEBIOM (4,76 kWh/kg): 7.23
A11: 45658 | B11: 2025T1 | C11: 5.04 | D11: €/saco | F11: 0.07 | G11: original (IVA incluido según AVEBIOM) | H11: IVA incluido por la fuente (AVEBIOM indica el 21 % en el 3T2026; el tipo aplicado en trimestres con IVA reducido no está detallado) | J11: 2026-05-04 | K11: IPB-indice-precios-PELLET-1T2026.pdf | L11: precio medio trimestral; c€/kWh según AVEBIOM (4,76 kWh/kg): 7.05
A12: 45748 | B12: 2025T2 | C12: 5.14 | D12: €/saco | F12: 0.071389 | G12: original (IVA incluido según AVEBIOM) | H12: IVA incluido por la fuente (AVEBIOM indica el 21 % en el 3T2026; el tipo aplicado en trimestres con IVA reducido no está detallado) | J12: 2026-07-31 | K12: IPB-indice-precios-PELLET-2T2026.pdf | L12: precio medio trimestral; c€/kWh según AVEBIOM (4,76 kWh/kg): 7.19
A13: 45839 | B13: 2025T3 | C13: 5.12 | D13: €/saco | F13: 0.071111 | G13: original (IVA incluido según AVEBIOM) | H13: IVA incluido por la fuente (AVEBIOM indica el 21 % en el 3T2026; el tipo aplicado en trimestres con IVA reducido no está detallado) | J13: 2026-10-20 | K13: IPB-indice-precios-PELLET-3T2026.pdf | L13: precio medio trimestral; c€/kWh según AVEBIOM (4,76 kWh/kg): 7.17
A14: 45931 | B14: 2025T4 | C14: 5.31 | D14: €/saco | F14: 0.07375 | G14: original (IVA incluido según AVEBIOM) | H14: IVA incluido por la fuente (AVEBIOM indica el 21 % en el 3T2026; el tipo aplicado en trimestres con IVA reducido no está detallado) | J14: 2026-10-20 | K14: IPB-indice-precios-PELLET-3T2026.pdf | L14: precio medio trimestral; c€/kWh según AVEBIOM (4,76 kWh/kg): 7.43
A15: 46023 | B15: 2026T1 | C15: 5.29 | D15: €/saco | F15: 0.073472 | G15: original (IVA incluido según AVEBIOM) | H15: IVA incluido por la fuente (AVEBIOM indica el 21 % en el 3T2026; el tipo aplicado en trimestres con IVA reducido no está detallado) | J15: 2026-10-20 | K15: IPB-indice-precios-PELLET-3T2026.pdf | L15: precio medio trimestral; c€/kWh según AVEBIOM (4,76 kWh/kg): 7.39
A16: 46113 | B16: 2026T2 | C16: 5.67 | D16: €/saco | F16: 0.07875 | G16: original (IVA incluido según AVEBIOM) | H16: IVA incluido por la fuente (AVEBIOM indica el 21 % en el 3T2026; el tipo aplicado en trimestres con IVA reducido no está detallado) | J16: 2026-10-20 | K16: IPB-indice-precios-PELLET-3T2026.pdf | L16: precio medio trimestral; c€/kWh según AVEBIOM (4,76 kWh/kg): 7.94
A17: 46204 | B17: 2026T3 | C17: 5.92 | D17: €/saco | F17: 0.082222 | G17: original (IVA incluido según AVEBIOM) | H17: IVA incluido por la fuente (AVEBIOM indica el 21 % en el 3T2026; el tipo aplicado en trimestres con IVA reducido no está detallado) | J17: 2026-10-20 | K17: IPB-indice-precios-PELLET-3T2026.pdf | L17: precio medio trimestral; c€/kWh según AVEBIOM (4,76 kWh/kg): 8.28

Sheet Datos 8 Pellet granel
A1: 8. Pellet: precio medio en España a granel en volquete
A2: Fuente: AVEBIOM, Índice de Precios de Biomasa al Consumidor (pellet de madera). Unidad original: €/t. Frecuencia: trimestral (medias anuales antes de 4T2024). Impuestos del dato original: con impuestos (IVA y transporte incluidos según AVEBIOM). Conversión: €/t ÷ 1.000 ÷ 4.8 kWh/kg (PCI; decisión 9). Se guarda también el c€/kWh de AVEBIOM.
A4: Fecha | B4: Periodo | C4: Valor original | D4: Unidad | E4: €/kWh sin impuestos | F4: €/kWh con impuestos | G4: Origen del precio con impuestos | H4: Impuestos aplicados | I4: Pendiente | J4: Fecha de publicación | K4: Referencia (fichero / BOE / PDF) | L4: Nota
A5: 43831 | B5: 2020 | C5: 240.27 | D5: €/t | F5: 0.050056 | G5: original (IVA incluido según AVEBIOM) | H5: IVA incluido por la fuente (AVEBIOM indica el 21 % en el 3T2026; el tipo aplicado en trimestres con IVA reducido no está detallado) | J5: 2026-10-20 | K5: IPB-indice-precios-PELLET-3T2026.pdf | L5: media anual publicada por AVEBIOM (no hay dato trimestral descargable); c€/kWh según AVEBIOM (4,76 kWh/kg): 5.04
A6: 44197 | B6: 2021 | C6: 246.43 | D6: €/t | F6: 0.05134 | G6: original (IVA incluido según AVEBIOM) | H6: IVA incluido por la fuente (AVEBIOM indica el 21 % en el 3T2026; el tipo aplicado en trimestres con IVA reducido no está detallado) | J6: 2026-10-20 | K6: IPB-indice-precios-PELLET-3T2026.pdf | L6: media anual publicada por AVEBIOM (no hay dato trimestral descargable); c€/kWh según AVEBIOM (4,76 kWh/kg): 5.17
A7: 44562 | B7: 2022 | C7: 407.88 | D7: €/t | F7: 0.084975 | G7: original (IVA incluido según AVEBIOM) | H7: IVA incluido por la fuente (AVEBIOM indica el 21 % en el 3T2026; el tipo aplicado en trimestres con IVA reducido no está detallado) | J7: 2026-10-20 | K7: IPB-indice-precios-PELLET-3T2026.pdf | L7: media anual publicada por AVEBIOM (no hay dato trimestral descargable); c€/kWh según AVEBIOM (4,76 kWh/kg): 8.56
A8: 44927 | B8: 2023 | C8: 361.35 | D8: €/t | F8: 0.075281 | G8: original (IVA incluido según AVEBIOM) | H8: IVA incluido por la fuente (AVEBIOM indica el 21 % en el 3T2026; el tipo aplicado en trimestres con IVA reducido no está detallado) | J8: 2026-10-20 | K8: IPB-indice-precios-PELLET-3T2026.pdf | L8: media anual publicada por AVEBIOM (no hay dato trimestral descargable); c€/kWh según AVEBIOM (4,76 kWh/kg): 7.58
A9: 45292 | B9: 2024 | C9: 324.73 | D9: €/t | F9: 0.067652 | G9: original (IVA incluido según AVEBIOM) | H9: IVA incluido por la fuente (AVEBIOM indica el 21 % en el 3T2026; el tipo aplicado en trimestres con IVA reducido no está detallado) | J9: 2026-10-20 | K9: IPB-indice-precios-PELLET-3T2026.pdf | L9: media anual publicada por AVEBIOM (no hay dato trimestral descargable); c€/kWh según AVEBIOM (4,76 kWh/kg): 6.81
A10: 45566 | B10: 2024T4 | C10: 316.99 | D10: €/t | F10: 0.06604 | G10: original (IVA incluido según AVEBIOM) | H10: IVA incluido por la fuente (AVEBIOM indica el 21 % en el 3T2026; el tipo aplicado en trimestres con IVA reducido no está detallado) | J10: 2026-02-04 | K10: IPB-indice-precios-PELLET-4T2025-1.pdf | L10: precio medio trimestral; c€/kWh según AVEBIOM (4,76 kWh/kg): 6.65
A11: 45658 | B11: 2025T1 | C11: 308.57 | D11: €/t | F11: 0.064285 | G11: original (IVA incluido según AVEBIOM) | H11: IVA incluido por la fuente (AVEBIOM indica el 21 % en el 3T2026; el tipo aplicado en trimestres con IVA reducido no está detallado) | J11: 2026-05-04 | K11: IPB-indice-precios-PELLET-1T2026.pdf | L11: precio medio trimestral; c€/kWh según AVEBIOM (4,76 kWh/kg): 6.48
A12: 45748 | B12: 2025T2 | C12: 309.5 | D12: €/t | F12: 0.064479 | G12: original (IVA incluido según AVEBIOM) | H12: IVA incluido por la fuente (AVEBIOM indica el 21 % en el 3T2026; el tipo aplicado en trimestres con IVA reducido no está detallado) | J12: 2026-07-31 | K12: IPB-indice-precios-PELLET-2T2026.pdf | L12: precio medio trimestral; c€/kWh según AVEBIOM (4,76 kWh/kg): 6.5
A13: 45839 | B13: 2025T3 | C13: 312.13 | D13: €/t | F13: 0.065027 | G13: original (IVA incluido según AVEBIOM) | H13: IVA incluido por la fuente (AVEBIOM indica el 21 % en el 3T2026; el tipo aplicado en trimestres con IVA reducido no está detallado) | J13: 2026-10-20 | K13: IPB-indice-precios-PELLET-3T2026.pdf | L13: precio medio trimestral; c€/kWh según AVEBIOM (4,76 kWh/kg): 6.55
A14: 45931 | B14: 2025T4 | C14: 327.38 | D14: €/t | F14: 0.068204 | G14: original (IVA incluido según AVEBIOM) | H14: IVA incluido por la fuente (AVEBIOM indica el 21 % en el 3T2026; el tipo aplicado en trimestres con IVA reducido no está detallado) | J14: 2026-10-20 | K14: IPB-indice-precios-PELLET-3T2026.pdf | L14: precio medio trimestral; c€/kWh según AVEBIOM (4,76 kWh/kg): 6.87
A15: 46023 | B15: 2026T1 | C15: 346.85 | D15: €/t | F15: 0.07226 | G15: original (IVA incluido según AVEBIOM) | H15: IVA incluido por la fuente (AVEBIOM indica el 21 % en el 3T2026; el tipo aplicado en trimestres con IVA reducido no está detallado) | J15: 2026-10-20 | K15: IPB-indice-precios-PELLET-3T2026.pdf | L15: precio medio trimestral; c€/kWh según AVEBIOM (4,76 kWh/kg): 7.28
A16: 46113 | B16: 2026T2 | C16: 352.28 | D16: €/t | F16: 0.073392 | G16: original (IVA incluido según AVEBIOM) | H16: IVA incluido por la fuente (AVEBIOM indica el 21 % en el 3T2026; el tipo aplicado en trimestres con IVA reducido no está detallado) | J16: 2026-10-20 | K16: IPB-indice-precios-PELLET-3T2026.pdf | L16: precio medio trimestral; c€/kWh según AVEBIOM (4,76 kWh/kg): 7.39
A17: 46204 | B17: 2026T3 | C17: 370.24 | D17: €/t | F17: 0.077133 | G17: original (IVA incluido según AVEBIOM) | H17: IVA incluido por la fuente (AVEBIOM indica el 21 % en el 3T2026; el tipo aplicado en trimestres con IVA reducido no está detallado) | J17: 2026-10-20 | K17: IPB-indice-precios-PELLET-3T2026.pdf | L17: precio medio trimestral; c€/kWh según AVEBIOM (4,76 kWh/kg): 7.77

Sheet Fuentes y criterios
A1: N.º | B1: Indicador | C1: Fuente | D1: Dirección | E1: Unidad original | F1: Frecuencia | G1: Impuestos del dato original | H1: Conversión a €/kWh | I1: Nota
A2: 1 | B2: Electricidad: precio del mercado diario OMIE, España | C2: OMIE, ficheros marginalpdbc (precio marginal del mercado diario) | D2: https://www.omie.es/es/file-access-list?parents=/Mercado%20Diario/1.%20Precios&dir=Precios%20horarios%20del%20mercado%20diario%20en%20Espa%C3%B1a&realdir=marginalpdbc | E2: €/MWh | F2: diaria (media aritmética de los periodos horarios o cuarto-horarios del día) | G2: sin impuestos (precio mayorista) | H2: €/MWh ÷ 1.000 = €/kWh | I2: Precio mayorista: no se le aplican impuestos (decisión 1).
A3: 2 | B3: Gas natural: MIBGAS-ES Index | C3: MIBGAS, fichero anual MIBGAS_Data (hoja de índices), MIBGAS-ES Index | D3: https://www.mibgas.es/es/file-access | E3: €/MWh | F3: diaria (por día de gas) | G3: sin impuestos (precio mayorista) | H3: €/MWh ÷ 1.000 = €/kWh (el índice se expresa sobre PCS, como todo el mercado gasista) | I3: Precio mayorista: no se le aplican impuestos (decisión 1).
A4: 3 | B4: Gasóleo de automoción: precio medio en España | C4: Comisión Europea, Weekly Oil Bulletin (fichero histórico de precios) | D4: https://energy.ec.europa.eu/data-and-analysis/weekly-oil-bulletin_en | E4: €/l | F4: semanal (precio del lunes) | G4: con impuestos (y también sin impuestos) | H4: €/l ÷ 10.28 kWh/l (PCI; decisión 10) | I4: De abril a diciembre de 2022 el Boletín no descuenta la bonificación de 20 c€/l del RDL 6/2022 (decisión 11).
A5: 4 | B5: Electricidad PVPC: término de energía, tarifa 2.0TD (Península) | C5: REE/ESIOS, indicador 1001 (término de facturación de energía activa del PVPC 2.0TD, Península) | D5: https://www.esios.ree.es/es/pvpc | E5: €/MWh | F5: diaria (media aritmética de los valores horarios o cuarto-horarios del día) | G5: sin impuestos | H5: €/MWh ÷ 1.000 = €/kWh; con impuestos: (precio + cuota IEE) × (1 + IVA) vigentes en la fecha | I5: Indicador 1001 de ESIOS. Requiere ESIOS_TOKEN. Existe desde el 01/06/2021 (inicio de la 2.0TD).
A6: 5 | B6: Gas natural TUR 2: término variable | C6: BOE, resoluciones de la DGPEM por las que se publica la tarifa de último recurso de gas natural | D6: https://www.boe.es/ | E6: c€/kWh (PCS) | F6: trimestral (valor vigente desde la fecha de efectos de cada resolución) | G6: sin impuestos | H6: c€/kWh (PCS) ÷ 100 ÷ 0.904 = €/kWh (PCI); con impuestos: (precio + IH gas) × (1 + IVA) vigentes | I6: Consumo entre 5.000 y 15.000 kWh/año.
A7: 6 | B7: Gasóleo de calefacción: precio medio en España | C7: Comisión Europea, Weekly Oil Bulletin (fichero histórico de precios) | D7: https://energy.ec.europa.eu/data-and-analysis/weekly-oil-bulletin_en | E7: €/l | F7: semanal (precio del lunes) | G7: con impuestos (y también sin impuestos) | H7: €/l ÷ 10.28 kWh/l (PCI) | I7: De abril a diciembre de 2022 el Boletín no descuenta la bonificación de 20 c€/l del RDL 6/2022 (decisión 11).
A8: 7 | B8: Butano: bombona regulada de 12,5 kg | C8: BOE, resoluciones de la DGPEM con los precios máximos de venta, antes de impuestos, de los GLP envasados | D8: https://www.boe.es/ | E8: c€/kg (antes de impuestos) | F8: bimestral (valor vigente desde el tercer martes de ene/mar/may/jul/sep/nov) | G8: sin impuestos | H8: bombona: c€/kg ÷ 100 × 12,5 kg (+ IH GLP, × (1 + IVA)); €/kWh = € ÷ 12,5 kg ÷ 12.73 kWh/kg (PCI) | I8: El BOE solo publica el precio antes de impuestos; el precio de la bombona con impuestos es calculado.
A9: 8 | B9: Pellet: precio medio en España del saco de 15 kg | C9: AVEBIOM, Índice de Precios de Biomasa al Consumidor (pellet de madera) | D9: https://avebiom.org/actividades/indice-de-precios-biocombustibles-solidos/ | E9: €/saco | F9: trimestral (medias anuales antes de 4T2024) | G9: con impuestos (IVA incluido según AVEBIOM) | H9: €/saco ÷ 15 kg ÷ 4.8 kWh/kg (PCI; decisión 9). Se guarda también el c€/kWh de AVEBIOM (4,76 kWh/kg). | I9: Trimestral solo desde 4T2024 (PDF disponibles); 2020–2024: medias anuales publicadas por AVEBIOM (decisión 6).
A10: 8 | B10: Pellet: precio medio en España a granel en volquete | C10: AVEBIOM, Índice de Precios de Biomasa al Consumidor (pellet de madera) | D10: https://avebiom.org/actividades/indice-de-precios-biocombustibles-solidos/ | E10: €/t | F10: trimestral (medias anuales antes de 4T2024) | G10: con impuestos (IVA y transporte incluidos según AVEBIOM) | H10: €/t ÷ 1.000 ÷ 4.8 kWh/kg (PCI; decisión 9). Se guarda también el c€/kWh de AVEBIOM. | I10: Trimestral solo desde 4T2024 (PDF disponibles); 2020–2024: medias anuales publicadas por AVEBIOM (decisión 6).
A12: Factores de conversión (poder calorífico inferior)
B13: Pellet de madera, PCI | C13: 4.8 | D13: kWh/kg | E13: Boletín de referencia (fuente citada: IDAE). AVEBIOM usa 4.100 kcal/kg = 4,76 kWh/kg en su índice.
B14: Pellet de madera, PCI usado por AVEBIOM | C14: 4.76 | D14: kWh/kg | E14: Índice de precios AVEBIOM: «poder calorífico del pellet de 4100 kcal/kg (4,76 kWh/kg)».
B15: Gasóleo (automoción y calefacción), PCI | C15: 10.28 | D15: kWh/l | E15: Boletín de referencia (fuente citada: IDAE). Decisión 10: mismo factor para gasóleo A y C.
B16: Butano, PCI | C16: 12.73 | D16: kWh/kg | E16: Boletín de referencia (fuente citada: IDAE).
B17: Gas natural, relación PCI/PCS | C17: 0.904 | D17: adimensional | E17: Boletín de referencia (fuente citada: IDAE). La TUR se factura en kWh sobre PCS.
A19: Criterios
A20: Nada se rellena ni se estima: si la fuente no da un dato, la celda queda vacía (n. d.).
A21: Datos originales (valor original) frente a calculados (precio con impuestos de PVPC, TUR 2 y butano). El Boletín Petrolero y AVEBIOM publican ya con impuestos.
A22: Impuestos vigentes en cada fecha, con referencia al BOE en la columna «Impuestos aplicados»; en 2026 varios tipos dependen del IPC del INE.
A23: Medias mensuales: media aritmética de los datos del mes (diarios/semanales); valor vigente ponderado por días (TUR 2, butano); valor del periodo (pellet).
A24: OMIE y MIBGAS son precios mayoristas y se muestran sin impuestos.
A25: Metodología completa y tabla de impuestos: https://github.com/pablopardopazosgestan/cuadro-mando-precios-energia/blob/main/docs/METODOLOGIA.md · Cuadro de mando: https://pablopardopazosgestan.github.io/cuadro-mando-precios-energia/
